Workbook
Name Slicer_Type: #N/A
Name Slicer_Type1: #N/A

Sheet DASHBOARD

Sheet Analysis
B2: Automated | C2: 1135 | D2: 1135 | E2: 1126 | F2: 1019 | G2: 853 | H2: 767 | K2: AUTOMATED FUNDERS
B3: % Change | D3: =SUM(D2-C2)/C2 -> 0 | E3: =SUM(E2-D2)/D2 -> -0.0079295154 | F3: =SUM(F2-E2)/E2 -> -0.095026643 | G3: =SUM(G2-F2)/F2 -> -0.16290481 | H3: =SUM(H2-G2)/G2 -> -0.10082063 | K3: WORK Most Automated
B4: Type | C4: 2019-20 | D4: 2020-21 | E4: 2021-22 | F4: 2022-23 | G4: 2023-24 | H4: 2024-25 | K4: # | L4: 2019-20 | M4: 2020-21 | N4: 2021-22 | O4: 2022-23 | P4: 2023-24 | Q4: 2024-25
B5: Work | C5: 652 | D5: 557 | E5: 652 | F5: 664 | G5: 575 | H5: 533 | K5: 1 | L5: Kennedy Trust for Rheumatology Research | M5: Kennedy Trust for Rheumatology Research | N5: Kennedy Trust for Rheumatology Research | O5: Kennedy Trust for Rheumatology Research | P5: Kennedy Trust for Rheumatology Research | Q5: University College London
B6: % Change | D6: =SUM(D5-C5)/C5 -> -0.14570552 | E6: =SUM(E5-D5)/D5 -> 0.17055655 | F6: =SUM(F5-E5)/E5 -> 0.018404908 | G6: =SUM(G5-F5)/F5 -> -0.13403614 | H6: =SUM(H5-G5)/G5 -> -0.073043478 | K6: 2 | L6: University of Cambridge | M6: Versus Arthritis | N6: Versus Arthritis | O6: Versus Arthritis | P6: Imperial College | Q6: Imperial College
B7: Profiled | C7: 377 | D7: 404 | E7: 377 | F7: 285 | G7: 210 | H7: 179 | K7: 3 | L7: Versus Arthritis | M7: University of Cambridge | N7: University of Cambridge | O7: Oxford University Hospitals NHS Foundation Trust | P7: Versus Arthritis | Q7: Oxford University Hospitals NHS Foundation Trust
B8: % Change | D8: =SUM(D7-C7)/C7 -> 0.071618037 | E8: =SUM(E7-D7)/D7 -> -0.066831683 | F8: =SUM(F7-E7)/E7 -> -0.24403183 | G8: =SUM(G7-F7)/F7 -> -0.26315789 | H8: =SUM(H7-G7)/G7 -> -0.14761905 | K8: 4 | L8: University of York | M8: University of Leeds | N8: Royal College of Art | O8: University Hospital Southampton NHS Foundation Trust | P8: University of Liverpool | Q8: University Court of the University of Edinburgh
B9: Milestone | C9: 106 | D9: 174 | E9: 97 | F9: 70 | G9: 68 | H9: 55 | K9: 5 | L9: University of Southampton | M9: University College London | N9: Oxford University Hospitals NHS Foundation Trust | O9: University of Cambridge | P9: Oxford University Hospitals NHS Foundation Trust | Q9: University of Birmingham
B10: % Change | D10: =SUM(D9-C9)/C9 -> 0.64150943 | E10: =SUM(E9-D9)/D9 -> -0.44252874 | F10: =SUM(F9-E9)/E9 -> -0.27835052 | G10: =SUM(G9-F9)/F9 -> -0.028571429 | H10: =SUM(H9-G9)/G9 -> -0.19117647
K11: PROFILED Most Automated
K12: # | L12: 2019-20 | M12: 2020-21 | N12: 2021-22 | O12: 2022-23 | P12: 2023-24 | Q12: 2024-25
K13: 1 | L13: National Instititute for Health Research | M13: Medical Research Council | N13: Medical Research Council | O13: Novo Nordisk A/S | P13: Medical Research Council | Q13: Breakthrough Prize Foundation
K14: 2 | L14: Medical Research Council | M14: Oxford University Hospitals NHS Foundation Trust | N14: Novo Nordisk A/S | O14: Podium Analytics | P14: National Philanthropic Trust | Q14: Medical Research Council
K15: 3 | L15: AWE plc | M15: Support for the Sick Newborn and their Parents | N15: AstraZeneca UK Ltd | O15: Medical Research Council | P15: Novo Nordisk A/S | Q15: UK Biobank
K16: 4 | L16: M Suare Lasers Ltd | M16: AWE plc | N16: Janssen Research & Development, LLC | O16: AstraZeneca UK Ltd | P16: AstraZeneca UK Ltd | Q16: Podium Analytics
K17: 5 | L17: Healthcare Quality Improvement Partnership | M17: National Instititute for Health Research | N17: Wellcome Trust Sanger Institute | O17: UK Biobank | P17: Podium Analytics | Q17: Man Investments Ltd
K19: MILESTONE Most Automated
K20: # | L20: 2019-20 | M20: 2020-21 | N20: 2021-22 | O20: 2022-23 | P20: 2023-24 | Q20: 2024-25
K21: 1 | L21: Celgene Corporation | M21: Celgene Corporation | N21: Celgene Corporation | O21: Celgene Corporation | P21: Merck Sharp & Dohme Ltd
K22: 2 | L22: Department for Education | M22: DSTL | N22: Immunocore Ltd | O22: Janssen Research & Development, LLC | P22: Celgene Corporation
K23: 3 | L23: Pharmo Institute N.V. | M23: Kennedy Institute of Rheumatology | N23: Guangzhou Patronus Biotechnology Co. Ltd | O23: F Hoffmann-La Roche Ltd | P23: MCM Vaccine B.V.
K24: 4 | L24: Met Office | M24: Celgene International Sarl | N24: MCM Vaccine B.V. | O24: Merck KGaA | P24: Beijing Institute of Collaborative Innovation
K25: 5 | L25: Education Endowment Foundation | M25: Oxford University Hospitals NHS Foundation Trust | N25: Janssen Research & Development, LLC | O25: Eli Lilly and Company Ltd | P25: Heptares Therapeutics Limited
K27: AUTOMATED DEPARTMENTS
K28: WORK Most Automated
K29: # | L29: 2019-20 | M29: 2020-21 | N29: 2021-22 | O29: 2022-23 | P29: 2023-24 | Q29: 2024-25
K30: 1 | L30: Kennedy Institute of Rheumatology | M30: Kennedy Institute of Rheumatology | N30: Kennedy Institute of Rheumatology | O30: Kennedy Institute of Rheumatology | P30: Kennedy Institute of Rheumatology | Q30: Engineering Science
K31: 2 | L31: Botnar | M31: Botnar | N31: Botnar | O31: Paediatrics | P31: Paediatrics | Q31: Primary Care Health Sciences
B32: TOTAL INVOICES | C32: 0 | D32: 0 | E32: 10574 | F32: 13692 | G32: 11636 | H32: 11159 | K32: 3 | L32: Engineering Science | M32: Neurosciences | N32: Engineering Science | O32: Botnar | P32: Neurosciences | Q32: Biochemistry
B33: Cash Matching | C33: 2019-20 | D33: 2020-21 | E33: 2021-22 | F33: 2022-23 | G33: 2023-24 | H33: 2024-25 | K33: 4 | L33: Materials | M33: Engineering Science | N33: RDM Clinical Laboratory Sciences | O33: Neurosciences | P33: Tropical Medicine | Q33: Paediatrics
B34: Research Councils | C34: 0 | D34: 0 | E34: 1216 | F34: 1846 | G34: 2070 | H34: 1730 | K34: 5 | L34: Primary Care Health Sciences | M34: RDM Clinical Laboratory Sciences | N34: Neurosciences | O34: Materials | P34: Physical & Theoretical Chemistry | Q34: Neurosciences
B35: Department of Health | C35: 0 | D35: 0 | E35: 341 | F35: 593 | G35: 102 | H35: 488
B36: British Academy | C36: 0 | D36: 0 | E36: 275 | F36: 207 | G36: 144 | H36: 186 | K36: PROFILED Most Automated
B37: Royal Society | C37: 0 | D37: 0 | E37: 216 | F37: 316 | G37: 166 | H37: 244 | K37: # | L37: 2019-20 | M37: 2020-21 | N37: 2021-22 | O37: 2022-23 | P37: 2023-24 | Q37: 2024-25
B38: CRUK | C38: 0 | D38: 0 | E38: 141 | F38: 243 | G38: 297 | H38: 204 | K38: 1 | L38: Neurosciences | M38: Primary Care Health Sciences | N38: Clinical Trial Service Unit | O38: Clinical Trial Service Unit | P38: Clinical Trial Service Unit | Q38: Astrophysics
B39: Leverhulme | C39: 0 | D39: 0 | E39: 48 | F39: 154 | G39: 130 | H39: 165 | K39: 2 | L39: Department of Oncology | M39: Engineering Science | N39: Paediatrics | O39: Engineering Science | P39: RDM Investigative Medicine | Q39: Engineering Science
B40: Royal Academy of Engineering | C40: 0 | D40: 0 | E40: 23 | F40: 65 | G40: 24 | H40: 84 | K40: 3 | L40: Engineering Science | M40: Paediatrics | N40: Neurosciences | O40: Paediatrics | P40: Engineering Science | Q40: Clinical Trial Service Unit
B41: Academy of Medical Sciences | C41: 0 | D41: 0 | E41: 3 | F41: 15 | G41: 0 | H41: 18 | K41: 4 | L41: Clinical Trial Service Unit | M41: Neurosciences | N41: Department of Oncology | O41: Neurosciences | P41: Neurosciences | Q41: RDM Investigative Medicine
B42: Automated | C42: =C2 -> 1135 | D42: =D2 -> 1135 | E42: =E2 -> 1126 | F42: =F2 -> 1019 | G42: =G2 -> 853 | H42: =H2 -> 767 | K42: 5 | L42: Psychiatry | M42: Nuffield Department of Clinical Medicine | N42: Engineering Science | O42: Target Discovery Institute | P42: Paediatrics | Q42: Neurosciences
B43: Automated % | E43: =E42/SUM(E42+E44) -> 0.13548309 | F43: =F42/SUM(F42+F44) -> 0.099385546 | G43: =G42/SUM(G42+G44) -> 0.09801218 | H43: =H42/SUM(H42+H44) -> 0.09539801
B44: Day-to-Day invoices | E44: =E32-SUM(E34:E42) -> 7185 | F44: =F32-SUM(F34:F42) -> 9234 | G44: =G32-SUM(G34:G42) -> 7850 | H44: =H32-SUM(H34:H42) -> 7273 | K44: MILESTONE Most Automated
K45: # | L45: 2019-20 | M45: 2020-21 | N45: 2021-22 | O45: 2022-23 | P45: 2023-24 | Q45: 2024-25
B46: Milestones Enquired | F46: =60+67+65+49+42+66+49+53+59+50+43+46 -> 649 | G46: =35+39+57+51+39+58+44+12+51+45+41+32 -> 504 | H46: =44+40+52+41+44+26+39+31+37+3+30+32 -> 419 | K46: 1 | L46: Department for Education | M46: Neurosciences | N46: Department of Oncology | O46: Kennedy Institute of Rheumatology | P46: Engineering Science
B47: Conversion rate | F47: =F9/F46 -> 0.10785824 | G47: =G9/G46 -> 0.13492063 | H47: =H9/H46 -> 0.13126492 | K47: 2 | L47: Nuffield Department of Clinical Medicine | M47: Department of Oncology | N47: Kennedy Institute of Rheumatology | O47: Engineering Science | P47: Neurosciences
K48: 3 | L48: Tropical Medicine | M48: Engineering Science | N48: Engineering Science | O48: Neurosciences | P48: Pharmacology
B49: Analysis | K49: 4 | L49: Kennedy Institute of Rheumatology | M49: Kennedy Institute of Rheumatology | N49: Paediatrics | O49: RDM Clinical Laboratory Sciences | P49: Paediatrics
B50: All numbers down significantly | K50: 5 | L50: Botnar | M50: Nuffield Department of Clinical Medicine | N50: Biochemistry | O50: Environmental Change Institute | P50: RDM Investigative Medicine
B51: Billing becoming more complex
B52: Funder terms getting tighter, fewer projects eligible for Automation
B53: Introduction of more portals means less Automation ability
B54: Automated invoices 10% for 3 years now so while it's declining, invoicing is as a whole.
B56: Conclusions/Next steps
B57: How to expand Automation. AI?
B58: New customer templates to include transaction listing - will open up opportunity
B59: Worked hard on EngSci projects to get more Automated and it paid off

Sheet All Invoices
A1: ALL INVOICES | M1: DEPT FREQUENCY | R1: DEPT FREQUENCY | Z1: TOTAL FIGURES
A2: ID | B2: Month | C2: Dept | D2: Project No | E2: Paying | F2: Non-Paying | G2: Invoice Amount | H2: Invoice No | I2: Type | J2: Outstanding | K2: Paid | M2: Sum of ID | N2: Column Labels
A3: 1 | B3: 45870 | C3: =LEFT(Table1[[#This Row],[Project No]],2) -> AC | D3: ACR01720 | E3: Orfonyx Bio Ltd | F3: Orfonyx Bio Ltd | G3: 99999.79 | H3: 210165056 | I3: PROFILED | J3: =SUMIF(OpenInvoices!C:C,Table1[[#This Row],[Invoice No]],OpenInvoices!N:N) -> 0 | K3: =IF(Table1[[#This Row],[Outstanding]]=0,Table1[[#This Row],[Invoice Amount]],Table1[[#This Row],[Outstanding]]-Table1[[#This Row],[Invoice Amount]]) -> 99999.79 | M3: Row Labels | N3: MILESTONE | O3: PROFILED | P3: WORK | R3: # | S3: Dept | T3: Milestone | U3: Dept | V3: Profiled | W3: Dept | X3: Work | Z3: Total Invoices | AA3: =COUNT(Table1[ID]) -> 452
A4: 1 | B4: 45870 | C4: =LEFT(Table1[[#This Row],[Project No]],2) -> BZ | D4: BZR06920 | E4: Fund for Cures UK Ltd | F4: Fund for Cures UK Ltd | G4: 139750 | H4: 210165057 | I4: PROFILED | J4: =SUMIF(OpenInvoices!C:C,Table1[[#This Row],[Invoice No]],OpenInvoices!N:N) -> 0 | K4: =IF(Table1[[#This Row],[Outstanding]]=0,Table1[[#This Row],[Invoice Amount]],Table1[[#This Row],[Outstanding]]-Table1[[#This Row],[Invoice Amount]]) -> 139750 | M4: BZ | N4: 1 | O4: 13 | P4: 39 | R4: 1 | S4: =_xlfn.XLOOKUP(T4,N:N,M:M) -> DF | T4: =LARGE(N:N,ROW(T4)-ROW(T$3)) -> 6 | U4: =_xlfn.XLOOKUP(V4,O:O,M:M) -> DF | V4: =LARGE(O:O,ROW(V4)-ROW(V$3)) -> 19 | W4: =_xlfn.XLOOKUP(X4,P:P,M:M) -> BZ | X4: =LARGE(P:P,ROW(W4)-ROW(W$3)) -> 39 | Z4: Total Amount | AA4: =SUM(Table1[Invoice Amount]) -> 27086115
A5: 1 | B5: 45870 | C5: =LEFT(Table1[[#This Row],[Project No]],2) -> CD | D5: CDR01580 | E5: Paradifference Foundation | F5: Paradifference Foundation | G5: 178436.41 | H5: 210165058 | I5: PROFILED | J5: =SUMIF(OpenInvoices!C:C,Table1[[#This Row],[Invoice No]],OpenInvoices!N:N) -> 0 | K5: =IF(Table1[[#This Row],[Outstanding]]=0,Table1[[#This Row],[Invoice Amount]],Table1[[#This Row],[Outstanding]]-Table1[[#This Row],[Invoice Amount]]) -> 178436.41 | M5: DF | N5: 6 | O5: 19 | P5: 24 | R5: 2 | S5: =_xlfn.SINGLE(_xlfn.XLOOKUP(T5,N:N,M:M)) -> CB | T5: =LARGE(N:N,ROW(T5)-ROW(T$3)) -> 2 | U5: =_xlfn.SINGLE(_xlfn.XLOOKUP(V5,O:O,M:M)) -> HF | V5: =LARGE(O:O,ROW(V5)-ROW(V$3)) -> 14 | W5: =_xlfn.SINGLE(_xlfn.XLOOKUP(X5,P:P,M:M)) -> HM | X5: =LARGE(P:P,ROW(W5)-ROW(W$3)) -> 26
A6: 1 | B6: 45870 | C6: =LEFT(Table1[[#This Row],[Project No]],2) -> CW | D6: CWR00230 | E6: Drugs for Neglected Diseases Initiative | F6: Drugs for Neglected Diseases Initiative | G6: 84000 | H6: 210165059 | I6: PROFILED | J6: =SUMIF(OpenInvoices!C:C,Table1[[#This Row],[Invoice No]],OpenInvoices!N:N) -> 0 | K6: =IF(Table1[[#This Row],[Outstanding]]=0,Table1[[#This Row],[Invoice Amount]],Table1[[#This Row],[Outstanding]]-Table1[[#This Row],[Invoice Amount]]) -> 84000 | M6: HM | O6: 4 | P6: 26 | R6: 3 | S6: =_xlfn.SINGLE(_xlfn.XLOOKUP(T6,N:N,M:M)) -> CB | T6: =LARGE(N:N,ROW(T6)-ROW(T$3)) -> 2 | U6: =_xlfn.SINGLE(_xlfn.XLOOKUP(V6,O:O,M:M)) -> BZ | V6: =LARGE(O:O,ROW(V6)-ROW(V$3)) -> 13 | W6: =_xlfn.SINGLE(_xlfn.XLOOKUP(X6,P:P,M:M)) -> DF | X6: =LARGE(P:P,ROW(W6)-ROW(W$3)) -> 24 | Z6: Milestone | AA6: =COUNTIF(Table1[Type],Z6) -> 23 | AB6: =SUMIF(Table1[Type],Z6,Table1[Invoice Amount]) -> 2958243.7
A7: 1 | B7: 45870 | C7: =LEFT(Table1[[#This Row],[Project No]],2) -> DF | D7: DFR08401 | E7: Pennine Care NHS Foundation Trust | F7: National Institute for Health Research | G7: 5972.34 | H7: 210165060 | I7: PROFILED | J7: =SUMIF(OpenInvoices!C:C,Table1[[#This Row],[Invoice No]],OpenInvoices!N:N) -> 0 | K7: =IF(Table1[[#This Row],[Outstanding]]=0,Table1[[#This Row],[Invoice Amount]],Table1[[#This Row],[Outstanding]]-Table1[[#This Row],[Invoice Amount]]) -> 5972.34 | M7: HF | N7: 1 | O7: 14 | P7: 14 | R7: 4 | S7: =_xlfn.XLOOKUP(T7,N:N,M:M) -> BZ | T7: =LARGE(N:N,ROW(T7)-ROW(T$3)) -> 1 | U7: =_xlfn.SINGLE(_xlfn.XLOOKUP(V7,O:O,M:M)) -> H7 | V7: =LARGE(O:O,ROW(V7)-ROW(V$3)) -> 10 | W7: =_xlfn.SINGLE(_xlfn.XLOOKUP(X7,P:P,M:M)) -> HF | X7: =LARGE(P:P,ROW(W7)-ROW(W$3)) -> 14 | Z7: Profiled | AA7: =COUNTIF(Table1[Type],Z7) -> 125 | AB7: =SUMIF(Table1[Type],Z7,Table1[Invoice Amount]) -> 16340215
A8: 1 | B8: 45870 | C8: =LEFT(Table1[[#This Row],[Project No]],2) -> DF | D8: DFR10800 | E8: National Centre for the Replacement, Refinement and Reduction of Animals in research (NC3RS) | F8: National Centre for the Replacement, Refinement and Reduction of Animals in research (NC3RS) | G8: 22445.47 | H8: 210165061 | I8: PROFILED | J8: =SUMIF(OpenInvoices!C:C,Table1[[#This Row],[Invoice No]],OpenInvoices!N:N) -> 0 | K8: =IF(Table1[[#This Row],[Outstanding]]=0,Table1[[#This Row],[Invoice Amount]],Table1[[#This Row],[Outstanding]]-Table1[[#This Row],[Invoice Amount]]) -> 22445.47 | M8: HJ | O8: 5 | P8: 7 | R8: 5 | S8: =_xlfn.SINGLE(_xlfn.XLOOKUP(T8,N:N,M:M)) -> BZ | T8: =LARGE(N:N,ROW(T8)-ROW(T$3)) -> 1 | U8: =_xlfn.SINGLE(_xlfn.XLOOKUP(V8,O:O,M:M)) -> HJ | V8: =LARGE(O:O,ROW(V8)-ROW(V$3)) -> 5 | W8: =_xlfn.SINGLE(_xlfn.XLOOKUP(X8,P:P,M:M)) -> HQ | X8: =LARGE(P:P,ROW(W8)-ROW(W$3)) -> 12 | Z8: Work | AA8: =COUNTIF(Table1[Type],Z8) -> 304 | AB8: =SUMIF(Table1[Type],Z8,Table1[Invoice Amount]) -> 7787656.3
A9: 1 | B9: 45870 | C9: =LEFT(Table1[[#This Row],[Project No]],2) -> DM | D9: DMR02240 | E9: Man Investments Ltd | F9: Man Investments Ltd | G9: 305000 | H9: 210165062 | I9: PROFILED | J9: =SUMIF(OpenInvoices!C:C,Table1[[#This Row],[Invoice No]],OpenInvoices!N:N) -> 0 | K9: =IF(Table1[[#This Row],[Outstanding]]=0,Table1[[#This Row],[Invoice Amount]],Table1[[#This Row],[Outstanding]]-Table1[[#This Row],[Invoice Amount]]) -> 305000 | M9: HQ | P9: 12
A10: 1 | B10: 45870 | C10: =LEFT(Table1[[#This Row],[Project No]],2) -> DN | D10: DNR01320 | E10: Oxford Transplant Foundation | F10: Oxford Transplant Foundation | G10: 10000 | H10: 210165063 | I10: PROFILED | J10: =SUMIF(OpenInvoices!C:C,Table1[[#This Row],[Invoice No]],OpenInvoices!N:N) -> 0 | K10: =IF(Table1[[#This Row],[Outstanding]]=0,Table1[[#This Row],[Invoice Amount]],Table1[[#This Row],[Outstanding]]-Table1[[#This Row],[Invoice Amount]]) -> 10000 | M10: AV | P10: 12
A11: 1 | B11: 45870 | C11: =LEFT(Table1[[#This Row],[Project No]],2) -> EP | D11: EPR02280 | E11: Oxford Transplant Foundation | F11: Oxford Transplant Foundation | G11: 9950 | H11: 210165064 | I11: PROFILED | J11: =SUMIF(OpenInvoices!C:C,Table1[[#This Row],[Invoice No]],OpenInvoices!N:N) -> 0 | K11: =IF(Table1[[#This Row],[Outstanding]]=0,Table1[[#This Row],[Invoice Amount]],Table1[[#This Row],[Outstanding]]-Table1[[#This Row],[Invoice Amount]]) -> 9950 | M11: CB | N11: 2 | O11: 1 | P11: 8
A12: 1 | B12: 45870 | C12: =LEFT(Table1[[#This Row],[Project No]],2) -> H7 | D12: H7R01210 | E12: Diabetes UK | F12: Diabetes UK | G12: 49255.11 | H12: 210165065 | I12: PROFILED | J12: =SUMIF(OpenInvoices!C:C,Table1[[#This Row],[Invoice No]],OpenInvoices!N:N) -> 0 | K12: =IF(Table1[[#This Row],[Outstanding]]=0,Table1[[#This Row],[Invoice Amount]],Table1[[#This Row],[Outstanding]]-Table1[[#This Row],[Invoice Amount]]) -> 49255.11 | M12: H7 | N12: 1 | O12: 10
A13: 1 | B13: 45870 | C13: =LEFT(Table1[[#This Row],[Project No]],2) -> H7 | D13: H7R01280 | E13: Parker-Hannifin Corporation | F13: Parker-Hannifin Corporation | G13: 1080000 | H13: 210154155 | I13: MILESTONE | J13: =SUMIF(OpenInvoices!C:C,Table1[[#This Row],[Invoice No]],OpenInvoices!N:N) -> 0 | K13: =IF(Table1[[#This Row],[Outstanding]]=0,Table1[[#This Row],[Invoice Amount]],Table1[[#This Row],[Outstanding]]-Table1[[#This Row],[Invoice Amount]]) -> 1080000 | M13: DJ | P13: 11
A14: 1 | B14: 45901 | C14: =LEFT(Table1[[#This Row],[Project No]],2) -> AC | D14: ACR01720 | E14: Natural State Ltd | F14: Natural State Ltd | G14: 76907.54 | H14: 210165718 | I14: PROFILED | J14: =SUMIF(OpenInvoices!C:C,Table1[[#This Row],[Invoice No]],OpenInvoices!N:N) -> 0 | K14: =IF(Table1[[#This Row],[Outstanding]]=0,Table1[[#This Row],[Invoice Amount]],Table1[[#This Row],[Outstanding]]-Table1[[#This Row],[Invoice Amount]]) -> 76907.54 | M14: H4 | N14: 1 | O14: 2 | P14: 7
A15: 1 | B15: 45901 | C15: =LEFT(Table1[[#This Row],[Project No]],2) -> BZ | D15: BZR06920 | E15: Pennine Care NHS Foundation Trust | F15: National Institute for Health Research | G15: 2066.18 | H15: 210165719 | I15: PROFILED | J15: =SUMIF(OpenInvoices!C:C,Table1[[#This Row],[Invoice No]],OpenInvoices!N:N) -> 0 | K15: =IF(Table1[[#This Row],[Outstanding]]=0,Table1[[#This Row],[Invoice Amount]],Table1[[#This Row],[Outstanding]]-Table1[[#This Row],[Invoice Amount]]) -> 2066.18 | M15: AZ | N15: 1 | O15: 4 | P15: 5
A16: 1 | B16: 45901 | C16: =LEFT(Table1[[#This Row],[Project No]],2) -> CD | D16: CDR01580 | E16: German Historical Institute in Rome | F16: Max Weber Foundation | G16: 60000 | H16: 210165720 | I16: PROFILED | J16: =SUMIF(OpenInvoices!C:C,Table1[[#This Row],[Invoice No]],OpenInvoices!N:N) -> 0 | K16: =IF(Table1[[#This Row],[Outstanding]]=0,Table1[[#This Row],[Invoice Amount]],Table1[[#This Row],[Outstanding]]-Table1[[#This Row],[Invoice Amount]]) -> 60000 | M16: HB | N16: 2 | P16: 8
A17: 1 | B17: 45901 | C17: =LEFT(Table1[[#This Row],[Project No]],2) -> CW | D17: CWR00230 | E17: Iuvantium Limited | F17: Iuvantium Limited | G17: 8457 | H17: 210165721 | I17: PROFILED | J17: =SUMIF(OpenInvoices!C:C,Table1[[#This Row],[Invoice No]],OpenInvoices!N:N) -> 0 | K17: =IF(Table1[[#This Row],[Outstanding]]=0,Table1[[#This Row],[Invoice Amount]],Table1[[#This Row],[Outstanding]]-Table1[[#This Row],[Invoice Amount]]) -> 8457 | M17: BL | N17: 1 | O17: 1 | P17: 8
A18: 1 | B18: 45901 | C18: =LEFT(Table1[[#This Row],[Project No]],2) -> DF | D18: DFR08401 | E18: AWE Plc | F18: AWE Plc | G18: 3750.13 | H18: 210165722 | I18: PROFILED | J18: =SUMIF(OpenInvoices!C:C,Table1[[#This Row],[Invoice No]],OpenInvoices!N:N) -> 0 | K18: =IF(Table1[[#This Row],[Outstanding]]=0,Table1[[#This Row],[Invoice Amount]],Table1[[#This Row],[Outstanding]]-Table1[[#This Row],[Invoice Amount]]) -> 3750.13 | M18: B9 | O18: 1 | P18: 7
A19: 1 | B19: 45901 | C19: =LEFT(Table1[[#This Row],[Project No]],2) -> DF | D19: DFR10800 | E19: Toyota Motor Europe NV/SA | F19: Toyota Motor Europe NV/SA | G19: 82500 | H19: 210165723 | I19: PROFILED | J19: =SUMIF(OpenInvoices!C:C,Table1[[#This Row],[Invoice No]],OpenInvoices!N:N) -> 0 | K19: =IF(Table1[[#This Row],[Outstanding]]=0,Table1[[#This Row],[Invoice Amount]],Table1[[#This Row],[Outstanding]]-Table1[[#This Row],[Invoice Amount]]) -> 82500 | M19: DC | O19: 4 | P19: 4
A20: 1 | B20: 45901 | C20: =LEFT(Table1[[#This Row],[Project No]],2) -> DM | D20: DMR02240 | E20: Kodiform Therapeutics Limited | F20: Kodiform Therapeutics Limited | G20: 261704 | H20: 210165724 | I20: PROFILED | J20: =SUMIF(OpenInvoices!C:C,Table1[[#This Row],[Invoice No]],OpenInvoices!N:N) -> 0 | K20: =IF(Table1[[#This Row],[Outstanding]]=0,Table1[[#This Row],[Invoice Amount]],Table1[[#This Row],[Outstanding]]-Table1[[#This Row],[Invoice Amount]]) -> 261704 | M20: AL | P20: 7
A21: 1 | B21: 45901 | C21: =LEFT(Table1[[#This Row],[Project No]],2) -> DN | D21: DNR01320 | E21: Omass Therapeutics Ltd | F21: Omass Therapeutics Ltd | G21: 42264.42 | H21: 210165725 | I21: PROFILED | J21: =SUMIF(OpenInvoices!C:C,Table1[[#This Row],[Invoice No]],OpenInvoices!N:N) -> 0 | K21: =IF(Table1[[#This Row],[Outstanding]]=0,Table1[[#This Row],[Invoice Amount]],Table1[[#This Row],[Outstanding]]-Table1[[#This Row],[Invoice Amount]]) -> 42264.42 | M21: DB | P21: 7
A22: 1 | B22: 45901 | C22: =LEFT(Table1[[#This Row],[Project No]],2) -> EP | D22: EPR02280 | E22: Cardiff Metropolitan University | F22: Welsh Government | G22: 5750.67 | H22: 210165726 | I22: PROFILED | J22: =SUMIF(OpenInvoices!C:C,Table1[[#This Row],[Invoice No]],OpenInvoices!N:N) -> 0 | K22: =IF(Table1[[#This Row],[Outstanding]]=0,Table1[[#This Row],[Invoice Amount]],Table1[[#This Row],[Outstanding]]-Table1[[#This Row],[Invoice Amount]]) -> 5750.67 | M22: DM | O22: 2 | P22: 5
A23: 1 | B23: 45901 | C23: =LEFT(Table1[[#This Row],[Project No]],2) -> H7 | D23: H7R01210 | E23: Diabetes UK | F23: Diabetes UK | G23: 20750.99 | H23: 210165727 | I23: PROFILED | J23: =SUMIF(OpenInvoices!C:C,Table1[[#This Row],[Invoice No]],OpenInvoices!N:N) -> 0 | K23: =IF(Table1[[#This Row],[Outstanding]]=0,Table1[[#This Row],[Invoice Amount]],Table1[[#This Row],[Outstanding]]-Table1[[#This Row],[Invoice Amount]]) -> 20750.99 | M23: DG | O23: 1 | P23: 5
A24: 1 | B24: 45901 | C24: =LEFT(Table1[[#This Row],[Project No]],2) -> H7 | D24: H7R01280 | E24: Diabetes UK | F24: Diabetes UK | G24: 120455.34 | H24: 210165728 | I24: PROFILED | J24: =SUMIF(OpenInvoices!C:C,Table1[[#This Row],[Invoice No]],OpenInvoices!N:N) -> 0 | K24: =IF(Table1[[#This Row],[Outstanding]]=0,Table1[[#This Row],[Invoice Amount]],Table1[[#This Row],[Outstanding]]-Table1[[#This Row],[Invoice Amount]]) -> 120455.34 | M24: DN | O24: 2 | P24: 4
A25: 1 | B25: 45901 | C25: =LEFT(Table1[[#This Row],[Project No]],2) -> HC | D25: HCR02250 | E25: University College London | F25: Engineering & Physical Sciences Research Council | G25: 56005.66 | H25: 210165729 | I25: PROFILED | J25: =SUMIF(OpenInvoices!C:C,Table1[[#This Row],[Invoice No]],OpenInvoices!N:N) -> 0 | K25: =IF(Table1[[#This Row],[Outstanding]]=0,Table1[[#This Row],[Invoice Amount]],Table1[[#This Row],[Outstanding]]-Table1[[#This Row],[Invoice Amount]]) -> 56005.66 | M25: DH | O25: 2 | P25: 4
A26: 1 | B26: 45901 | C26: =LEFT(Table1[[#This Row],[Project No]],2) -> HF | D26: HFR02600 | E26: South Tees Hospitals NHS Foundation Trust | F26: National Institute for Health Research | G26: 940.94 | H26: 210165730 | I26: PROFILED | J26: =SUMIF(OpenInvoices!C:C,Table1[[#This Row],[Invoice No]],OpenInvoices!N:N) -> 0 | K26: =IF(Table1[[#This Row],[Outstanding]]=0,Table1[[#This Row],[Invoice Amount]],Table1[[#This Row],[Outstanding]]-Table1[[#This Row],[Invoice Amount]]) -> 940.94 | M26: CF | O26: 1 | P26: 4
A27: 1 | B27: 45901 | C27: =LEFT(Table1[[#This Row],[Project No]],2) -> HF | D27: HFR06650 | E27: National Institute for Health Research | F27: National Institute for Health Research | G27: 6794 | H27: 210165731 | I27: PROFILED | J27: =SUMIF(OpenInvoices!C:C,Table1[[#This Row],[Invoice No]],OpenInvoices!N:N) -> 0 | K27: =IF(Table1[[#This Row],[Outstanding]]=0,Table1[[#This Row],[Invoice Amount]],Table1[[#This Row],[Outstanding]]-Table1[[#This Row],[Invoice Amount]]) -> 6794 | M27: DU | O27: 3 | P27: 2
A28: 1 | B28: 45901 | C28: =LEFT(Table1[[#This Row],[Project No]],2) -> HF | D28: HFR06670 | E28: National Institute for Health Research | F28: National Institute for Health Research | G28: 69253 | H28: 210165732 | I28: PROFILED | J28: =SUMIF(OpenInvoices!C:C,Table1[[#This Row],[Invoice No]],OpenInvoices!N:N) -> 0 | K28: =IF(Table1[[#This Row],[Outstanding]]=0,Table1[[#This Row],[Invoice Amount]],Table1[[#This Row],[Outstanding]]-Table1[[#This Row],[Invoice Amount]]) -> 69253 | M28: H6 | O28: 2 | P28: 3
A29: 1 | B29: 45901 | C29: =LEFT(Table1[[#This Row],[Project No]],2) -> HJ | D29: HJR03470 | E29: Oxford Transplant Foundation | F29: Oxford Transplant Foundation | G29: 10000 | H29: 210165733 | I29: PROFILED | J29: =SUMIF(OpenInvoices!C:C,Table1[[#This Row],[Invoice No]],OpenInvoices!N:N) -> 0 | K29: =IF(Table1[[#This Row],[Outstanding]]=0,Table1[[#This Row],[Invoice Amount]],Table1[[#This Row],[Outstanding]]-Table1[[#This Row],[Invoice Amount]]) -> 10000 | M29: CY | P29: 5
A30: 1 | B30: 45901 | C30: =LEFT(Table1[[#This Row],[Project No]],2) -> HJ | D30: HJR03480 | E30: Oxford Transplant Foundation | F30: Oxford Transplant Foundation | G30: 9621 | H30: 210165734 | I30: PROFILED | J30: =SUMIF(OpenInvoices!C:C,Table1[[#This Row],[Invoice No]],OpenInvoices!N:N) -> 0 | K30: =IF(Table1[[#This Row],[Outstanding]]=0,Table1[[#This Row],[Invoice Amount]],Table1[[#This Row],[Outstanding]]-Table1[[#This Row],[Invoice Amount]]) -> 9621 | M30: A5 | P30: 5
A31: 1 | B31: 45901 | C31: =LEFT(Table1[[#This Row],[Project No]],2) -> LC | D31: LCR00180 | E31: Citigroup Global Markets Inc | F31: Citigroup Global Markets Inc | G31: 194959 | H31: 210165735 | I31: PROFILED | J31: =SUMIF(OpenInvoices!C:C,Table1[[#This Row],[Invoice No]],OpenInvoices!N:N) -> 0 | K31: =IF(Table1[[#This Row],[Outstanding]]=0,Table1[[#This Row],[Invoice Amount]],Table1[[#This Row],[Outstanding]]-Table1[[#This Row],[Invoice Amount]]) -> 194959 | M31: EP | N31: 1 | O31: 2 | P31: 2
A32: 1 | B32: 45901 | C32: =LEFT(Table1[[#This Row],[Project No]],2) -> BL | D32: BLR02930 | E32: Celgene Corporation | F32: Celgene Corporation | G32: 68412.34 | H32: 210166040 | I32: MILESTONE | J32: =SUMIF(OpenInvoices!C:C,Table1[[#This Row],[Invoice No]],OpenInvoices!N:N) -> 68412.34 | K32: =IF(Table1[[#This Row],[Outstanding]]=0,Table1[[#This Row],[Invoice Amount]],Table1[[#This Row],[Outstanding]]-Table1[[#This Row],[Invoice Amount]]) -> 0 | M32: HN | N32: 1 | P32: 3
A33: 1 | B33: 45901 | C33: =LEFT(Table1[[#This Row],[Project No]],2) -> BZ | D33: BZR06050 | E33: ModernaTX INC | F33: ModernaTX INC | G33: 590097.62 | H33: 210166041 | I33: MILESTONE | J33: =SUMIF(OpenInvoices!C:C,Table1[[#This Row],[Invoice No]],OpenInvoices!N:N) -> 590097.62 | K33: =IF(Table1[[#This Row],[Outstanding]]=0,Table1[[#This Row],[Invoice Amount]],Table1[[#This Row],[Outstanding]]-Table1[[#This Row],[Invoice Amount]]) -> 0 | M33: DK | O33: 1 | P33: 3
A34: 1 | B34: 45901 | C34: =LEFT(Table1[[#This Row],[Project No]],2) -> CB | D34: CBR00070 | E34: Institut de recherches en science de la sante | F34: Wellcome Trust | G34: 30600 | H34: 210166042 | I34: MILESTONE | J34: =SUMIF(OpenInvoices!C:C,Table1[[#This Row],[Invoice No]],OpenInvoices!N:N) -> 30600 | K34: =IF(Table1[[#This Row],[Outstanding]]=0,Table1[[#This Row],[Invoice Amount]],Table1[[#This Row],[Outstanding]]-Table1[[#This Row],[Invoice Amount]]) -> 0 | M34: HS | N34: 1 | O34: 3
A35: 1 | B35: 45901 | C35: =LEFT(Table1[[#This Row],[Project No]],2) -> CV | D35: CVR01340 | E35: Sexual violence research initiative (SVRI) | F35: Sexual violence research initiative (SVRI) | G35: 29739.4 | H35: 210166043 | I35: MILESTONE | J35: =SUMIF(OpenInvoices!C:C,Table1[[#This Row],[Invoice No]],OpenInvoices!N:N) -> 0 | K35: =IF(Table1[[#This Row],[Outstanding]]=0,Table1[[#This Row],[Invoice Amount]],Table1[[#This Row],[Outstanding]]-Table1[[#This Row],[Invoice Amount]]) -> 29739.4 | M35: CW | O35: 4
A36: 1 | B36: 45901 | C36: =LEFT(Table1[[#This Row],[Project No]],2) -> DF | D36: DFR09730 | E36: United Kingdom National Nuclear Laboratory Limited | F36: United Kingdom National Nuclear Laboratory Limited | G36: 36280 | H36: 210166044 | I36: MILESTONE | J36: =SUMIF(OpenInvoices!C:C,Table1[[#This Row],[Invoice No]],OpenInvoices!N:N) -> 0 | K36: =IF(Table1[[#This Row],[Outstanding]]=0,Table1[[#This Row],[Invoice Amount]],Table1[[#This Row],[Outstanding]]-Table1[[#This Row],[Invoice Amount]]) -> 36280 | M36: PS | P36: 4
A37: 1 | B37: 45901 | C37: =LEFT(Table1[[#This Row],[Project No]],2) -> DF | D37: DFR09871 | E37: Met Office | F37: Met Office | G37: 25207.52 | H37: 210166045 | I37: MILESTONE | J37: =SUMIF(OpenInvoices!C:C,Table1[[#This Row],[Invoice No]],OpenInvoices!N:N) -> 0 | K37: =IF(Table1[[#This Row],[Outstanding]]=0,Table1[[#This Row],[Invoice Amount]],Table1[[#This Row],[Outstanding]]-Table1[[#This Row],[Invoice Amount]]) -> 25207.52 | M37: CZ | O37: 1 | P37: 3
A38: 1 | B38: 45901 | C38: =LEFT(Table1[[#This Row],[Project No]],2) -> DF | D38: DFR10890 | E38: Marley Health Ltd | F38: Marley Health Ltd | G38: 138418 | H38: 210166046 | I38: MILESTONE | J38: =SUMIF(OpenInvoices!C:C,Table1[[#This Row],[Invoice No]],OpenInvoices!N:N) -> 0 | K38: =IF(Table1[[#This Row],[Outstanding]]=0,Table1[[#This Row],[Invoice Amount]],Table1[[#This Row],[Outstanding]]-Table1[[#This Row],[Invoice Amount]]) -> 138418 | M38: M3 | P38: 4
A39: 1 | B39: 45901 | C39: =LEFT(Table1[[#This Row],[Project No]],2) -> DL | D39: DLR00950 | E39: Cern | F39: Cern | G39: 35240.24 | H39: 210166047 | I39: MILESTONE | J39: =SUMIF(OpenInvoices!C:C,Table1[[#This Row],[Invoice No]],OpenInvoices!N:N) -> 0 | K39: =IF(Table1[[#This Row],[Outstanding]]=0,Table1[[#This Row],[Invoice Amount]],Table1[[#This Row],[Outstanding]]-Table1[[#This Row],[Invoice Amount]]) -> 35240.24 | M39: CS | P39: 3
A40: 1 | B40: 45901 | C40: =LEFT(Table1[[#This Row],[Project No]],2) -> EP | D40: EPR02210 | E40: Bell Foundation | F40: Bell Foundation | G40: 16930.77 | H40: 210166048 | I40: MILESTONE | J40: =SUMIF(OpenInvoices!C:C,Table1[[#This Row],[Invoice No]],OpenInvoices!N:N) -> 0 | K40: =IF(Table1[[#This Row],[Outstanding]]=0,Table1[[#This Row],[Invoice Amount]],Table1[[#This Row],[Outstanding]]-Table1[[#This Row],[Invoice Amount]]) -> 16930.77 | M40: AF | P40: 3
A41: 1 | B41: 45901 | C41: =LEFT(Table1[[#This Row],[Project No]],2) -> HB | D41: HBR05360 | E41: PSC Support | F41: PSC Support | G41: 7500 | H41: 210166049 | I41: MILESTONE | J41: =SUMIF(OpenInvoices!C:C,Table1[[#This Row],[Invoice No]],OpenInvoices!N:N) -> 7500 | K41: =IF(Table1[[#This Row],[Outstanding]]=0,Table1[[#This Row],[Invoice Amount]],Table1[[#This Row],[Outstanding]]-Table1[[#This Row],[Invoice Amount]]) -> 0 | M41: AJ | O41: 3
A42: 1 | B42: 45901 | C42: =LEFT(Table1[[#This Row],[Project No]],2) -> HS | D42: HSR01520 | E42: Celgene Corporation | F42: Celgene Corporation | G42: 55377 | H42: 210166050 | I42: MILESTONE | J42: =SUMIF(OpenInvoices!C:C,Table1[[#This Row],[Invoice No]],OpenInvoices!N:N) -> 55377 | K42: =IF(Table1[[#This Row],[Outstanding]]=0,Table1[[#This Row],[Invoice Amount]],Table1[[#This Row],[Outstanding]]-Table1[[#This Row],[Invoice Amount]]) -> 0 | M42: BW | N42: 1 | P42: 2
A43: 1 | B43: 45901 | C43: =LEFT(Table1[[#This Row],[Project No]],2) -> A4 | D43: A4R00050 | E43: Kings College London | F43: Biotechnology & Biological Sciences Research Council | G43: 1807.18 | H43: 210166234 | I43: WORK | J43: =SUMIF(OpenInvoices!C:C,Table1[[#This Row],[Invoice No]],OpenInvoices!N:N) -> 0 | K43: =IF(Table1[[#This Row],[Outstanding]]=0,Table1[[#This Row],[Invoice Amount]],Table1[[#This Row],[Outstanding]]-Table1[[#This Row],[Invoice Amount]]) -> 1807.18 | M43: BK | P43: 3
A44: 1 | B44: 45901 | C44: =LEFT(Table1[[#This Row],[Project No]],2) -> AE | D44: AER01590 | E44: University College London | F44: Economic & Social Research Council | G44: 10580.53 | H44: 210166235 | I44: WORK | J44: =SUMIF(OpenInvoices!C:C,Table1[[#This Row],[Invoice No]],OpenInvoices!N:N) -> 0 | K44: =IF(Table1[[#This Row],[Outstanding]]=0,Table1[[#This Row],[Invoice Amount]],Table1[[#This Row],[Outstanding]]-Table1[[#This Row],[Invoice Amount]]) -> 10580.53 | M44: A3 | O44: 2 | P44: 1
A45: 1 | B45: 45901 | C45: =LEFT(Table1[[#This Row],[Project No]],2) -> AF | D45: AFR01540 | E45: University of Leeds | F45: Engineering & Physical Sciences Research Council | G45: 47428 | H45: 210166236 | I45: WORK | J45: =SUMIF(OpenInvoices!C:C,Table1[[#This Row],[Invoice No]],OpenInvoices!N:N) -> 0 | K45: =IF(Table1[[#This Row],[Outstanding]]=0,Table1[[#This Row],[Invoice Amount]],Table1[[#This Row],[Outstanding]]-Table1[[#This Row],[Invoice Amount]]) -> 47428 | M45: BA | P45: 3
A46: 1 | B46: 45901 | C46: =LEFT(Table1[[#This Row],[Project No]],2) -> AL | D46: ALR02880 | E46: University Court of the University of Edinburgh | F46: Medical Research Council | G46: 63469.1 | H46: 210166237 | I46: WORK | J46: =SUMIF(OpenInvoices!C:C,Table1[[#This Row],[Invoice No]],OpenInvoices!N:N) -> 0 | K46: =IF(Table1[[#This Row],[Outstanding]]=0,Table1[[#This Row],[Invoice Amount]],Table1[[#This Row],[Outstanding]]-Table1[[#This Row],[Invoice Amount]]) -> 63469.1 | M46: BX | O46: 2 | P46: 1
A47: 1 | B47: 45901 | C47: =LEFT(Table1[[#This Row],[Project No]],2) -> AL | D47: ALR02900 | E47: Medical Research Council | F47: Medical Research Council | G47: 128506.65 | H47: 210166238 | I47: WORK | J47: =SUMIF(OpenInvoices!C:C,Table1[[#This Row],[Invoice No]],OpenInvoices!N:N) -> 0 | K47: =IF(Table1[[#This Row],[Outstanding]]=0,Table1[[#This Row],[Invoice Amount]],Table1[[#This Row],[Outstanding]]-Table1[[#This Row],[Invoice Amount]]) -> 128506.65 | M47: CV | N47: 1 | P47: 2
A48: 1 | B48: 45901 | C48: =LEFT(Table1[[#This Row],[Project No]],2) -> AP | D48: APR01060 | E48: University of Warwick | F48: Biotechnology & Biological Sciences Research Council | G48: 1549.06 | H48: 210166239 | I48: WORK | J48: =SUMIF(OpenInvoices!C:C,Table1[[#This Row],[Invoice No]],OpenInvoices!N:N) -> 0 | K48: =IF(Table1[[#This Row],[Outstanding]]=0,Table1[[#This Row],[Invoice Amount]],Table1[[#This Row],[Outstanding]]-Table1[[#This Row],[Invoice Amount]]) -> 1549.06 | M48: HE | P48: 3
A49: 1 | B49: 45901 | C49: =LEFT(Table1[[#This Row],[Project No]],2) -> AV | D49: AVR03340 | E49: Alzheimer's Society | F49: Alzheimer's Society | G49: 13768.66 | H49: 210166240 | I49: WORK | J49: =SUMIF(OpenInvoices!C:C,Table1[[#This Row],[Invoice No]],OpenInvoices!N:N) -> 0 | K49: =IF(Table1[[#This Row],[Outstanding]]=0,Table1[[#This Row],[Invoice Amount]],Table1[[#This Row],[Outstanding]]-Table1[[#This Row],[Invoice Amount]]) -> 13768.66 | M49: H5 | P49: 3
A50: 1 | B50: 45901 | C50: =LEFT(Table1[[#This Row],[Project No]],2) -> AV | D50: AVR03370 | E50: Royal Veterinary College | F50: Medical Research Council | G50: 2887.97 | H50: 210166241 | I50: WORK | J50: =SUMIF(OpenInvoices!C:C,Table1[[#This Row],[Invoice No]],OpenInvoices!N:N) -> 0 | K50: =IF(Table1[[#This Row],[Outstanding]]=0,Table1[[#This Row],[Invoice Amount]],Table1[[#This Row],[Outstanding]]-Table1[[#This Row],[Invoice Amount]]) -> 2887.97 | M50: CQ | P50: 3
A51: 1 | B51: 45901 | C51: =LEFT(Table1[[#This Row],[Project No]],2) -> BA | D51: BAR00850 | E51: University of York | F51: Economic & Social Research Council | G51: 1897.39 | H51: 210166242 | I51: WORK | J51: =SUMIF(OpenInvoices!C:C,Table1[[#This Row],[Invoice No]],OpenInvoices!N:N) -> 0 | K51: =IF(Table1[[#This Row],[Outstanding]]=0,Table1[[#This Row],[Invoice Amount]],Table1[[#This Row],[Outstanding]]-Table1[[#This Row],[Invoice Amount]]) -> 1897.39 | M51: CD | O51: 3
A52: 1 | B52: 45901 | C52: =LEFT(Table1[[#This Row],[Project No]],2) -> BK | D52: BKR02200 | E52: University of Notre Dame | F52: Office of Naval Research | G52: 26999.39 | H52: 210166243 | I52: WORK | J52: =SUMIF(OpenInvoices!C:C,Table1[[#This Row],[Invoice No]],OpenInvoices!N:N) -> 0 | K52: =IF(Table1[[#This Row],[Outstanding]]=0,Table1[[#This Row],[Invoice Amount]],Table1[[#This Row],[Outstanding]]-Table1[[#This Row],[Invoice Amount]]) -> 26999.39 | M52: AC | O52: 3
A53: 1 | B53: 45901 | C53: =LEFT(Table1[[#This Row],[Project No]],2) -> BL | D53: BLR03200 | E53: University of Nottingham | F53: Medical Research Council | G53: 24052.35 | H53: 210166245 | I53: WORK | J53: =SUMIF(OpenInvoices!C:C,Table1[[#This Row],[Invoice No]],OpenInvoices!N:N) -> 0 | K53: =IF(Table1[[#This Row],[Outstanding]]=0,Table1[[#This Row],[Invoice Amount]],Table1[[#This Row],[Outstanding]]-Table1[[#This Row],[Invoice Amount]]) -> 24052.35 | M53: CN | O53: 2
A54: 1 | B54: 45901 | C54: =LEFT(Table1[[#This Row],[Project No]],2) -> BL | D54: BLR03610 | E54: University of Leeds | F54: Natural Environment Research Council | G54: 3687.55 | H54: 210166246 | I54: WORK | J54: =SUMIF(OpenInvoices!C:C,Table1[[#This Row],[Invoice No]],OpenInvoices!N:N) -> 0 | K54: =IF(Table1[[#This Row],[Outstanding]]=0,Table1[[#This Row],[Invoice Amount]],Table1[[#This Row],[Outstanding]]-Table1[[#This Row],[Invoice Amount]]) -> 3687.55 | M54: AE | P54: 2
A55: 1 | B55: 45901 | C55: =LEFT(Table1[[#This Row],[Project No]],2) -> BL | D55: BLR03860 | E55: University of Bristol | F55: Engineering & Physical Sciences Research Council | G55: 101530.75 | H55: 210166247 | I55: WORK | J55: =SUMIF(OpenInvoices!C:C,Table1[[#This Row],[Invoice No]],OpenInvoices!N:N) -> 0 | K55: =IF(Table1[[#This Row],[Outstanding]]=0,Table1[[#This Row],[Invoice Amount]],Table1[[#This Row],[Outstanding]]-Table1[[#This Row],[Invoice Amount]]) -> 101530.75 | M55: A4 | P55: 2
A56: 1 | B56: 45901 | C56: =LEFT(Table1[[#This Row],[Project No]],2) -> BW | D56: BWR01590 | E56: University of Manchester | F56: British Heart Foundation | G56: 14205.69 | H56: 210166248 | I56: WORK | J56: =SUMIF(OpenInvoices!C:C,Table1[[#This Row],[Invoice No]],OpenInvoices!N:N) -> 0 | K56: =IF(Table1[[#This Row],[Outstanding]]=0,Table1[[#This Row],[Invoice Amount]],Table1[[#This Row],[Outstanding]]-Table1[[#This Row],[Invoice Amount]]) -> 14205.69 | M56: BV | P56: 2
A57: 1 | B57: 45901 | C57: =LEFT(Table1[[#This Row],[Project No]],2) -> BZ | D57: BZR06150 | E57: Cardiff University | F57: Welsh Government | G57: 5748.54 | H57: 210166249 | I57: WORK | J57: =SUMIF(OpenInvoices!C:C,Table1[[#This Row],[Invoice No]],OpenInvoices!N:N) -> 0 | K57: =IF(Table1[[#This Row],[Outstanding]]=0,Table1[[#This Row],[Invoice Amount]],Table1[[#This Row],[Outstanding]]-Table1[[#This Row],[Invoice Amount]]) -> 5748.54 | M57: BB | O57: 1 | P57: 1
A58: 1 | B58: 45901 | C58: =LEFT(Table1[[#This Row],[Project No]],2) -> BZ | D58: BZR06190 | E58: Leeds Beckett University | F58: National Institute for Health Research | G58: 455.44 | H58: 210166250 | I58: WORK | J58: =SUMIF(OpenInvoices!C:C,Table1[[#This Row],[Invoice No]],OpenInvoices!N:N) -> 0 | K58: =IF(Table1[[#This Row],[Outstanding]]=0,Table1[[#This Row],[Invoice Amount]],Table1[[#This Row],[Outstanding]]-Table1[[#This Row],[Invoice Amount]]) -> 455.44 | M58: AM | O58: 2
A59: 1 | B59: 45901 | C59: =LEFT(Table1[[#This Row],[Project No]],2) -> BZ | D59: BZR06870 | E59: Imperial College | F59: National Institute for Health Research | G59: 26811.41 | H59: 210166251 | I59: WORK | J59: =SUMIF(OpenInvoices!C:C,Table1[[#This Row],[Invoice No]],OpenInvoices!N:N) -> 0 | K59: =IF(Table1[[#This Row],[Outstanding]]=0,Table1[[#This Row],[Invoice Amount]],Table1[[#This Row],[Outstanding]]-Table1[[#This Row],[Invoice Amount]]) -> 26811.41 | M59: ET | P59: 2
A60: 1 | B60: 45901 | C60: =LEFT(Table1[[#This Row],[Project No]],2) -> BZ | D60: BZR06910 | E60: Northern Care Alliance NHS Foundation Trust | F60: National Institute for Health Research | G60: 3494.7 | H60: 210166252 | I60: WORK | J60: =SUMIF(OpenInvoices!C:C,Table1[[#This Row],[Invoice No]],OpenInvoices!N:N) -> 0 | K60: =IF(Table1[[#This Row],[Outstanding]]=0,Table1[[#This Row],[Invoice Amount]],Table1[[#This Row],[Outstanding]]-Table1[[#This Row],[Invoice Amount]]) -> 3494.7 | M60: LE | O60: 1
A61: 1 | B61: 45901 | C61: =LEFT(Table1[[#This Row],[Project No]],2) -> BZ | D61: BZR06940 | E61: Barts Health NHS Trust | F61: National Institute for Health Research | G61: 2173.62 | H61: 210166253 | I61: WORK | J61: =SUMIF(OpenInvoices!C:C,Table1[[#This Row],[Invoice No]],OpenInvoices!N:N) -> 0 | K61: =IF(Table1[[#This Row],[Outstanding]]=0,Table1[[#This Row],[Invoice Amount]],Table1[[#This Row],[Outstanding]]-Table1[[#This Row],[Invoice Amount]]) -> 2173.62 | M61: B5 | P61: 1
A62: 1 | B62: 45901 | C62: =LEFT(Table1[[#This Row],[Project No]],2) -> BZ | D62: BZR07000 | E62: University of York | F62: National Institute for Health Research | G62: 1550.54 | H62: 210166254 | I62: WORK | J62: =SUMIF(OpenInvoices!C:C,Table1[[#This Row],[Invoice No]],OpenInvoices!N:N) -> 0 | K62: =IF(Table1[[#This Row],[Outstanding]]=0,Table1[[#This Row],[Invoice Amount]],Table1[[#This Row],[Outstanding]]-Table1[[#This Row],[Invoice Amount]]) -> 1550.54 | M62: HC | O62: 1
A63: 1 | B63: 45901 | C63: =LEFT(Table1[[#This Row],[Project No]],2) -> BZ | D63: BZR07100 | E63: Great Western Hospitals NHS Foundation Trust | F63: Motor Neurone Disease Association | G63: 5271.58 | H63: 210166255 | I63: WORK | J63: =SUMIF(OpenInvoices!C:C,Table1[[#This Row],[Invoice No]],OpenInvoices!N:N) -> 0 | K63: =IF(Table1[[#This Row],[Outstanding]]=0,Table1[[#This Row],[Invoice Amount]],Table1[[#This Row],[Outstanding]]-Table1[[#This Row],[Invoice Amount]]) -> 5271.58 | M63: AP | P63: 1
A64: 1 | B64: 45901 | C64: =LEFT(Table1[[#This Row],[Project No]],2) -> BZ | D64: BZR07110 | E64: Tidalsense Limited | F64: National Institute for Health Research | G64: 344196.32 | H64: 210166256 | I64: WORK | J64: =SUMIF(OpenInvoices!C:C,Table1[[#This Row],[Invoice No]],OpenInvoices!N:N) -> 0 | K64: =IF(Table1[[#This Row],[Outstanding]]=0,Table1[[#This Row],[Invoice Amount]],Table1[[#This Row],[Outstanding]]-Table1[[#This Row],[Invoice Amount]]) -> 344196.32 | M64: LD | P64: 1
A65: 1 | B65: 45901 | C65: =LEFT(Table1[[#This Row],[Project No]],2) -> CB | D65: CBR00570 | E65: University of Birmingham | F65: Biotechnology & Biological Sciences Research Council | G65: 26443.55 | H65: 210166257 | I65: WORK | J65: =SUMIF(OpenInvoices!C:C,Table1[[#This Row],[Invoice No]],OpenInvoices!N:N) -> 26443.55 | K65: =IF(Table1[[#This Row],[Outstanding]]=0,Table1[[#This Row],[Invoice Amount]],Table1[[#This Row],[Outstanding]]-Table1[[#This Row],[Invoice Amount]]) -> 0 | M65: B8 | O65: 1
A66: 1 | B66: 45901 | C66: =LEFT(Table1[[#This Row],[Project No]],2) -> CB | D66: CBR00600 | E66: University of Sheffield | F66: Biotechnology & Biological Sciences Research Council | G66: 14307.66 | H66: 210166258 | I66: WORK | J66: =SUMIF(OpenInvoices!C:C,Table1[[#This Row],[Invoice No]],OpenInvoices!N:N) -> 0 | K66: =IF(Table1[[#This Row],[Outstanding]]=0,Table1[[#This Row],[Invoice Amount]],Table1[[#This Row],[Outstanding]]-Table1[[#This Row],[Invoice Amount]]) -> 14307.66 | M66: EB | P66: 1
A67: 1 | B67: 45901 | C67: =LEFT(Table1[[#This Row],[Project No]],2) -> CB | D67: CBR01050 | E67: Royal Veterinary College | F67: Biotechnology & Biological Sciences Research Council | G67: 936.71 | H67: 210166259 | I67: WORK | J67: =SUMIF(OpenInvoices!C:C,Table1[[#This Row],[Invoice No]],OpenInvoices!N:N) -> 0 | K67: =IF(Table1[[#This Row],[Outstanding]]=0,Table1[[#This Row],[Invoice Amount]],Table1[[#This Row],[Outstanding]]-Table1[[#This Row],[Invoice Amount]]) -> 936.71 | M67: AB | P67: 1
A68: 1 | B68: 45901 | C68: =LEFT(Table1[[#This Row],[Project No]],2) -> CF | D68: CFR01500 | E68: California Institute of Technology | F68: California Institute of Technology | G68: 20028.52 | H68: 210166260 | I68: WORK | J68: =SUMIF(OpenInvoices!C:C,Table1[[#This Row],[Invoice No]],OpenInvoices!N:N) -> 0 | K68: =IF(Table1[[#This Row],[Outstanding]]=0,Table1[[#This Row],[Invoice Amount]],Table1[[#This Row],[Outstanding]]-Table1[[#This Row],[Invoice Amount]]) -> 20028.52 | M68: DL | N68: 1
A69: 1 | B69: 45901 | C69: =LEFT(Table1[[#This Row],[Project No]],2) -> CY | D69: CYR00620 | E69: University of Sheffield | F69: Economic & Social Research Council | G69: 28900.04 | H69: 210166261 | I69: WORK | J69: =SUMIF(OpenInvoices!C:C,Table1[[#This Row],[Invoice No]],OpenInvoices!N:N) -> 0 | K69: =IF(Table1[[#This Row],[Outstanding]]=0,Table1[[#This Row],[Invoice Amount]],Table1[[#This Row],[Outstanding]]-Table1[[#This Row],[Invoice Amount]]) -> 28900.04 | M69: LC | O69: 1
A70: 1 | B70: 45901 | C70: =LEFT(Table1[[#This Row],[Project No]],2) -> CZ | D70: CZR01280 | E70: University of Sheffield | F70: Economic & Social Research Council | G70: 17258.4 | H70: 210166262 | I70: WORK | J70: =SUMIF(OpenInvoices!C:C,Table1[[#This Row],[Invoice No]],OpenInvoices!N:N) -> 0 | K70: =IF(Table1[[#This Row],[Outstanding]]=0,Table1[[#This Row],[Invoice Amount]],Table1[[#This Row],[Outstanding]]-Table1[[#This Row],[Invoice Amount]]) -> 17258.4 | M70: MQ | N70: 1
A71: 1 | B71: 45901 | C71: =LEFT(Table1[[#This Row],[Project No]],2) -> DC | D71: DCR01310 | E71: University of Reading | F71: Natural Environment Research Council | G71: 30668.12 | H71: 210166263 | I71: WORK | J71: =SUMIF(OpenInvoices!C:C,Table1[[#This Row],[Invoice No]],OpenInvoices!N:N) -> 0 | K71: =IF(Table1[[#This Row],[Outstanding]]=0,Table1[[#This Row],[Invoice Amount]],Table1[[#This Row],[Outstanding]]-Table1[[#This Row],[Invoice Amount]]) -> 30668.12 | M71: DQ | O71: 1
A72: 1 | B72: 45901 | C72: =LEFT(Table1[[#This Row],[Project No]],2) -> DF | D72: DFR10720 | E72: Cardiff University | F72: Wellcome Trust | G72: 4041.25 | H72: 210166264 | I72: WORK | J72: =SUMIF(OpenInvoices!C:C,Table1[[#This Row],[Invoice No]],OpenInvoices!N:N) -> 4041.25 | K72: =IF(Table1[[#This Row],[Outstanding]]=0,Table1[[#This Row],[Invoice Amount]],Table1[[#This Row],[Outstanding]]-Table1[[#This Row],[Invoice Amount]]) -> 0 | M72: DR | P72: 1
A73: 1 | B73: 45901 | C73: =LEFT(Table1[[#This Row],[Project No]],2) -> DF | D73: DFR10780 | E73: University College London | F73: National Institute for Health Research | G73: 35190.35 | H73: 210166265 | I73: WORK | J73: =SUMIF(OpenInvoices!C:C,Table1[[#This Row],[Invoice No]],OpenInvoices!N:N) -> 0 | K73: =IF(Table1[[#This Row],[Outstanding]]=0,Table1[[#This Row],[Invoice Amount]],Table1[[#This Row],[Outstanding]]-Table1[[#This Row],[Invoice Amount]]) -> 35190.35
A74: 1 | B74: 45901 | C74: =LEFT(Table1[[#This Row],[Project No]],2) -> DF | D74: DFR10900 | E74: University of Leeds | F74: Natural Environment Research Council | G74: 57763.81 | H74: 210166266 | I74: WORK | J74: =SUMIF(OpenInvoices!C:C,Table1[[#This Row],[Invoice No]],OpenInvoices!N:N) -> 0 | K74: =IF(Table1[[#This Row],[Outstanding]]=0,Table1[[#This Row],[Invoice Amount]],Table1[[#This Row],[Outstanding]]-Table1[[#This Row],[Invoice Amount]]) -> 57763.81
A75: 1 | B75: 45901 | C75: =LEFT(Table1[[#This Row],[Project No]],2) -> DF | D75: DFR10940 | E75: University of Bath | F75: Engineering & Physical Sciences Research Council | G75: 2827.53 | H75: 210166267 | I75: WORK | J75: =SUMIF(OpenInvoices!C:C,Table1[[#This Row],[Invoice No]],OpenInvoices!N:N) -> 0 | K75: =IF(Table1[[#This Row],[Outstanding]]=0,Table1[[#This Row],[Invoice Amount]],Table1[[#This Row],[Outstanding]]-Table1[[#This Row],[Invoice Amount]]) -> 2827.53
A76: 1 | B76: 45901 | C76: =LEFT(Table1[[#This Row],[Project No]],2) -> DG | D76: DGR02000 | E76: University Court of the University of Edinburgh | F76: Natural Environment Research Council | G76: 1083.1 | H76: 210166268 | I76: WORK | J76: =SUMIF(OpenInvoices!C:C,Table1[[#This Row],[Invoice No]],OpenInvoices!N:N) -> 0 | K76: =IF(Table1[[#This Row],[Outstanding]]=0,Table1[[#This Row],[Invoice Amount]],Table1[[#This Row],[Outstanding]]-Table1[[#This Row],[Invoice Amount]]) -> 1083.1
A77: 1 | B77: 45901 | C77: =LEFT(Table1[[#This Row],[Project No]],2) -> DH | D77: DHR01661 | E77: University of Liverpool | F77: Unilever UK Limited | G77: 243.7 | H77: 210166269 | I77: WORK | J77: =SUMIF(OpenInvoices!C:C,Table1[[#This Row],[Invoice No]],OpenInvoices!N:N) -> 0 | K77: =IF(Table1[[#This Row],[Outstanding]]=0,Table1[[#This Row],[Invoice Amount]],Table1[[#This Row],[Outstanding]]-Table1[[#This Row],[Invoice Amount]]) -> 243.7
A78: 1 | B78: 45901 | C78: =LEFT(Table1[[#This Row],[Project No]],2) -> DJ | D78: DJR02620 | E78: University of Exeter | F78: Engineering & Physical Sciences Research Council | G78: 22181.5 | H78: 210166270 | I78: WORK | J78: =SUMIF(OpenInvoices!C:C,Table1[[#This Row],[Invoice No]],OpenInvoices!N:N) -> 0 | K78: =IF(Table1[[#This Row],[Outstanding]]=0,Table1[[#This Row],[Invoice Amount]],Table1[[#This Row],[Outstanding]]-Table1[[#This Row],[Invoice Amount]]) -> 22181.5
A79: 1 | B79: 45901 | C79: =LEFT(Table1[[#This Row],[Project No]],2) -> DJ | D79: DJR03190 | E79: Heriot-Watt University | F79: Engineering & Physical Sciences Research Council | G79: 57740.97 | H79: 210166271 | I79: WORK | J79: =SUMIF(OpenInvoices!C:C,Table1[[#This Row],[Invoice No]],OpenInvoices!N:N) -> 0 | K79: =IF(Table1[[#This Row],[Outstanding]]=0,Table1[[#This Row],[Invoice Amount]],Table1[[#This Row],[Outstanding]]-Table1[[#This Row],[Invoice Amount]]) -> 57740.97
A80: 1 | B80: 45901 | C80: =LEFT(Table1[[#This Row],[Project No]],2) -> DK | D80: DKR01260 | E80: University of Surrey | F80: Engineering & Physical Sciences Research Council | G80: 7947.94 | H80: 210166272 | I80: WORK | J80: =SUMIF(OpenInvoices!C:C,Table1[[#This Row],[Invoice No]],OpenInvoices!N:N) -> 0 | K80: =IF(Table1[[#This Row],[Outstanding]]=0,Table1[[#This Row],[Invoice Amount]],Table1[[#This Row],[Outstanding]]-Table1[[#This Row],[Invoice Amount]]) -> 7947.94
A81: 1 | B81: 45901 | C81: =LEFT(Table1[[#This Row],[Project No]],2) -> DM | D81: DMR02180 | E81: Lancaster University | F81: Engineering & Physical Sciences Research Council | G81: 39726.56 | H81: 210166273 | I81: WORK | J81: =SUMIF(OpenInvoices!C:C,Table1[[#This Row],[Invoice No]],OpenInvoices!N:N) -> 0 | K81: =IF(Table1[[#This Row],[Outstanding]]=0,Table1[[#This Row],[Invoice Amount]],Table1[[#This Row],[Outstanding]]-Table1[[#This Row],[Invoice Amount]]) -> 39726.56
A82: 1 | B82: 45901 | C82: =LEFT(Table1[[#This Row],[Project No]],2) -> DN | D82: DNR00793 | E82: University of Bristol | F82: Engineering & Physical Sciences Research Council | G82: 41686.05 | H82: 210166274 | I82: WORK | J82: =SUMIF(OpenInvoices!C:C,Table1[[#This Row],[Invoice No]],OpenInvoices!N:N) -> 0 | K82: =IF(Table1[[#This Row],[Outstanding]]=0,Table1[[#This Row],[Invoice Amount]],Table1[[#This Row],[Outstanding]]-Table1[[#This Row],[Invoice Amount]]) -> 41686.05
A83: 1 | B83: 45901 | C83: =LEFT(Table1[[#This Row],[Project No]],2) -> DN | D83: DNR01390 | E83: Heriot-Watt University | F83: Leverhulme Trust | G83: 14348.39 | H83: 210166275 | I83: WORK | J83: =SUMIF(OpenInvoices!C:C,Table1[[#This Row],[Invoice No]],OpenInvoices!N:N) -> 0 | K83: =IF(Table1[[#This Row],[Outstanding]]=0,Table1[[#This Row],[Invoice Amount]],Table1[[#This Row],[Outstanding]]-Table1[[#This Row],[Invoice Amount]]) -> 14348.39
A84: 1 | B84: 45901 | C84: =LEFT(Table1[[#This Row],[Project No]],2) -> ET | D84: ETR00030 | E84: University College London | F84: Arts and Humanities Research Council | G84: 3638 | H84: 210166276 | I84: WORK | J84: =SUMIF(OpenInvoices!C:C,Table1[[#This Row],[Invoice No]],OpenInvoices!N:N) -> 0 | K84: =IF(Table1[[#This Row],[Outstanding]]=0,Table1[[#This Row],[Invoice Amount]],Table1[[#This Row],[Outstanding]]-Table1[[#This Row],[Invoice Amount]]) -> 3638
... A223: 1 | B223: 45962 | C223: =LEFT(Table1[[#This Row],[Project No]],2) -> M3 | D223: M3R00870 | E223: Freie Universitat Berlin | F223: Volkswagen-Stiftung | G223: 2497.3 | H223: 210168855 | I223: WORK | J223: =SUMIF(OpenInvoices!C:C,Table1[[#This Row],[Invoice No]],OpenInvoices!N:N) -> 0 | K223: =IF(Table1[[#This Row],[Outstanding]]=0,Table1[[#This Row],[Invoice Amount]],Table1[[#This Row],[Outstanding]]-Table1[[#This Row],[Invoice Amount]]) -> 2497.3
A224: 1 | B224: 45992 | C224: =LEFT(Table1[[#This Row],[Project No]],2) -> HF | D224: HFR06650 | E224: National Institute for Health Research | G224: 6794 | H224: 1210169837 | I224: PROFILED | J224: =SUMIF(OpenInvoices!C:C,Table1[[#This Row],[Invoice No]],OpenInvoices!N:N) -> 0 | K224: =IF(Table1[[#This Row],[Outstanding]]=0,Table1[[#This Row],[Invoice Amount]],Table1[[#This Row],[Outstanding]]-Table1[[#This Row],[Invoice Amount]]) -> 6794
A225: 1 | B225: 45992 | C225: =LEFT(Table1[[#This Row],[Project No]],2) -> BB | D225: BBR00270 | E225: University of Southampton | G225: 125000 | H225: 210169832 | I225: PROFILED | J225: =SUMIF(OpenInvoices!C:C,Table1[[#This Row],[Invoice No]],OpenInvoices!N:N) -> 0 | K225: =IF(Table1[[#This Row],[Outstanding]]=0,Table1[[#This Row],[Invoice Amount]],Table1[[#This Row],[Outstanding]]-Table1[[#This Row],[Invoice Amount]]) -> 125000
A226: 1 | B226: 45992 | C226: =LEFT(Table1[[#This Row],[Project No]],2) -> BZ | D226: BZR06920 | E226: Pennine Care NHS Foundation Trust | G226: 2066.18 | H226: 210169833 | I226: PROFILED | J226: =SUMIF(OpenInvoices!C:C,Table1[[#This Row],[Invoice No]],OpenInvoices!N:N) -> 2066.18 | K226: =IF(Table1[[#This Row],[Outstanding]]=0,Table1[[#This Row],[Invoice Amount]],Table1[[#This Row],[Outstanding]]-Table1[[#This Row],[Invoice Amount]]) -> 0
A227: 1 | B227: 45992 | C227: =LEFT(Table1[[#This Row],[Project No]],2) -> H7 | D227: H7R01210 | E227: Diabetes UK | G227: 20750.99 | H227: 210169834 | I227: PROFILED | J227: =SUMIF(OpenInvoices!C:C,Table1[[#This Row],[Invoice No]],OpenInvoices!N:N) -> 20750.99 | K227: =IF(Table1[[#This Row],[Outstanding]]=0,Table1[[#This Row],[Invoice Amount]],Table1[[#This Row],[Outstanding]]-Table1[[#This Row],[Invoice Amount]]) -> 0
A228: 1 | B228: 45992 | C228: =LEFT(Table1[[#This Row],[Project No]],2) -> H7 | D228: H7R01240 | E228: Diabetes UK | G228: 29645.26 | H228: 210169835 | I228: PROFILED | J228: =SUMIF(OpenInvoices!C:C,Table1[[#This Row],[Invoice No]],OpenInvoices!N:N) -> 0 | K228: =IF(Table1[[#This Row],[Outstanding]]=0,Table1[[#This Row],[Invoice Amount]],Table1[[#This Row],[Outstanding]]-Table1[[#This Row],[Invoice Amount]]) -> 29645.26
A229: 1 | B229: 45992 | C229: =LEFT(Table1[[#This Row],[Project No]],2) -> H7 | D229: H7R01280 | E229: Diabetes UK | G229: 120455.35 | H229: 210169836 | I229: PROFILED | J229: =SUMIF(OpenInvoices!C:C,Table1[[#This Row],[Invoice No]],OpenInvoices!N:N) -> 0 | K229: =IF(Table1[[#This Row],[Outstanding]]=0,Table1[[#This Row],[Invoice Amount]],Table1[[#This Row],[Outstanding]]-Table1[[#This Row],[Invoice Amount]]) -> 120455.35
A230: 1 | B230: 45992 | C230: =LEFT(Table1[[#This Row],[Project No]],2) -> HF | D230: HFR06670 | E230: National Institute for Health Research | G230: 74552 | H230: 210169838 | I230: PROFILED | J230: =SUMIF(OpenInvoices!C:C,Table1[[#This Row],[Invoice No]],OpenInvoices!N:N) -> 0 | K230: =IF(Table1[[#This Row],[Outstanding]]=0,Table1[[#This Row],[Invoice Amount]],Table1[[#This Row],[Outstanding]]-Table1[[#This Row],[Invoice Amount]]) -> 74552
A231: 1 | B231: 45992 | C231: =LEFT(Table1[[#This Row],[Project No]],2) -> AL | D231: ALR02430 | E231: University of Dundee | F231: Wellcome Trust | G231: 20.81 | H231: 210169841 | I231: WORK | J231: =SUMIF(OpenInvoices!C:C,Table1[[#This Row],[Invoice No]],OpenInvoices!N:N) -> 0 | K231: =IF(Table1[[#This Row],[Outstanding]]=0,Table1[[#This Row],[Invoice Amount]],Table1[[#This Row],[Outstanding]]-Table1[[#This Row],[Invoice Amount]]) -> 20.81
A232: 1 | B232: 45992 | C232: =LEFT(Table1[[#This Row],[Project No]],2) -> EP | D232: EPR02280 | E232: Cardiff Metropolitan University | F232: Welsh Government | G232: 7319.03 | H232: 210169869 | I232: WORK | J232: =SUMIF(OpenInvoices!C:C,Table1[[#This Row],[Invoice No]],OpenInvoices!N:N) -> 0 | K232: =IF(Table1[[#This Row],[Outstanding]]=0,Table1[[#This Row],[Invoice Amount]],Table1[[#This Row],[Outstanding]]-Table1[[#This Row],[Invoice Amount]]) -> 7319.03
A233: 1 | B233: 45992 | C233: =LEFT(Table1[[#This Row],[Project No]],2) -> HF | D233: HFR06500 | E233: Health Data Research UK | F233: 0 | G233: 45110.88 | H233: 210169872 | I233: WORK | J233: =SUMIF(OpenInvoices!C:C,Table1[[#This Row],[Invoice No]],OpenInvoices!N:N) -> 0 | K233: =IF(Table1[[#This Row],[Outstanding]]=0,Table1[[#This Row],[Invoice Amount]],Table1[[#This Row],[Outstanding]]-Table1[[#This Row],[Invoice Amount]]) -> 45110.88
A234: 1 | B234: 45992 | C234: =LEFT(Table1[[#This Row],[Project No]],2) -> AL | D234: ALR02880 | E234: University Court of the University of Edinburgh | F234: Medical Research Council | G234: 71198.56 | H234: 210169842 | I234: WORK | J234: =SUMIF(OpenInvoices!C:C,Table1[[#This Row],[Invoice No]],OpenInvoices!N:N) -> 71198.56 | K234: =IF(Table1[[#This Row],[Outstanding]]=0,Table1[[#This Row],[Invoice Amount]],Table1[[#This Row],[Outstanding]]-Table1[[#This Row],[Invoice Amount]]) -> 0
A235: 1 | B235: 45992 | C235: =LEFT(Table1[[#This Row],[Project No]],2) -> B9 | D235: B9R06420 | E235: University of Malaya | F235: Wellcome Trust | G235: 56.4 | H235: 210169843 | I235: WORK | J235: =SUMIF(OpenInvoices!C:C,Table1[[#This Row],[Invoice No]],OpenInvoices!N:N) -> 56.4 | K235: =IF(Table1[[#This Row],[Outstanding]]=0,Table1[[#This Row],[Invoice Amount]],Table1[[#This Row],[Outstanding]]-Table1[[#This Row],[Invoice Amount]]) -> 0
A236: 1 | B236: 45992 | C236: =LEFT(Table1[[#This Row],[Project No]],2) -> BK | D236: BKR02200 | E236: University of Notre Dame | F236: Office of Naval Research | G236: 6544.95 | H236: 210169844 | I236: WORK | J236: =SUMIF(OpenInvoices!C:C,Table1[[#This Row],[Invoice No]],OpenInvoices!N:N) -> 0 | K236: =IF(Table1[[#This Row],[Outstanding]]=0,Table1[[#This Row],[Invoice Amount]],Table1[[#This Row],[Outstanding]]-Table1[[#This Row],[Invoice Amount]]) -> 6544.95
A237: 1 | B237: 45992 | C237: =LEFT(Table1[[#This Row],[Project No]],2) -> BL | D237: BLR03200 | E237: University of Nottingham | F237: Medical Research Council | G237: 19436.03 | H237: 210169845 | I237: WORK | J237: =SUMIF(OpenInvoices!C:C,Table1[[#This Row],[Invoice No]],OpenInvoices!N:N) -> 0 | K237: =IF(Table1[[#This Row],[Outstanding]]=0,Table1[[#This Row],[Invoice Amount]],Table1[[#This Row],[Outstanding]]-Table1[[#This Row],[Invoice Amount]]) -> 19436.03
A238: 1 | B238: 45992 | C238: =LEFT(Table1[[#This Row],[Project No]],2) -> BL | D238: BLR03610 | E238: University of Leeds | F238: Natural Environment Research Council | G238: 3687.54 | H238: 210169846 | I238: WORK | J238: =SUMIF(OpenInvoices!C:C,Table1[[#This Row],[Invoice No]],OpenInvoices!N:N) -> 0 | K238: =IF(Table1[[#This Row],[Outstanding]]=0,Table1[[#This Row],[Invoice Amount]],Table1[[#This Row],[Outstanding]]-Table1[[#This Row],[Invoice Amount]]) -> 3687.54
...

Sheet Tables and Pivots
A1: INVOICES PER DEPARTMENT | F1: TOTAL PER DEPARTMENT | K1: TOTAL PER FUNDER | N1: TOP FUNDERS (slicer) | R1: TOTAL PER FUNDER | U1: TOP DEPTS (slicer) | Z1: RAISED BY MONTH | AF1: DEBT BY MONTH | AT1: DEBT BY TYPE | AV1: TOTAL | AW1: UNPAID | AX1: PAID
A2: Sum of ID | B2: Column Labels | F2: Sum of Invoice Amount | G2: Column Labels | K2: Row Labels | L2: Sum of Invoice Amount | N2: # | O2: Amount | P2: Funder | R2: Row Labels | S2: Sum of Invoice Amount | U2: # | V2: Amount | W2: Dept Code | X2: Department | Z2: MONTH | AA2: WORK | AB2: PROFILED | AC2: MILESTONE | AG2: RAISED | AH2: UNPAID | AK2: RAISED | AL2: UNPAID | AO2: RAISED | AP2: UNPAID | AT2: WORK | AU2: =SUMIF('All Invoices'!I:I,'Tables and Pivots'!AT2,'All Invoices'!J:J) -> 2119859.7 | AV2: =SUMIF('All Invoices'!I:I,'Tables and Pivots'!AT2,'All Invoices'!G:G) -> 7787656.3 | AW2: =AU2/AV2 -> 0.27220766 | AX2: =1-AW2 -> 0.72779234
A3: Row Labels | B3: MILESTONE | C3: PROFILED | D3: WORK | F3: Row Labels | G3: MILESTONE | H3: PROFILED | I3: WORK | K3: AWE Plc | L3: 68744.48 | N3: 1 | O3: =LARGE(L$3:L$1048576,ROW(O3)-ROW(O$2)) -> 1080000 | P3: =_xlfn.XLOOKUP(O3,L:L,K:K) -> Parker-Hannifin Corporation | R3: AZ | S3: 54285 | U3: 1 | V3: =LARGE(S$3:S$1048576,ROW(V3)-ROW(V$2)) -> 1080000 | W3: =_xlfn.XLOOKUP(V3,S:S,R:R) -> H7 | X3: =_xlfn.XLOOKUP(W3,Depts!A:A,Depts!B:B) -> OCDEM | Z3: 45870 | AA3: =COUNTIFS(Table1[Month],'Tables and Pivots'!$Z3,Table1[Type],'Tables and Pivots'!AA$2) -> 0 | AB3: =COUNTIFS(Table1[Month],'Tables and Pivots'!$Z3,Table1[Type],'Tables and Pivots'!AB$2) -> 10 | AC3: =COUNTIFS(Table1[Month],'Tables and Pivots'!$Z3,Table1[Type],'Tables and Pivots'!AC$2) -> 1 | AF3: MONTH | AG3: WORK | AH3: WORK | AI3: PAID | AJ3: UNPAID | AK3: PROFILED | AL3: PROFILED | AM3: PAID | AN3: UNPAID | AO3: MILESTONE | AP3: MILESTONE | AQ3: PAID | AR3: UNPAID | AT3: PROFILED | AU3: =SUMIF('All Invoices'!I:I,'Tables and Pivots'!AT3,'All Invoices'!J:J) -> 4869509 | AV3: =SUMIF('All Invoices'!I:I,'Tables and Pivots'!AT3,'All Invoices'!G:G) -> 16340215 | AW3: =AU3/AV3 -> 0.29800764 | AX3: =1-AW3 -> 0.70199236
A4: AC | C4: 3 | F4: AC | H4: 253814.88 | K4: Celgene Corporation | L4: 123789.34 | N4: 2 | O4: =LARGE(L$3:L$1048576,ROW(O4)-ROW(O$2)) -> 590097.62 | P4: =_xlfn.SINGLE(_xlfn.XLOOKUP(O4,L:L,K:K)) -> ModernaTX INC | R4: BL | S4: 68412.34 | U4: 2 | V4: =LARGE(S$3:S$1048576,ROW(V4)-ROW(V$2)) -> 590097.62 | W4: =_xlfn.SINGLE(_xlfn.XLOOKUP(V4,S:S,R:R)) -> BZ | X4: =_xlfn.XLOOKUP(W4,Depts!A:A,Depts!B:B) -> Primary Care Health Sciences | Z4: 45901 | AA4: =COUNTIFS(Table1[Month],'Tables and Pivots'!$Z4,Table1[Type],'Tables and Pivots'!AA$2) -> 55 | AB4: =COUNTIFS(Table1[Month],'Tables and Pivots'!$Z4,Table1[Type],'Tables and Pivots'!AB$2) -> 18 | AC4: =COUNTIFS(Table1[Month],'Tables and Pivots'!$Z4,Table1[Type],'Tables and Pivots'!AC$2) -> 11 | AF4: 45870 | AG4: =SUMIFS(Table1[Invoice Amount],Table1[Month],'Tables and Pivots'!AF4,Table1[Type],'Tables and Pivots'!$AG$3) -> 0 | AH4: =SUMIFS(Table1[Outstanding],Table1[Month],'Tables and Pivots'!AF4,Table1[Type],'Tables and Pivots'!$AH$3) -> 0 | AI4: =SUM(AG4-AH4)/AG4 -> #DIV/0! | AJ4: =AH4/AG4 -> #DIV/0! | AK4: =SUMIFS(Table1[Invoice Amount],Table1[Month],'Tables and Pivots'!AF4,Table1[Type],'Tables and Pivots'!$AK$3) -> 904809.12 | AL4: =SUMIFS(Table1[Outstanding],Table1[Month],'Tables and Pivots'!AF4,Table1[Type],'Tables and Pivots'!$AL$3) -> 0 | AM4: =SUM(AK4-AL4)/AK4 -> 1 | AN4: =AL4/AK4 -> 0 | AO4: =SUMIFS(Table1[Invoice Amount],Table1[Month],'Tables and Pivots'!AF4,Table1[Type],'Tables and Pivots'!$AO$3) -> 1080000 | AP4: =SUMIFS(Table1[Outstanding],Table1[Month],'Tables and Pivots'!AF4,Table1[Type],'Tables and Pivots'!$AP$3) -> 0 | AQ4: =SUM(AO4-AP4)/AO4 -> 1 | AR4: =AP4/AO4 -> 0 | AT4: MILESTONE | AU4: =SUMIF('All Invoices'!I:I,'Tables and Pivots'!AT4,'All Invoices'!J:J) -> 829829.71 | AV4: =SUMIF('All Invoices'!I:I,'Tables and Pivots'!AT4,'All Invoices'!G:G) -> 2958243.7 | AW4: =AU4/AV4 -> 0.28051432 | AX4: =1-AW4 -> 0.71948568
A5: AE | D5: 2 | F5: AE | I5: 19373.35 | K5: London School of Economics & Political Science | L5: 5000 | N5: 3 | O5: =LARGE(L$3:L$1048576,ROW(O5)-ROW(O$2)) -> 276836 | P5: =_xlfn.SINGLE(_xlfn.XLOOKUP(O5,L:L,K:K)) -> Marley Health Ltd | R5: BW | S5: 244983.81 | U5: 3 | V5: =LARGE(S$3:S$1048576,ROW(V5)-ROW(V$2)) -> 464748 | W5: =_xlfn.SINGLE(_xlfn.XLOOKUP(V5,S:S,R:R)) -> DF | X5: =_xlfn.XLOOKUP(W5,Depts!A:A,Depts!B:B) -> Engineering Science | Z5: 45931 | AA5: =COUNTIFS(Table1[Month],'Tables and Pivots'!$Z5,Table1[Type],'Tables and Pivots'!AA$2) -> 56 | AB5: =COUNTIFS(Table1[Month],'Tables and Pivots'!$Z5,Table1[Type],'Tables and Pivots'!AB$2) -> 23 | AC5: =COUNTIFS(Table1[Month],'Tables and Pivots'!$Z5,Table1[Type],'Tables and Pivots'!AC$2) -> 5 | AF5: 45901 | AG5: =SUMIFS(Table1[Invoice Amount],Table1[Month],'Tables and Pivots'!AF5,Table1[Type],'Tables and Pivots'!$AG$3) -> 1594389.1 | AH5: =SUMIFS(Table1[Outstanding],Table1[Month],'Tables and Pivots'!AF5,Table1[Type],'Tables and Pivots'!$AH$3) -> 59976.34 | AI5: =SUM(AG5-AH5)/AG5 -> 0.96238287 | AJ5: =AH5/AG5 -> 0.037617128 | AK5: =SUMIFS(Table1[Invoice Amount],Table1[Month],'Tables and Pivots'!AF5,Table1[Type],'Tables and Pivots'!$AK$3) -> 1032179.9 | AL5: =SUMIFS(Table1[Outstanding],Table1[Month],'Tables and Pivots'!AF5,Table1[Type],'Tables and Pivots'!$AL$3) -> 0 | AM5: =SUM(AK5-AL5)/AK5 -> 1 | AN5: =AL5/AK5 -> 0 | AO5: =SUMIFS(Table1[Invoice Amount],Table1[Month],'Tables and Pivots'!AF5,Table1[Type],'Tables and Pivots'!$AO$3) -> 1033802.9 | AP5: =SUMIFS(Table1[Outstanding],Table1[Month],'Tables and Pivots'!AF5,Table1[Type],'Tables and Pivots'!$AP$3) -> 751986.96 | AQ5: =SUM(AO5-AP5)/AO5 -> 0.27260122 | AR5: =AP5/AO5 -> 0.72739878 | AU5: =SUM(AU2:AU4) -> 7819198.4 | AW5: =AVERAGE(AW2:AW4) -> 0.28357654
A6: AF | D6: 3 | F6: AF | I6: 82432.85 | K6: Met Office | L6: 82887.52 | N6: 4 | O6: =LARGE(L$3:L$1048576,ROW(O6)-ROW(O$2)) -> 244983.81 | P6: =_xlfn.SINGLE(_xlfn.XLOOKUP(O6,L:L,K:K)) -> LifeArc | R6: BZ | S6: 590097.62 | U6: 4 | V6: =LARGE(S$3:S$1048576,ROW(V6)-ROW(V$2)) -> 244983.81 | W6: =_xlfn.SINGLE(_xlfn.XLOOKUP(V6,S:S,R:R)) -> BW | X6: =_xlfn.XLOOKUP(W6,Depts!A:A,Depts!B:B) -> Pharmacology | Z6: 45962 | AA6: =COUNTIFS(Table1[Month],'Tables and Pivots'!$Z6,Table1[Type],'Tables and Pivots'!AA$2) -> 32 | AB6: =COUNTIFS(Table1[Month],'Tables and Pivots'!$Z6,Table1[Type],'Tables and Pivots'!AB$2) -> 10 | AC6: =COUNTIFS(Table1[Month],'Tables and Pivots'!$Z6,Table1[Type],'Tables and Pivots'!AC$2) -> 0 | AF6: 45931 | AG6: =SUMIFS(Table1[Invoice Amount],Table1[Month],'Tables and Pivots'!AF6,Table1[Type],'Tables and Pivots'!$AG$3) -> 1815639.1 | AH6: =SUMIFS(Table1[Outstanding],Table1[Month],'Tables and Pivots'!AF6,Table1[Type],'Tables and Pivots'!$AH$3) -> 74874.41 | AI6: =SUM(AG6-AH6)/AG6 -> 0.9587614 | AJ6: =AH6/AG6 -> 0.041238597 | AK6: =SUMIFS(Table1[Invoice Amount],Table1[Month],'Tables and Pivots'!AF6,Table1[Type],'Tables and Pivots'!$AK$3) -> 4236096.4 | AL6: =SUMIFS(Table1[Outstanding],Table1[Month],'Tables and Pivots'!AF6,Table1[Type],'Tables and Pivots'!$AL$3) -> 15867.1 | AM6: =SUM(AK6-AL6)/AK6 -> 0.99625431 | AN6: =AL6/AK6 -> 0.0037456891 | AO6: =SUMIFS(Table1[Invoice Amount],Table1[Month],'Tables and Pivots'!AF6,Table1[Type],'Tables and Pivots'!$AO$3) -> 383196.23 | AP6: =SUMIFS(Table1[Outstanding],Table1[Month],'Tables and Pivots'!AF6,Table1[Type],'Tables and Pivots'!$AP$3) -> 0 | AQ6: =SUM(AO6-AP6)/AO6 -> 1 | AR6: =AP6/AO6 -> 0
A7: AJ | C7: 3 | F7: AJ | H7: 231347.22 | K7: MiroBio Ltd | L7: 54285 | N7: 5 | O7: =LARGE(L$3:L$1048576,ROW(O7)-ROW(O$2)) -> 123789.34 | P7: =_xlfn.SINGLE(_xlfn.XLOOKUP(O7,L:L,K:K)) -> Celgene Corporation | R7: CV | S7: 29739.4 | U7: 5 | V7: =LARGE(S$3:S$1048576,ROW(V7)-ROW(V$2)) -> 133801.85 | W7: =_xlfn.SINGLE(_xlfn.XLOOKUP(V7,S:S,R:R)) -> CB | X7: =_xlfn.XLOOKUP(W7,Depts!A:A,Depts!B:B) -> Biology | Z7: 45992 | AA7: =COUNTIFS(Table1[Month],'Tables and Pivots'!$Z7,Table1[Type],'Tables and Pivots'!AA$2) -> 32 | AB7: =COUNTIFS(Table1[Month],'Tables and Pivots'!$Z7,Table1[Type],'Tables and Pivots'!AB$2) -> 7 | AC7: =COUNTIFS(Table1[Month],'Tables and Pivots'!$Z7,Table1[Type],'Tables and Pivots'!AC$2) -> 0 | AF7: 45962 | AG7: =SUMIFS(Table1[Invoice Amount],Table1[Month],'Tables and Pivots'!AF7,Table1[Type],'Tables and Pivots'!$AG$3) -> 627656.46 | AH7: =SUMIFS(Table1[Outstanding],Table1[Month],'Tables and Pivots'!AF7,Table1[Type],'Tables and Pivots'!$AH$3) -> 194162.7 | AI7: =SUM(AG7-AH7)/AG7 -> 0.6906545 | AJ7: =AH7/AG7 -> 0.3093455 | AK7: =SUMIFS(Table1[Invoice Amount],Table1[Month],'Tables and Pivots'!AF7,Table1[Type],'Tables and Pivots'!$AK$3) -> 1855885.9 | AL7: =SUMIFS(Table1[Outstanding],Table1[Month],'Tables and Pivots'!AF7,Table1[Type],'Tables and Pivots'!$AL$3) -> 0 | AM7: =SUM(AK7-AL7)/AK7 -> 1 | AN7: =AL7/AK7 -> 0 | AO7: =SUMIFS(Table1[Invoice Amount],Table1[Month],'Tables and Pivots'!AF7,Table1[Type],'Tables and Pivots'!$AO$3) -> 0 | AP7: =SUMIFS(Table1[Outstanding],Table1[Month],'Tables and Pivots'!AF7,Table1[Type],'Tables and Pivots'!$AP$3) -> 0 | AQ7: =SUM(AO7-AP7)/AO7 -> #DIV/0! | AR7: =AP7/AO7 -> #DIV/0!
A8: AL | D8: 7 | F8: AL | I8: 460100.38 | K8: University of Cambridge | L8: 103201.85 | R8: DF | S8: 464748 | Z8: 46023 | AA8: =COUNTIFS(Table1[Month],'Tables and Pivots'!$Z8,Table1[Type],'Tables and Pivots'!AA$2) -> 65 | AB8: =COUNTIFS(Table1[Month],'Tables and Pivots'!$Z8,Table1[Type],'Tables and Pivots'!AB$2) -> 31 | AC8: =COUNTIFS(Table1[Month],'Tables and Pivots'!$Z8,Table1[Type],'Tables and Pivots'!AC$2) -> 3 | AF8: 45992 | AG8: =SUMIFS(Table1[Invoice Amount],Table1[Month],'Tables and Pivots'!AF8,Table1[Type],'Tables and Pivots'!$AG$3) -> 621094.45 | AH8: =SUMIFS(Table1[Outstanding],Table1[Month],'Tables and Pivots'!AF8,Table1[Type],'Tables and Pivots'!$AH$3) -> 134752.77 | AI8: =SUM(AG8-AH8)/AG8 -> 0.78303981 | AJ8: =AH8/AG8 -> 0.21696019 | AK8: =SUMIFS(Table1[Invoice Amount],Table1[Month],'Tables and Pivots'!AF8,Table1[Type],'Tables and Pivots'!$AK$3) -> 379263.78 | AL8: =SUMIFS(Table1[Outstanding],Table1[Month],'Tables and Pivots'!AF8,Table1[Type],'Tables and Pivots'!$AL$3) -> 22817.17 | AM8: =SUM(AK8-AL8)/AK8 -> 0.93983826 | AN8: =AL8/AK8 -> 0.060161743 | AO8: =SUMIFS(Table1[Invoice Amount],Table1[Month],'Tables and Pivots'!AF8,Table1[Type],'Tables and Pivots'!$AO$3) -> 0 | AP8: =SUMIFS(Table1[Outstanding],Table1[Month],'Tables and Pivots'!AF8,Table1[Type],'Tables and Pivots'!$AP$3) -> 0 | AQ8: =SUM(AO8-AP8)/AO8 -> #DIV/0! | AR8: =AP8/AO8 -> #DIV/0!
A9: AM | C9: 2 | F9: AM | H9: 435715.12 | K9: Liverpool School of Tropical Medicine | L9: 11162.75 | R9: EP | S9: 16930.77 | Z9: 46054 | AA9: =COUNTIFS(Table1[Month],'Tables and Pivots'!$Z9,Table1[Type],'Tables and Pivots'!AA$2) -> 24 | AB9: =COUNTIFS(Table1[Month],'Tables and Pivots'!$Z9,Table1[Type],'Tables and Pivots'!AB$2) -> 12 | AC9: =COUNTIFS(Table1[Month],'Tables and Pivots'!$Z9,Table1[Type],'Tables and Pivots'!AC$2) -> 3 | AF9: 46023 | AG9: =SUMIFS(Table1[Invoice Amount],Table1[Month],'Tables and Pivots'!AF9,Table1[Type],'Tables and Pivots'!$AG$3) -> 2044413.2 | AH9: =SUMIFS(Table1[Outstanding],Table1[Month],'Tables and Pivots'!AF9,Table1[Type],'Tables and Pivots'!$AH$3) -> 797908.12 | AI9: =SUM(AG9-AH9)/AG9 -> 0.6097129 | AJ9: =AH9/AG9 -> 0.3902871 | AK9: =SUMIFS(Table1[Invoice Amount],Table1[Month],'Tables and Pivots'!AF9,Table1[Type],'Tables and Pivots'!$AK$3) -> 4676851 | AL9: =SUMIFS(Table1[Outstanding],Table1[Month],'Tables and Pivots'!AF9,Table1[Type],'Tables and Pivots'!$AL$3) -> 2015181.4 | AM9: =SUM(AK9-AL9)/AK9 -> 0.56911577 | AN9: =AL9/AK9 -> 0.43088423 | AO9: =SUMIFS(Table1[Invoice Amount],Table1[Month],'Tables and Pivots'!AF9,Table1[Type],'Tables and Pivots'!$AO$3) -> 313826.56 | AP9: =SUMIFS(Table1[Outstanding],Table1[Month],'Tables and Pivots'!AF9,Table1[Type],'Tables and Pivots'!$AP$3) -> 68842.75 | AQ9: =SUM(AO9-AP9)/AO9 -> 0.78063441 | AR9: =AP9/AO9 -> 0.21936559
A10: AP | D10: 1 | F10: AP | I10: 1549.06 | K10: Institut de recherches en science de la sante | L10: 30600 | R10: H4 | S10: 56964.9 | Z10: 46082 | AA10: =COUNTIFS(Table1[Month],'Tables and Pivots'!$Z10,Table1[Type],'Tables and Pivots'!AA$2) -> 40 | AB10: =COUNTIFS(Table1[Month],'Tables and Pivots'!$Z10,Table1[Type],'Tables and Pivots'!AB$2) -> 14 | AC10: =COUNTIFS(Table1[Month],'Tables and Pivots'!$Z10,Table1[Type],'Tables and Pivots'!AC$2) -> 0 | AF10: 46054 | AG10: =SUMIFS(Table1[Invoice Amount],Table1[Month],'Tables and Pivots'!AF10,Table1[Type],'Tables and Pivots'!$AG$3) -> 447225.59 | AH10: =SUMIFS(Table1[Outstanding],Table1[Month],'Tables and Pivots'!AF10,Table1[Type],'Tables and Pivots'!$AH$3) -> 220947.06 | AI10: =SUM(AG10-AH10)/AG10 -> 0.5059606 | AJ10: =AH10/AG10 -> 0.4940394 | AK10: =SUMIFS(Table1[Invoice Amount],Table1[Month],'Tables and Pivots'!AF10,Table1[Type],'Tables and Pivots'!$AK$3) -> 1406322.9 | AL10: =SUMIFS(Table1[Outstanding],Table1[Month],'Tables and Pivots'!AF10,Table1[Type],'Tables and Pivots'!$AL$3) -> 1000587.2 | AM10: =SUM(AK10-AL10)/AK10 -> 0.28850823 | AN10: =AL10/AK10 -> 0.71149177 | AO10: =SUMIFS(Table1[Invoice Amount],Table1[Month],'Tables and Pivots'!AF10,Table1[Type],'Tables and Pivots'!$AO$3) -> 147418 | AP10: =SUMIFS(Table1[Outstanding],Table1[Month],'Tables and Pivots'!AF10,Table1[Type],'Tables and Pivots'!$AP$3) -> 9000 | AQ10: =SUM(AO10-AP10)/AO10 -> 0.93894911 | AR10: =AP10/AO10 -> 0.061050889
A11: AV | D11: 12 | F11: AV | I11: 223215.9 | K11: Cern | L11: 35240.24 | R11: H7 | S11: 1080000 | Z11: 46113 | AA11: =COUNTIFS(Table1[Month],'Tables and Pivots'!$Z11,Table1[Type],'Tables and Pivots'!AA$2) -> 0 | AB11: =COUNTIFS(Table1[Month],'Tables and Pivots'!$Z11,Table1[Type],'Tables and Pivots'!AB$2) -> 0 | AC11: =COUNTIFS(Table1[Month],'Tables and Pivots'!$Z11,Table1[Type],'Tables and Pivots'!AC$2) -> 0 | AF11: 46082 | AG11: =SUMIFS(Table1[Invoice Amount],Table1[Month],'Tables and Pivots'!AF11,Table1[Type],'Tables and Pivots'!$AG$3) -> 637238.31 | AH11: =SUMIFS(Table1[Outstanding],Table1[Month],'Tables and Pivots'!AF11,Table1[Type],'Tables and Pivots'!$AH$3) -> 637238.31 | AI11: =SUM(AG11-AH11)/AG11 -> 0 | AJ11: =AH11/AG11 -> 1 | AK11: =SUMIFS(Table1[Invoice Amount],Table1[Month],'Tables and Pivots'!AF11,Table1[Type],'Tables and Pivots'!$AK$3) -> 1848806.2 | AL11: =SUMIFS(Table1[Outstanding],Table1[Month],'Tables and Pivots'!AF11,Table1[Type],'Tables and Pivots'!$AL$3) -> 1815056.2 | AM11: =SUM(AK11-AL11)/AK11 -> 0.018255023 | AN11: =AL11/AK11 -> 0.98174498 | AO11: =SUMIFS(Table1[Invoice Amount],Table1[Month],'Tables and Pivots'!AF11,Table1[Type],'Tables and Pivots'!$AO$3) -> 0 | AP11: =SUMIFS(Table1[Outstanding],Table1[Month],'Tables and Pivots'!AF11,Table1[Type],'Tables and Pivots'!$AP$3) -> 0 | AQ11: =SUM(AO11-AP11)/AO11 -> #DIV/0! | AR11: =AP11/AO11 -> #DIV/0!
A12: AZ | B12: 1 | C12: 4 | D12: 5 | F12: AZ | G12: 54285 | H12: 429818.85 | I12: 96606.1 | K12: LifeArc | L12: 244983.81 | R12: HB | S12: 11500 | Z12: 46143 | AA12: =COUNTIFS(Table1[Month],'Tables and Pivots'!$Z12,Table1[Type],'Tables and Pivots'!AA$2) -> 0 | AB12: =COUNTIFS(Table1[Month],'Tables and Pivots'!$Z12,Table1[Type],'Tables and Pivots'!AB$2) -> 0 | AC12: =COUNTIFS(Table1[Month],'Tables and Pivots'!$Z12,Table1[Type],'Tables and Pivots'!AC$2) -> 0 | AF12: 46113 | AG12: =SUMIFS(Table1[Invoice Amount],Table1[Month],'Tables and Pivots'!AF12,Table1[Type],'Tables and Pivots'!$AG$3) -> 0 | AH12: =SUMIFS(Table1[Outstanding],Table1[Month],'Tables and Pivots'!AF12,Table1[Type],'Tables and Pivots'!$AH$3) -> 0 | AI12: =SUM(AG12-AH12)/AG12 -> #DIV/0! | AJ12: =AH12/AG12 -> #DIV/0! | AK12: =SUMIFS(Table1[Invoice Amount],Table1[Month],'Tables and Pivots'!AF12,Table1[Type],'Tables and Pivots'!$AK$3) -> 0 | AL12: =SUMIFS(Table1[Outstanding],Table1[Month],'Tables and Pivots'!AF12,Table1[Type],'Tables and Pivots'!$AL$3) -> 0 | AM12: =SUM(AK12-AL12)/AK12 -> #DIV/0! | AN12: =AL12/AK12 -> #DIV/0! | AO12: =SUMIFS(Table1[Invoice Amount],Table1[Month],'Tables and Pivots'!AF12,Table1[Type],'Tables and Pivots'!$AO$3) -> 0 | AP12: =SUMIFS(Table1[Outstanding],Table1[Month],'Tables and Pivots'!AF12,Table1[Type],'Tables and Pivots'!$AP$3) -> 0 | AQ12: =SUM(AO12-AP12)/AO12 -> #DIV/0! | AR12: =AP12/AO12 -> #DIV/0!
A13: B8 | C13: 1 | F13: B8 | H13: 26250 | K13: PSC Support | L13: 11500 | R13: HF | S13: 100000 | Z13: 46174 | AA13: =COUNTIFS(Table1[Month],'Tables and Pivots'!$Z13,Table1[Type],'Tables and Pivots'!AA$2) -> 0 | AB13: =COUNTIFS(Table1[Month],'Tables and Pivots'!$Z13,Table1[Type],'Tables and Pivots'!AB$2) -> 0 | AC13: =COUNTIFS(Table1[Month],'Tables and Pivots'!$Z13,Table1[Type],'Tables and Pivots'!AC$2) -> 0 | AF13: 46143 | AG13: =SUMIFS(Table1[Invoice Amount],Table1[Month],'Tables and Pivots'!AF13,Table1[Type],'Tables and Pivots'!$AG$3) -> 0 | AH13: =SUMIFS(Table1[Outstanding],Table1[Month],'Tables and Pivots'!AF13,Table1[Type],'Tables and Pivots'!$AH$3) -> 0 | AI13: =SUM(AG13-AH13)/AG13 -> #DIV/0! | AJ13: =AH13/AG13 -> #DIV/0! | AK13: =SUMIFS(Table1[Invoice Amount],Table1[Month],'Tables and Pivots'!AF13,Table1[Type],'Tables and Pivots'!$AK$3) -> 0 | AL13: =SUMIFS(Table1[Outstanding],Table1[Month],'Tables and Pivots'!AF13,Table1[Type],'Tables and Pivots'!$AL$3) -> 0 | AM13: =SUM(AK13-AL13)/AK13 -> #DIV/0! | AN13: =AL13/AK13 -> #DIV/0! | AO13: =SUMIFS(Table1[Invoice Amount],Table1[Month],'Tables and Pivots'!AF13,Table1[Type],'Tables and Pivots'!$AO$3) -> 0 | AP13: =SUMIFS(Table1[Outstanding],Table1[Month],'Tables and Pivots'!AF13,Table1[Type],'Tables and Pivots'!$AP$3) -> 0 | AQ13: =SUM(AO13-AP13)/AO13 -> #DIV/0! | AR13: =AP13/AO13 -> #DIV/0!
A14: B9 | C14: 1 | D14: 7 | F14: B9 | H14: 84000 | I14: 125523.49 | K14: Bell Foundation | L14: 16930.77 | R14: HN | S14: 11162.75 | Z14: 46204 | AA14: =COUNTIFS(Table1[Month],'Tables and Pivots'!$Z14,Table1[Type],'Tables and Pivots'!AA$2) -> 0 | AB14: =COUNTIFS(Table1[Month],'Tables and Pivots'!$Z14,Table1[Type],'Tables and Pivots'!AB$2) -> 0 | AC14: =COUNTIFS(Table1[Month],'Tables and Pivots'!$Z14,Table1[Type],'Tables and Pivots'!AC$2) -> 0 | AF14: 46174 | AG14: =SUMIFS(Table1[Invoice Amount],Table1[Month],'Tables and Pivots'!AF14,Table1[Type],'Tables and Pivots'!$AG$3) -> 0 | AH14: =SUMIFS(Table1[Outstanding],Table1[Month],'Tables and Pivots'!AF14,Table1[Type],'Tables and Pivots'!$AH$3) -> 0 | AI14: =SUM(AG14-AH14)/AG14 -> #DIV/0! | AJ14: =AH14/AG14 -> #DIV/0! | AK14: =SUMIFS(Table1[Invoice Amount],Table1[Month],'Tables and Pivots'!AF14,Table1[Type],'Tables and Pivots'!$AK$3) -> 0 | AL14: =SUMIFS(Table1[Outstanding],Table1[Month],'Tables and Pivots'!AF14,Table1[Type],'Tables and Pivots'!$AL$3) -> 0 | AM14: =SUM(AK14-AL14)/AK14 -> #DIV/0! | AN14: =AL14/AK14 -> #DIV/0! | AO14: =SUMIFS(Table1[Invoice Amount],Table1[Month],'Tables and Pivots'!AF14,Table1[Type],'Tables and Pivots'!$AO$3) -> 0 | AP14: =SUMIFS(Table1[Outstanding],Table1[Month],'Tables and Pivots'!AF14,Table1[Type],'Tables and Pivots'!$AP$3) -> 0 | AQ14: =SUM(AO14-AP14)/AO14 -> #DIV/0! | AR14: =AP14/AO14 -> #DIV/0!
A15: BB | C15: 1 | D15: 1 | F15: BB | H15: 125000 | I15: 1299.5 | K15: Parker-Hannifin Corporation | L15: 1080000 | R15: HS | S15: 55377 | AF15: 46204 | AG15: =SUMIFS(Table1[Invoice Amount],Table1[Month],'Tables and Pivots'!AF15,Table1[Type],'Tables and Pivots'!$AG$3) -> 0 | AH15: =SUMIFS(Table1[Outstanding],Table1[Month],'Tables and Pivots'!AF15,Table1[Type],'Tables and Pivots'!$AH$3) -> 0 | AI15: =SUM(AG15-AH15)/AG15 -> #DIV/0! | AJ15: =AH15/AG15 -> #DIV/0! | AK15: =SUMIFS(Table1[Invoice Amount],Table1[Month],'Tables and Pivots'!AF15,Table1[Type],'Tables and Pivots'!$AK$3) -> 0 | AL15: =SUMIFS(Table1[Outstanding],Table1[Month],'Tables and Pivots'!AF15,Table1[Type],'Tables and Pivots'!$AL$3) -> 0 | AM15: =SUM(AK15-AL15)/AK15 -> #DIV/0! | AN15: =AL15/AK15 -> #DIV/0! | AO15: =SUMIFS(Table1[Invoice Amount],Table1[Month],'Tables and Pivots'!AF15,Table1[Type],'Tables and Pivots'!$AO$3) -> 0 | AP15: =SUMIFS(Table1[Outstanding],Table1[Month],'Tables and Pivots'!AF15,Table1[Type],'Tables and Pivots'!$AP$3) -> 0 | AQ15: =SUM(AO15-AP15)/AO15 -> #DIV/0! | AR15: =AP15/AO15 -> #DIV/0!
A16: BK | D16: 3 | F16: BK | I16: 39258.84 | K16: ModernaTX INC | L16: 590097.62 | R16: DL | S16: 35240.24
A17: BL | B17: 1 | C17: 1 | D17: 8 | F17: BL | G17: 68412.34 | H17: 370370.37 | I17: 371760.09 | K17: Sexual violence research initiative (SVRI) | L17: 29739.4 | R17: CB | S17: 133801.85
A18: BV | D18: 2 | F18: BV | I18: 116572.76 | K18: United Kingdom National Nuclear Laboratory Limited | L18: 36280 | R18: MQ | S18: 5000
A19: BW | B19: 1 | D19: 2 | F19: BW | G19: 244983.81 | I19: 29664.82 | K19: Marley Health Ltd | L19: 276836
A20: BX | C20: 2 | D20: 1 | F20: BX | H20: 27832.12 | I20: 3242.95 | K20: Yellowstone Biosciences Limited | L20: 56964.9
A21: BZ | B21: 1 | C21: 13 | D21: 39 | F21: BZ | G21: 590097.62 | H21: 447890.22 | I21: 1127208.5 | K21: K36 Therapeutics, Inc. | L21: 100000
A22: CD | C22: 3 | F22: CD | H22: 313436.41
A23: CF | C23: 1 | D23: 4 | F23: CF | H23: 773750 | I23: 73869.28
A24: CQ | D24: 3 | F24: CQ | I24: 16547.01
A25: CS | D25: 3 | F25: CS | I25: 54993.82
A26: CV | B26: 1 | D26: 2 | F26: CV | G26: 29739.4 | I26: 13078.44
A27: CZ | C27: 1 | D27: 3 | F27: CZ | H27: 5481.18 | I27: 53158.59
A28: DB | D28: 7 | F28: DB | I28: 117348.25
A29: DC | C29: 4 | D29: 4 | F29: DC | H29: 35000 | I29: 75072.26
A30: DF | B30: 6 | C30: 19 | D30: 24 | F30: DF | G30: 464748 | H30: 3970658.2 | I30: 1074890
A31: DG | C31: 1 | D31: 5 | F31: DG | H31: 25000 | I31: 9600.84
A32: DH | C32: 2 | D32: 4 | F32: DH | H32: 32871 | I32: 90452.17
A33: DJ | D33: 11 | F33: DJ | I33: 423634.16
A34: DK | C34: 1 | D34: 3 | F34: DK | H34: 500000 | I34: 10687.86
A35: DM | C35: 2 | D35: 5 | F35: DM | H35: 566704 | I35: 85645.89
A36: DN | C36: 2 | D36: 4 | F36: DN | H36: 52264.42 | I36: 136489.67
A37: DQ | C37: 1 | F37: DQ | H37: 104166.67
A38: DR | D38: 1 | F38: DR | I38: 24704.25
A39: DU | C39: 3 | D39: 2 | F39: DU | H39: 105223.47 | I39: 61626.64
A40: EB | D40: 1 | F40: EB | I40: 14932.77
A41: EP | B41: 1 | C41: 2 | D41: 2 | F41: EP | G41: 16930.77 | H41: 15700.67 | I41: 8706.9
A42: H4 | B42: 1 | C42: 2 | D42: 7 | F42: H4 | G42: 56964.9 | H42: 2767000 | I42: 61960.46
A43: H5 | D43: 3 | F43: H5 | I43: 39336.49
A44: H6 | C44: 2 | D44: 3 | F44: H6 | H44: 1347090 | I44: 28341.07
A45: H7 | B45: 1 | C45: 10 | F45: H7 | G45: 1080000 | H45: 561878.79
A46: HB | B46: 2 | D46: 8 | F46: HB | G46: 11500 | I46: 102772.78
A47: HC | C47: 1 | F47: HC | H47: 56005.66
A48: HE | D48: 3 | F48: HE | I48: 33364.38
A49: HF | B49: 1 | C49: 14 | D49: 14 | F49: HF | G49: 100000 | H49: 1193031.8 | I49: 465644.25
A50: HJ | C50: 5 | D50: 7 | F50: HJ | H50: 61355.2 | I50: 316839.51
A51: HM | C51: 4 | D51: 26 | F51: HM | H51: 678601.5 | I51: 325478.3
A52: HN | B52: 1 | D52: 3 | F52: HN | G52: 11162.75 | I52: 27666.84
A53: HQ | D53: 12 | F53: HQ | I53: 337693.24
A54: LC | C54: 1 | F54: LC | H54: 194959
A55: LD | D55: 1 | F55: LD | I55: 13197.16
A56: LE | C56: 1 | F56: LE | H56: 22000
A57: BA | D57: 3 | F57: BA | I57: 5692.17
A58: HS | B58: 1 | C58: 3 | F58: HS | G58: 55377 | H58: 167490.82
A59: DL | B59: 1 | F59: DL | G59: 35240.24
A60: B5 | D60: 1 | F60: B5 | I60: 15361.22
A61: CY | D61: 5 | F61: CY | I61: 90093.19
A62: CB | B62: 2 | C62: 1 | D62: 8 | F62: CB | G62: 133801.85 | H62: 22952.7 | I62: 130441.37
A63: AB | D63: 1 | F63: AB | I63: 10245.54
A64: PS | D64: 4 | F64: PS | I64: 438777
A65: MQ | B65: 1 | F65: MQ | G65: 5000
A66: A3 | C66: 2 | D66: 1 | F66: A3 | H66: 189750 | I66: 14004.82
A67: CN | C67: 2 | F67: CN | H67: 44890.94
A68: A4 | D68: 2 | F68: A4 | I68: 3614.34
A69: M3 | D69: 4 | F69: M3 | I69: 90971.92
A70: A5 | D70: 5 | F70: A5 | I70: 185636.87
A71: CW | C71: 4 | F71: CW | H71: 100914
A72: ET | D72: 2 | F72: ET | I72: 7276

Sheet Depts
A1: Code | B1: Department Name
A2: A3 | B2: IDRM- Paediatrics
A3: A4 | B3: Institute of Developmental and Regenerative Medicine
A4: A5 | B4: DPAG Bionanoscience
A5: A9 | B5: Kenya (Trop Med)
A6: AB | B6: Pitt Rivers Museum
A7: AC | B7: School of Geography and the Environment
A8: AE | B8: Social & Cultural Anthropology
A9: AF | B9: Environmental Change Institute
A10: AJ | B10: Target Discovery Institute
A11: AL | B11: Biochemistry
A12: AM | B12: Statistics
... A127: YS | B127: Uehiro Institute

Sheet OpenInvoices
A1: Sponsor | B1: Sponsor Account | C1: Invoice Number | D1: Invoice Date | E1: Due Date | F1: Today | G1: Days Overdue | H1: Ageing Bucket | I1: Currency | J1: Invoice Amount Inv Curr | K1: Vat Amount Inv Curr | L1: Amount Remaining Inv Curr | M1: Vat Remaining Gbp | N1: Actual Outstanding | O1: Amount Remaining GBP | P1: Project Number | Q1: Project Name | R1: Project Type | S1: Project Status | T1: Project Department | U1: Principal Investigator | V1: Invoice Comments | W1: Customer Order Number
A2: M Squared Lasers Ltd | B2: 74596 | C2: 210084653 | D2: 43832 | E2: 43862 | F2: 46091 | G2: 2229 | H2: 360+ days overdue | I2: GBP | J2: 3836.57 | K2: 639.43 | L2: 2692.56 | M2: 448.76 | N2: =IF(I2="GBP",L2-K2,O2-K2) -> 2053.13 | O2: 2692.56 | P2: BWR00971 | Q2: M Squared/Emptage KTP | R2: Research | S2: Pending Close | T2: Pharmacology | U2: Emptage, Prof. Nigel | V2: g- 16/07/25 email from Graeme - We would pay £4895 in first 2 weeks of August then £10k per month Sept-Dec. Could that work to get this finished off. 17/07/25 email to Graeme - Thanks for your email, yes that will work and agree to this payment plan. 27/08/25 email to Graeme - Can you let me know if the initial payment of £4,895.00 has been made? 24/09/25 email to Graeme Malcolm - Have you and update on when we will receive the expected payments. 29/10/25 email from Jimmy (dept) to James B - Would it be worth my PI who worked with them getting in touch? I will reach out to him now. 01/12/2025 email from James B to Heidi (dept) - For BWR00971, we haven’t yet created a specific provision for this debt. I would like to set up a departmental provision for this, £36,674.68 as calculated below, charged to BW0000, when we compile our Q2 bad debt provision. Would this be acceptable to you? 01/12/2025 email from Heidi to James - Many thanks for both of your replies, much appreciated. The dept is happy to accept your suggestions re both debts. Please let us know if you need us to do anything else, pending any provision we add to our Q2 figures. 02/12/2025 email from James to Heidi - Many thanks for getting back to me Heidi. We’ll create the agreed provisions during our usual quarterly BDP process, in early Feb 2026 (for the Jan-26 books). No further action required from you on this point. 21/01/2026 email to Graeme Malcolm - We are yet to receive any payments per your email can you let me know when payment will begin. | W2: KTP010823
A3: OxStem Immuno | B3: 75563 | C3: 210085688 | D3: 43843 | E3: 43873 | F3: 46091 | G3: 2218 | H3: 360+ days overdue | I3: GBP | J3: 37237.97 | K3: 6206.33 | L3: 37237.97 | M3: 6206.33 | N3: =IF(I3="GBP",L3-K3,O3-K3) -> 31031.64 | O3: 37237.97 | P3: BVR01440 | Q3: Greaves - OxStem | R3: Research | S3: Pending Close | T3: Dunn School of Pathology | U3: Greaves, Prof. David | V3: g- 22/08/24 email from Robert Bough to Stephen - The Company is still disputing parts of the invoices, and we continue to rebut their arguments. Angela Lintern is completely up to speed with the latest position.
A4: Oxstem Oncology Ltd | B4: 70397 | C4: 210086645 | D4: 43861 | E4: 43891 | F4: 46091 | G4: 2200 | H4: 360+ days overdue | I4: GBP | J4: 172095.46 | K4: 28682.58 | L4: 172095.46 | M4: 28682.58 | N4: =IF(I4="GBP",L4-K4,O4-K4) -> 143412.88 | O4: 172095.46 | P4: DMR00830 | Q4: Oxstem Oncology | R4: Research | S4: Pending Close | T4: Organic Chemistry | U4: Russell, Prof. Angela | V4: g- 22/08/24 email from Robert Bough to Stephen - The Company is still disputing parts of the invoices, and we continue to rebut their arguments. Angela Lintern is completely up to speed with the latest position. | W4: N/A
A5: Oxstem Ltd | B5: 70393 | C5: 210086643 | D5: 43861 | E5: 43891 | F5: 46091 | G5: 2200 | H5: 360+ days overdue | I5: GBP | J5: 16789.2 | K5: 2798.2 | L5: 16789.2 | M5: 2798.2 | N5: =IF(I5="GBP",L5-K5,O5-K5) -> 13991 | O5: 16789.2 | P5: DMR00820 | Q5: OxStem 4D -single cell culture | R5: Research | S5: Pending Close | T5: Organic Chemistry | U5: Russell, Prof. Angela | V5: g- 22/08/24 email from Robert Bough to Stephen - The Company is still disputing parts of the invoices, and we continue to rebut their arguments. Angela Lintern is completely up to speed with the latest position. | W5: N/A
A6: OxStem Neuro Ltd | B6: 70872 | C6: 210086650 | D6: 43861 | E6: 43891 | F6: 46091 | G6: 2200 | H6: 360+ days overdue | I6: GBP | J6: 296447.64 | K6: 49407.94 | L6: 296447.64 | M6: 49407.94 | N6: =IF(I6="GBP",L6-K6,O6-K6) -> 247039.7 | O6: 296447.64 | P6: DMR00870 | Q6: OxStem Neuro | R6: Research | S6: Pending Close | T6: Organic Chemistry | U6: Russell, Prof. Angela | V6: g- 22/08/24 email from Robert Bough to Stephen - The Company is still disputing parts of the invoices, and we continue to rebut their arguments. Angela Lintern is completely up to speed with the latest position. | W6: N/A
A7: Oxstem Cardio Limited | B7: 71939 | C7: 210086652 | D7: 43861 | E7: 43891 | F7: 46091 | G7: 2200 | H7: 360+ days overdue | I7: GBP | J7: 356133.34 | K7: 59355.56 | L7: 356133.34 | M7: 59355.56 | N7: =IF(I7="GBP",L7-K7,O7-K7) -> 296777.78 | O7: 356133.34 | P7: DMR00970 | Q7: OxStem Cardio | R7: Research | S7: Pending Close | T7: Organic Chemistry | U7: Russell, Prof. Angela | V7: g- 22/08/24 email from Robert Bough to Stephen - The Company is still disputing parts of the invoices, and we continue to rebut their arguments. Angela Lintern is completely up to speed with the latest position.
A8: M Squared Lasers Ltd | B8: 74596 | C8: 210086738 | D8: 43865 | E8: 43895 | F8: 46091 | G8: 2196 | H8: 360+ days overdue | I8: GBP | J8: 3836.57 | K8: 639.43 | L8: 3836.57 | M8: 639.43 | N8: =IF(I8="GBP",L8-K8,O8-K8) -> 3197.14 | O8: 3836.57 | P8: BWR00971 | Q8: M Squared/Emptage KTP | R8: Research | S8: Pending Close | T8: Pharmacology | U8: Emptage, Prof. Nigel | V8: g- 16/07/25 email from Graeme - We would pay £4895 in first 2 weeks of August then £10k per month Sept-Dec. Could that work to get this finished off. 17/07/25 email to Graeme - Thanks for your email, yes that will work and agree to this payment plan. 27/08/25 email to Graeme - Can you let me know if the initial payment of £4,895.00 has been made? 24/09/25 email to Graeme Malcolm - Have you and update on when we will receive the expected payments. 29/10/25 email from Jimmy (dept) to James B - Would it be worth my PI who worked with them getting in touch? I will reach out to him now. 01/12/2025 email from James B to Heidi (dept) - For BWR00971, we haven’t yet created a specific provision for this debt. I would like to set up a departmental provision for this, £36,674.68 as calculated below, charged to BW0000, when we compile our Q2 bad debt provision. Would this be acceptable to you? 01/12/2025 email from Heidi to James - Many thanks for both of your replies, much appreciated. The dept is happy to accept your suggestions re both debts. Please let us know if you need us to do anything else, pending any provision we add to our Q2 figures. 02/12/2025 email from James to Heidi - Many thanks for getting back to me Heidi. We’ll create the agreed provisions during our usual quarterly BDP process, in early Feb 2026 (for the Jan-26 books). No further action required from you on this point. 21/01/2026 email to Graeme Malcolm - We are yet to receive any payments per your email can you let me know when payment will begin. | W8: KTP010823
A9: M Squared Lasers Ltd | B9: 74596 | C9: 210087541 | D9: 43892 | E9: 43922 | F9: 46091 | G9: 2169 | H9: 360+ days overdue | I9: GBP | J9: 3836.57 | K9: 639.43 | L9: 3836.57 | M9: 639.43 | N9: =IF(I9="GBP",L9-K9,O9-K9) -> 3197.14 | O9: 3836.57 | P9: BWR00971 | Q9: M Squared/Emptage KTP | R9: Research | S9: Pending Close | T9: Pharmacology | U9: Emptage, Prof. Nigel | V9: g- 16/07/25 email from Graeme - We would pay £4895 in first 2 weeks of August then £10k per month Sept-Dec. Could that work to get this finished off. 17/07/25 email to Graeme - Thanks for your email, yes that will work and agree to this payment plan. 27/08/25 email to Graeme - Can you let me know if the initial payment of £4,895.00 has been made? 24/09/25 email to Graeme Malcolm - Have you and update on when we will receive the expected payments. 29/10/25 email from Jimmy (dept) to James B - Would it be worth my PI who worked with them getting in touch? I will reach out to him now. 01/12/2025 email from James B to Heidi (dept) - For BWR00971, we haven’t yet created a specific provision for this debt. I would like to set up a departmental provision for this, £36,674.68 as calculated below, charged to BW0000, when we compile our Q2 bad debt provision. Would this be acceptable to you? 01/12/2025 email from Heidi to James - Many thanks for both of your replies, much appreciated. The dept is happy to accept your suggestions re both debts. Please let us know if you need us to do anything else, pending any provision we add to our Q2 figures. 02/12/2025 email from James to Heidi - Many thanks for getting back to me Heidi. We’ll create the agreed provisions during our usual quarterly BDP process, in early Feb 2026 (for the Jan-26 books). No further action required from you on this point. 21/01/2026 email to Graeme Malcolm - We are yet to receive any payments per your email can you let me know when payment will begin. | W9: KTP010823
A10: M Squared Lasers Ltd | B10: 74596 | C10: 210089046 | D10: 43922 | E10: 43952 | F10: 46091 | G10: 2139 | H10: 360+ days overdue | I10: GBP | J10: 3836.57 | K10: 639.43 | L10: 3836.57 | M10: 639.43 | N10: =IF(I10="GBP",L10-K10,O10-K10) -> 3197.14 | O10: 3836.57 | P10: BWR00971 | Q10: M Squared/Emptage KTP | R10: Research | S10: Pending Close | T10: Pharmacology | U10: Emptage, Prof. Nigel | V10: g- 16/07/25 email from Graeme - We would pay £4895 in first 2 weeks of August then £10k per month Sept-Dec. Could that work to get this finished off. 17/07/25 email to Graeme - Thanks for your email, yes that will work and agree to this payment plan. 27/08/25 email to Graeme - Can you let me know if the initial payment of £4,895.00 has been made? 24/09/25 email to Graeme Malcolm - Have you and update on when we will receive the expected payments. 29/10/25 email from Jimmy (dept) to James B - Would it be worth my PI who worked with them getting in touch? I will reach out to him now. 01/12/2025 email from James B to Heidi (dept) - For BWR00971, we haven’t yet created a specific provision for this debt. I would like to set up a departmental provision for this, £36,674.68 as calculated below, charged to BW0000, when we compile our Q2 bad debt provision. Would this be acceptable to you? 01/12/2025 email from Heidi to James - Many thanks for both of your replies, much appreciated. The dept is happy to accept your suggestions re both debts. Please let us know if you need us to do anything else, pending any provision we add to our Q2 figures. 02/12/2025 email from James to Heidi - Many thanks for getting back to me Heidi. We’ll create the agreed provisions during our usual quarterly BDP process, in early Feb 2026 (for the Jan-26 books). No further action required from you on this point. 21/01/2026 email to Graeme Malcolm - We are yet to receive any payments per your email can you let me know when payment will begin. | W10: KTP010823
A11: M Squared Lasers Ltd | B11: 74596 | C11: 210090369 | D11: 43952 | E11: 43982 | F11: 46091 | G11: 2109 | H11: 360+ days overdue | I11: GBP | J11: 3836.57 | K11: 639.43 | L11: 3836.57 | M11: 639.43 | N11: =IF(I11="GBP",L11-K11,O11-K11) -> 3197.14 | O11: 3836.57 | P11: BWR00971 | Q11: M Squared/Emptage KTP | R11: Research | S11: Pending Close | T11: Pharmacology | U11: Emptage, Prof. Nigel | V11: g- 16/07/25 email from Graeme - We would pay £4895 in first 2 weeks of August then £10k per month Sept-Dec. Could that work to get this finished off. 17/07/25 email to Graeme - Thanks for your email, yes that will work and agree to this payment plan. 27/08/25 email to Graeme - Can you let me know if the initial payment of £4,895.00 has been made? 24/09/25 email to Graeme Malcolm - Have you and update on when we will receive the expected payments. 29/10/25 email from Jimmy (dept) to James B - Would it be worth my PI who worked with them getting in touch? I will reach out to him now. 01/12/2025 email from James B to Heidi (dept) - For BWR00971, we haven’t yet created a specific provision for this debt. I would like to set up a departmental provision for this, £36,674.68 as calculated below, charged to BW0000, when we compile our Q2 bad debt provision. Would this be acceptable to you? 01/12/2025 email from Heidi to James - Many thanks for both of your replies, much appreciated. The dept is happy to accept your suggestions re both debts. Please let us know if you need us to do anything else, pending any provision we add to our Q2 figures. 02/12/2025 email from James to Heidi - Many thanks for getting back to me Heidi. We’ll create the agreed provisions during our usual quarterly BDP process, in early Feb 2026 (for the Jan-26 books). No further action required from you on this point. 21/01/2026 email to Graeme Malcolm - We are yet to receive any payments per your email can you let me know when payment will begin. | W11: KTP010823
A12: OxStem Ocular Ltd | B12: 70871 | C12: 210090932 | D12: 43979 | E12: 44009 | F12: 46091 | G12: 2082 | H12: 360+ days overdue | I12: GBP | J12: 31939.05 | K12: 5323.18 | L12: 31939.05 | M12: 5323.18 | N12: =IF(I12="GBP",L12-K12,O12-K12) -> 26615.87 | O12: 31939.05 | P12: DMR00880 | Q12: OxStem Ocular | R12: Research | S12: Pending Close | T12: Organic Chemistry | U12: Russell, Prof. Angela | V12: g- 22/08/24 email from Robert Bough to Stephen - The Company is still disputing parts of the invoices, and we continue to rebut their arguments. Angela Lintern is completely up to speed with the latest position. | W12: n/a
A13: Oxstem Ltd | B13: 70393 | C13: 210090925 | D13: 43979 | E13: 44009 | F13: 46091 | G13: 2082 | H13: 360+ days overdue | I13: GBP | J13: 17203.37 | K13: 2867.23 | L13: 17203.37 | M13: 2867.23 | N13: =IF(I13="GBP",L13-K13,O13-K13) -> 14336.14 | O13: 17203.37 | P13: DMR00820 | Q13: OxStem 4D -single cell culture | R13: Research | S13: Pending Close | T13: Organic Chemistry | U13: Russell, Prof. Angela | V13: g- 22/08/24 email from Robert Bough to Stephen - The Company is still disputing parts of the invoices, and we continue to rebut their arguments. Angela Lintern is completely up to speed with the latest position. | W13: N/A
A14: Oxstem Oncology Ltd | B14: 70397 | C14: 210090929 | D14: 43979 | E14: 44009 | F14: 46091 | G14: 2082 | H14: 360+ days overdue | I14: GBP | J14: 40663.25 | K14: 6777.21 | L14: 40663.25 | M14: 6777.21 | N14: =IF(I14="GBP",L14-K14,O14-K14) -> 33886.04 | O14: 40663.25 | P14: DMR00830 | Q14: Oxstem Oncology | R14: Research | S14: Pending Close | T14: Organic Chemistry | U14: Russell, Prof. Angela | V14: g- 22/08/24 email from Robert Bough to Stephen - The Company is still disputing parts of the invoices, and we continue to rebut their arguments. Angela Lintern is completely up to speed with the latest position. | W14: N/A
A15: M Squared Lasers Ltd | B15: 74596 | C15: 210090966 | D15: 43983 | E15: 44013 | F15: 46091 | G15: 2078 | H15: 360+ days overdue | I15: GBP | J15: 3836.57 | K15: 639.43 | L15: 3836.57 | M15: 639.43 | N15: =IF(I15="GBP",L15-K15,O15-K15) -> 3197.14 | O15: 3836.57 | P15: BWR00971 | Q15: M Squared/Emptage KTP | R15: Research | S15: Pending Close | T15: Pharmacology | U15: Emptage, Prof. Nigel | V15: g- 16/07/25 email from Graeme - We would pay £4895 in first 2 weeks of August then £10k per month Sept-Dec. Could that work to get this finished off. 17/07/25 email to Graeme - Thanks for your email, yes that will work and agree to this payment plan. 27/08/25 email to Graeme - Can you let me know if the initial payment of £4,895.00 has been made? 24/09/25 email to Graeme Malcolm - Have you and update on when we will receive the expected payments. 29/10/25 email from Jimmy (dept) to James B - Would it be worth my PI who worked with them getting in touch? I will reach out to him now. 01/12/2025 email from James B to Heidi (dept) - For BWR00971, we haven’t yet created a specific provision for this debt. I would like to set up a departmental provision for this, £36,674.68 as calculated below, charged to BW0000, when we compile our Q2 bad debt provision. Would this be acceptable to you? 01/12/2025 email from Heidi to James - Many thanks for both of your replies, much appreciated. The dept is happy to accept your suggestions re both debts. Please let us know if you need us to do anything else, pending any provision we add to our Q2 figures. 02/12/2025 email from James to Heidi - Many thanks for getting back to me Heidi. We’ll create the agreed provisions during our usual quarterly BDP process, in early Feb 2026 (for the Jan-26 books). No further action required from you on this point. 21/01/2026 email to Graeme Malcolm - We are yet to receive any payments per your email can you let me know when payment will begin. | W15: KTP010823
A16: Oxstem Beta | B16: 75557 | C16: 210092020 | D16: 44004 | E16: 44034 | F16: 46091 | G16: 2057 | H16: 360+ days overdue | I16: GBP | J16: 27410.85 | K16: 4568.48 | L16: 27410.85 | M16: 4568.48 | N16: =IF(I16="GBP",L16-K16,O16-K16) -> 22842.37 | O16: 27410.85 | P16: AVR02100 | Q16: JCantley-OxStem Beta P.Priming | R16: Research | S16: Pending Close | T16: Physiology Anatomy and Genetic | U16: Cantley, Dr. James | V16: g- 22/08/24 email from Robert Bough to Stephen - The Company is still disputing parts of the invoices, and we continue to rebut their arguments. Angela Lintern is completely up to speed with the latest position. | W16: n/a
A17: M Squared Lasers Ltd | B17: 74596 | C17: 210092267 | D17: 44013 | E17: 44043 | F17: 46091 | G17: 2048 | H17: 360+ days overdue | I17: GBP | J17: 3836.57 | K17: 639.43 | L17: 3836.57 | M17: 639.43 | N17: =IF(I17="GBP",L17-K17,O17-K17) -> 3197.14 | O17: 3836.57 | P17: BWR00971 | Q17: M Squared/Emptage KTP | R17: Research | S17: Pending Close | T17: Pharmacology | U17: Emptage, Prof. Nigel | V17: g- 16/07/25 email from Graeme - We would pay £4895 in first 2 weeks of August then £10k per month Sept-Dec. Could that work to get this finished off. 17/07/25 email to Graeme - Thanks for your email, yes that will work and agree to this payment plan. 27/08/25 email to Graeme - Can you let me know if the initial payment of £4,895.00 has been made? 24/09/25 email to Graeme Malcolm - Have you and update on when we will receive the expected payments. 29/10/25 email from Jimmy (dept) to James B - Would it be worth my PI who worked with them getting in touch? I will reach out to him now. 01/12/2025 email from James B to Heidi (dept) - For BWR00971, we haven’t yet created a specific provision for this debt. I would like to set up a departmental provision for this, £36,674.68 as calculated below, charged to BW0000, when we compile our Q2 bad debt provision. Would this be acceptable to you? 01/12/2025 email from Heidi to James - Many thanks for both of your replies, much appreciated. The dept is happy to accept your suggestions re both debts. Please let us know if you need us to do anything else, pending any provision we add to our Q2 figures. 02/12/2025 email from James to Heidi - Many thanks for getting back to me Heidi. We’ll create the agreed provisions during our usual quarterly BDP process, in early Feb 2026 (for the Jan-26 books). No further action required from you on this point. 21/01/2026 email to Graeme Malcolm - We are yet to receive any payments per your email can you let me know when payment will begin. | W17: KTP010823
A18: M Squared Lasers Ltd | B18: 74596 | C18: 210094024 | D18: 44056 | E18: 44086 | F18: 46091 | G18: 2005 | H18: 360+ days overdue | I18: GBP | J18: 3836.57 | K18: 639.43 | L18: 3836.57 | M18: 639.43 | N18: =IF(I18="GBP",L18-K18,O18-K18) -> 3197.14 | O18: 3836.57 | P18: BWR00971 | Q18: M Squared/Emptage KTP | R18: Research | S18: Pending Close | T18: Pharmacology | U18: Emptage, Prof. Nigel | V18: g- 16/07/25 email from Graeme - We would pay £4895 in first 2 weeks of August then £10k per month Sept-Dec. Could that work to get this finished off. 17/07/25 email to Graeme - Thanks for your email, yes that will work and agree to this payment plan. 27/08/25 email to Graeme - Can you let me know if the initial payment of £4,895.00 has been made? 24/09/25 email to Graeme Malcolm - Have you and update on when we will receive the expected payments. 29/10/25 email from Jimmy (dept) to James B - Would it be worth my PI who worked with them getting in touch? I will reach out to him now. 01/12/2025 email from James B to Heidi (dept) - For BWR00971, we haven’t yet created a specific provision for this debt. I would like to set up a departmental provision for this, £36,674.68 as calculated below, charged to BW0000, when we compile our Q2 bad debt provision. Would this be acceptable to you? 01/12/2025 email from Heidi to James - Many thanks for both of your replies, much appreciated. The dept is happy to accept your suggestions re both debts. Please let us know if you need us to do anything else, pending any provision we add to our Q2 figures. 02/12/2025 email from James to Heidi - Many thanks for getting back to me Heidi. We’ll create the agreed provisions during our usual quarterly BDP process, in early Feb 2026 (for the Jan-26 books). No further action required from you on this point. 21/01/2026 email to Graeme Malcolm - We are yet to receive any payments per your email can you let me know when payment will begin. | W18: KTP010823
A19: M Squared Lasers Ltd | B19: 74596 | C19: 210094327 | D19: 44075 | E19: 44105 | F19: 46091 | G19: 1986 | H19: 360+ days overdue | I19: GBP | J19: 3836.57 | K19: 639.43 | L19: 3836.57 | M19: 639.43 | N19: =IF(I19="GBP",L19-K19,O19-K19) -> 3197.14 | O19: 3836.57 | P19: BWR00971 | Q19: M Squared/Emptage KTP | R19: Research | S19: Pending Close | T19: Pharmacology | U19: Emptage, Prof. Nigel | V19: g- 16/07/25 email from Graeme - We would pay £4895 in first 2 weeks of August then £10k per month Sept-Dec. Could that work to get this finished off. 17/07/25 email to Graeme - Thanks for your email, yes that will work and agree to this payment plan. 27/08/25 email to Graeme - Can you let me know if the initial payment of £4,895.00 has been made? 24/09/25 email to Graeme Malcolm - Have you and update on when we will receive the expected payments. 29/10/25 email from Jimmy (dept) to James B - Would it be worth my PI who worked with them getting in touch? I will reach out to him now. 01/12/2025 email from James B to Heidi (dept) - For BWR00971, we haven’t yet created a specific provision for this debt. I would like to set up a departmental provision for this, £36,674.68 as calculated below, charged to BW0000, when we compile our Q2 bad debt provision. Would this be acceptable to you? 01/12/2025 email from Heidi to James - Many thanks for both of your replies, much appreciated. The dept is happy to accept your suggestions re both debts. Please let us know if you need us to do anything else, pending any provision we add to our Q2 figures. 02/12/2025 email from James to Heidi - Many thanks for getting back to me Heidi. We’ll create the agreed provisions during our usual quarterly BDP process, in early Feb 2026 (for the Jan-26 books). No further action required from you on this point. 21/01/2026 email to Graeme Malcolm - We are yet to receive any payments per your email can you let me know when payment will begin. | W19: KTP010823
A20: Oxstem Cardio Limited | B20: 71939 | C20: 210094739 | D20: 44082 | E20: 44112 | F20: 46091 | G20: 1979 | H20: 360+ days overdue | I20: GBP | J20: 754499.15 | K20: 125749.86 | L20: 754499.15 | M20: 125749.86 | N20: =IF(I20="GBP",L20-K20,O20-K20) -> 628749.29 | O20: 754499.15 | P20: DMR00970 | Q20: OxStem Cardio | R20: Research | S20: Pending Close | T20: Organic Chemistry | U20: Russell, Prof. Angela | V20: g- 22/08/24 email from Robert Bough to Stephen - The Company is still disputing parts of the invoices, and we continue to rebut their arguments. Angela Lintern is completely up to speed with the latest position.
A21: OxStem Neuro Ltd | B21: 70872 | C21: 210095194 | D21: 44097 | E21: 44127 | F21: 46091 | G21: 1964 | H21: 360+ days overdue | I21: GBP | J21: 232489.77 | K21: 38748.3 | L21: 232489.77 | M21: 38748.3 | N21: =IF(I21="GBP",L21-K21,O21-K21) -> 193741.47 | O21: 232489.77 | P21: DMR00870 | Q21: OxStem Neuro | R21: Research | S21: Pending Close | T21: Organic Chemistry | U21: Russell, Prof. Angela | V21: g- 22/08/24 email from Robert Bough to Stephen - The Company is still disputing parts of the invoices, and we continue to rebut their arguments. Angela Lintern is completely up to speed with the latest position. | W21: N/A
A22: M Squared Lasers Ltd | B22: 74596 | C22: 210095389 | D22: 44105 | E22: 44135 | F22: 46091 | G22: 1956 | H22: 360+ days overdue | I22: GBP | J22: 3836.57 | K22: 639.43 | L22: 3836.57 | M22: 639.43 | N22: =IF(I22="GBP",L22-K22,O22-K22) -> 3197.14 | O22: 3836.57 | P22: BWR00971 | Q22: M Squared/Emptage KTP | R22: Research | S22: Pending Close | T22: Pharmacology | U22: Emptage, Prof. Nigel | V22: g- 16/07/25 email from Graeme - We would pay £4895 in first 2 weeks of August then £10k per month Sept-Dec. Could that work to get this finished off. 17/07/25 email to Graeme - Thanks for your email, yes that will work and agree to this payment plan. 27/08/25 email to Graeme - Can you let me know if the initial payment of £4,895.00 has been made? 24/09/25 email to Graeme Malcolm - Have you and update on when we will receive the expected payments. 29/10/25 email from Jimmy (dept) to James B - Would it be worth my PI who worked with them getting in touch? I will reach out to him now. 01/12/2025 email from James B to Heidi (dept) - For BWR00971, we haven’t yet created a specific provision for this debt. I would like to set up a departmental provision for this, £36,674.68 as calculated below, charged to BW0000, when we compile our Q2 bad debt provision. Would this be acceptable to you? 01/12/2025 email from Heidi to James - Many thanks for both of your replies, much appreciated. The dept is happy to accept your suggestions re both debts. Please let us know if you need us to do anything else, pending any provision we add to our Q2 figures. 02/12/2025 email from James to Heidi - Many thanks for getting back to me Heidi. We’ll create the agreed provisions during our usual quarterly BDP process, in early Feb 2026 (for the Jan-26 books). No further action required from you on this point. 21/01/2026 email to Graeme Malcolm - We are yet to receive any payments per your email can you let me know when payment will begin. | W22: KTP010823
A23: M Squared Lasers Ltd | B23: 74596 | C23: 210096997 | D23: 44137 | E23: 44167 | F23: 46091 | G23: 1924 | H23: 360+ days overdue | I23: GBP | J23: 3836.57 | K23: 639.43 | L23: 3836.57 | M23: 639.43 | N23: =IF(I23="GBP",L23-K23,O23-K23) -> 3197.14 | O23: 3836.57 | P23: BWR00971 | Q23: M Squared/Emptage KTP | R23: Research | S23: Pending Close | T23: Pharmacology | U23: Emptage, Prof. Nigel | V23: g- 16/07/25 email from Graeme - We would pay £4895 in first 2 weeks of August then £10k per month Sept-Dec. Could that work to get this finished off. 17/07/25 email to Graeme - Thanks for your email, yes that will work and agree to this payment plan. 27/08/25 email to Graeme - Can you let me know if the initial payment of £4,895.00 has been made? 24/09/25 email to Graeme Malcolm - Have you and update on when we will receive the expected payments. 29/10/25 email from Jimmy (dept) to James B - Would it be worth my PI who worked with them getting in touch? I will reach out to him now. 01/12/2025 email from James B to Heidi (dept) - For BWR00971, we haven’t yet created a specific provision for this debt. I would like to set up a departmental provision for this, £36,674.68 as calculated below, charged to BW0000, when we compile our Q2 bad debt provision. Would this be acceptable to you? 01/12/2025 email from Heidi to James - Many thanks for both of your replies, much appreciated. The dept is happy to accept your suggestions re both debts. Please let us know if you need us to do anything else, pending any provision we add to our Q2 figures. 02/12/2025 email from James to Heidi - Many thanks for getting back to me Heidi. We’ll create the agreed provisions during our usual quarterly BDP process, in early Feb 2026 (for the Jan-26 books). No further action required from you on this point. 21/01/2026 email to Graeme Malcolm - We are yet to receive any payments per your email can you let me know when payment will begin. | W23: KTP010823
A24: M Squared Lasers Ltd | B24: 74596 | C24: 210097911 | D24: 44166 | E24: 44196 | F24: 46091 | G24: 1895 | H24: 360+ days overdue | I24: GBP | J24: 3836.57 | K24: 639.43 | L24: 3836.57 | M24: 639.43 | N24: =IF(I24="GBP",L24-K24,O24-K24) -> 3197.14 | O24: 3836.57 | P24: BWR00971 | Q24: M Squared/Emptage KTP | R24: Research | S24: Pending Close | T24: Pharmacology | U24: Emptage, Prof. Nigel | V24: g- 16/07/25 email from Graeme - We would pay £4895 in first 2 weeks of August then £10k per month Sept-Dec. Could that work to get this finished off. 17/07/25 email to Graeme - Thanks for your email, yes that will work and agree to this payment plan. 27/08/25 email to Graeme - Can you let me know if the initial payment of £4,895.00 has been made? 24/09/25 email to Graeme Malcolm - Have you and update on when we will receive the expected payments. 29/10/25 email from Jimmy (dept) to James B - Would it be worth my PI who worked with them getting in touch? I will reach out to him now. 01/12/2025 email from James B to Heidi (dept) - For BWR00971, we haven’t yet created a specific provision for this debt. I would like to set up a departmental provision for this, £36,674.68 as calculated below, charged to BW0000, when we compile our Q2 bad debt provision. Would this be acceptable to you? 01/12/2025 email from Heidi to James - Many thanks for both of your replies, much appreciated. The dept is happy to accept your suggestions re both debts. Please let us know if you need us to do anything else, pending any provision we add to our Q2 figures. 02/12/2025 email from James to Heidi - Many thanks for getting back to me Heidi. We’ll create the agreed provisions during our usual quarterly BDP process, in early Feb 2026 (for the Jan-26 books). No further action required from you on this point. 21/01/2026 email to Graeme Malcolm - We are yet to receive any payments per your email can you let me know when payment will begin. | W24: KTP010823
A25: Engineering & Physical Sciences Research Council | B25: 2422 | C25: 210098445 | D25: 44173 | E25: 44203 | F25: 46091 | G25: 1888 | H25: 360+ days overdue | I25: GBP | J25: -4385 | K25: 0 | L25: -4385 | M25: 0 | N25: =IF(I25="GBP",L25-K25,O25-K25) -> -4385 | O25: -4385 | P25: DJR01070 | Q25: Sir Henry Royce Institute - OE | R25: Research | S25: Pending Close | T25: Materials | U25: Grant, Prof. Patrick | V25: d- 03/10/25 email from Laura to grants post award - With regards to my email below, specifically the following, I don’t seem to have received a repose: With regards to DJR01070 EP/R010145/1 Please find attached the FES which was submitted. You will see that it reports a balance of £4,385. Which matches the credit we have on file. I don’t therefore see that there is any additional work required here. Only for you to take the credit/offset against future remit. As I understand it we still have the income. Can you please take a look into this and take the credit/offset against future remit? 07/10/25 email from Laura - I chased DJR01070 today. 17/11/2025 email from Maurice Guiry to Laura - Thank you for your email correspondence dated 03/10/2025 (copy appended below). The purpose of this email is to notify you that the UKRI Grants Post Award team has now generated a Supplementary Expenditure Statement (SES) deliverable for Grant reference number EP/R010145/1. The SES is scheduled to be issued overnight and should appear in your Je-S portal by tomorrow morning. 19/11/2025 email from Laura - Please see the email below. Basically no action at all for us. Just a mechanism for the debt to be settled. 19/11/2025 email from Laura - Thank you for this information Maurice. 18/12/2025 email from Maurice to Laura - This email is sent to advise you that grant reference EP/R010145/1 has now been re-reconciled, and a final balance payment of [-£4385.00] will be recovered from your organisation in the next pay run. | W25: EP/R010145/1
A26: Oxstem Cardio Limited | B26: 71939 | C26: 210100467 | D26: 44218 | E26: 44248 | F26: 46091 | G26: 1843 | H26: 360+ days overdue | I26: GBP | J26: 749559.52 | K26: 124926.59 | L26: 749559.52 | M26: 124926.59 | N26: =IF(I26="GBP",L26-K26,O26-K26) -> 624632.93 | O26: 749559.52 | P26: DMR00970 | Q26: OxStem Cardio | R26: Research | S26: Pending Close | T26: Organic Chemistry | U26: Russell, Prof. Angela | V26: g- 22/08/24 email from Robert Bough to Stephen - The Company is still disputing parts of the invoices, and we continue to rebut their arguments. Angela Lintern is completely up to speed with the latest position.
A27: University of Leicester | B27: 3607 | C27: 210104961 | D27: 44339 | E27: 44369 | F27: 46091 | G27: 1722 | H27: 360+ days overdue | I27: GBP | J27: 125834.25 | K27: 0 | L27: 125834.25 | M27: 0 | N27: =IF(I27="GBP",L27-K27,O27-K27) -> 125834.25 | O27: 125834.25 | P27: HJR00080 | Q27: UK TAVI | R27: Research | S27: Pending Close | T27: Surgical Sciences | U27: Morgan, Dr. Lauren | V27: g- 31/07/25 email from Barbara Kitchener to Paul Hogben - In Zoe’s absence, I wonder whether you could liaise with Wayne (cc’d) in Research Accounts about progress with Oxford’s signature of this accession agreement as there is a pressing contract end date, and analysis to complete, of 30 September 2025 (background detailed below). 01/08/25 email from Paul to various - Can you forward me a copy of the draft agreement please. Can you also give me a little more background (apologies, Im not familiar with this grant). Assuming this relates to Oxford grant code HJR00080 (Barabra – please confirm) we don’t currently seem to have an active agreement. Looking at our files the last VTC we had was until 31 October 2023. 01/08/25 email from Bill Toff to Paul - Attached is the email that was circulated some weeks ago, which includes the draft agreement (Variation 03) as one of the attachments. Are you free to speak or meet in Teams briefly and I can fill you in on the background? 16/10/25 email to Paul Hogben - With reference to the emails below regarding project HJR00080 can you let me know if there is any update? 06/11/25 email from Paul Hogben - Apologies for the delayed reply, I was on leave and struggling to get through the backlog or e mails. I've cc'd John Gilbert as NDS are the lead department, but as far as Im aware a contract amendment to reduce Oxfords budget was signed of by Research Servies and sent back to Leicester. 23/01/2026 email to Paul & John - Thanks for your email, can you let me know if the contract amendments have been resolved. | W27: RM61G0394 - NIHR 09-55-63
A28: EH Group Engineering AG | B28: 80947 | C28: 210108391 | D28: 44428 | E28: 44458 | F28: 46091 | G28: 1633 | H28: 360+ days overdue | I28: GBP | J28: 62500 | K28: 0 | L28: 36000 | M28: 0 | N28: =IF(I28="GBP",L28-K28,O28-K28) -> 36000 | O28: 36000 | P28: DHR01390 | Q28: Oxford HydroFuel | R28: Research | S28: Pending Close | T28: Inorganic Chemistry | U28: Edwards, Prof. Peter | V28: g- 21/02/25 email from Chris - Aiming for next tranche by mid March which should be get us below 20k, and close it altogether by end of April (funding deadline for the current raise). 02/05/25 email to Chris - Thanks for your email, can you let me know when we can expect the next payment. 20/05/25 further chase to Chris. 29/05/25 email from Chris Brandon - Nice to hear from you and sorry for the radio silence. Been a challenging period in climate-tech to put it mildly. As such we have had to seek alternative sources of funding than traditional VC crowd – we have a few advanced routes to completing our funding which has taken much longer than anticipated, and are aiming to wrap it up in mid-July. Oxford not forgotten, nor our outstanding invoices – working very hard to get the funding across the line and close this up. 22/07/25 email to Chris - Thanks for your email, how is your funding process getting on is there any update. 08/08/25 chase to Chris. 22/10/25 email to Christopher Brandon - Can you let me know when we can expect the final payment of £36,000.00. 19/01/2026 email to Chris - We still have the outstanding balance of £36,000.00 to be paid against the invoice can you let me know when this will be paid? 19/02/2026 final demand letter sent. 26/02/2026 email from Chris Brandon - Sorry for the late notice, we have been battling for several months to get paid by the Dutch government for an 8.5M EUR contract we have secured. The second tranche was due in December and is now due next week – we should be able to start clearing this during the month of March. Attaching the contract for full transparency.
A29: European Commission | B29: 5367 | C29: 210111066 | D29: 44489 | E29: 44519 | F29: 46091 | G29: 1572 | H29: 360+ days overdue | I29: EUR | J29: 41394.62 | K29: 0 | L29: 7021.66 | M29: 0 | N29: =IF(I29="GBP",L29-K29,O29-K29) -> 6160.1 | O29: 6160.1 | P29: HSR00310 | Q29: BETA3_LVH | R29: Research | S29: Pending Close | T29: RDM Cardiovascular Medicine | U29: Casadei, Prof Barbara | V29: d- Payment expected end of January 2026 | W29: 634559
A30: Economic & Social Research Council | B30: 8101 | C30: 210111282 | D30: 44495 | E30: 44525 | F30: 46091 | G30: 1566 | H30: 360+ days overdue | I30: GBP | J30: 96590.72 | K30: 0 | L30: 15010 | M30: 0 | N30: =IF(I30="GBP",L30-K30,O30-K30) -> 15010 | O30: 15010 | P30: EPR01230 | Q30: CGHE TRANSFER | R30: Research | S30: Pending Close | T30: Education | U30: Marginson, Prof. Simon | V30: b- 03/10/25 email from Maurice Guiry (post award) - Thank you for your email concerning Grant reference number ES/M010082/2 and dated 18/08/2025. I am sorry for the delay in acknowledging it. With regard to your question about why the grant only received funds in the amount of £2,002,290.38 rather than funds in the amount of £2,039,928.17 as you would have expected. While reviewing the grant’s reconciliation history I encountered an issue that meant I have had to escalate your query to my line manager. I will contact you again as soon as I receive any further information on the matter. 06/11/2026 email from Maurice Guiry - In summary, expenditure reported of £2,039,928.17 only received the payment amount of £2,002,290.38” due to the Exceptions Other Costs heading being overspent, whilst this fund heading should have only been paid up to £167,275.22. However, due to an exceptional arrangement with ESRC a further £84,372.69 was paid as a manual payment to the RO to allow some of the funds unspent from Exceptions equipment to pay against other costs incurred. So, in total the correct payment figure against this grant = SES reconciliation Q3 22/23 £1,917917.69. Plus, the £84,372.69 paid as manual payment Total paid = £2,002,290.38. 23/02/2026 email to Daniel - Please see the email below regarding project EPR01230 and invoices 210111282 & 210123182, can you look into this with the department and let me know the outcome. | W30: ES/M010082/2
A31: European Commission | B31: 5367 | C31: 210111584 | D31: 44505 | E31: 44535 | F31: 46091 | G31: 1556 | H31: 360+ days overdue | I31: EUR | J31: 1043093.4 | K31: 0 | L31: 56940.8 | M31: 0 | N31: =IF(I31="GBP",L31-K31,O31-K31) -> 48374.06 | O31: 48374.06 | P31: DMR00910 | Q31: ENABLE. | R31: Research | S31: Pending Close | T31: Organic Chemistry | U31: Schofield, Prof Christopher | V31: g- 10/02/2026 email from Anders Karlen - We are writing to inform you that we have received €123 977,43 from the appointed liquidator of JUVABIS AG to be distributed to ENABLE beneficiaries that have suffered a financial loss deriving from the misuse of pre-financing by JUVABIS AG. It represents approximately 22% of the losses. In order to reduce the administrative burden of executing the payments, the distribution cut-off will be 500 EUR, representing nineteen of thirty-one partners with a financial loss. Please contact us if you have any questions related to this final payment. Thank you for your cooperation. We will contact you to check the financial details of your organization shortly. 10/02/2026 email from Tequila to the dept plus - Please see the email below and the attached final payment for UOXF following the liquidators’ distribution. Our share of the payment is €16,404.94. | W31: 115583
A32: European Commission | B32: 5367 | C32: 210115272 | D32: 44600 | E32: 44630 | F32: 46091 | G32: 1461 | H32: 360+ days overdue | I32: EUR | J32: 15397.83 | K32: 0 | L32: 15397.83 | M32: 0 | N32: =IF(I32="GBP",L32-K32,O32-K32) -> 13081.23 | O32: 13081.23 | P32: DMR00910 | Q32: ENABLE. | R32: Research | S32: Pending Close | T32: Organic Chemistry | U32: Schofield, Prof Christopher | V32: g- 10/02/2026 email from Anders Karlen - We are writing to inform you that we have received €123 977,43 from the appointed liquidator of JUVABIS AG to be distributed to ENABLE beneficiaries that have suffered a financial loss deriving from the misuse of pre-financing by JUVABIS AG. It represents approximately 22% of the losses. In order to reduce the administrative burden of executing the payments, the distribution cut-off will be 500 EUR, representing nineteen of thirty-one partners with a financial loss. Please contact us if you have any questions related to this final payment. Thank you for your cooperation. We will contact you to check the financial details of your organization shortly. 10/02/2026 email from Tequila to the dept plus - Please see the email below and the attached final payment for UOXF following the liquidators’ distribution. Our share of the payment is €16,404.94. | W32: 115583
A33: European Commission | B33: 5367 | C33: 210115677 | D33: 44620 | E33: 44650 | F33: 46091 | G33: 1441 | H33: 360+ days overdue | I33: EUR | J33: 54317.42 | K33: 0 | L33: 14600.3 | M33: 0 | N33: =IF(I33="GBP",L33-K33,O33-K33) -> 12547.52 | O33: 12547.52 | P33: ATR00950 | Q33: COMBACTE-MAGNET | R33: Research | S33: Pending Close | T33: Zoology | U33: Maclean, Prof Roderick | V33: d- Payment expected end of January 2026
A34: European Commission | B34: 5367 | C34: 210117780 | D34: 44662 | E34: 44692 | F34: 46091 | G34: 1399 | H34: 360+ days overdue | I34: EUR | J34: 5070.42 | K34: 0 | L34: 5070.42 | M34: 0 | N34: =IF(I34="GBP",L34-K34,O34-K34) -> 4302.2 | O34: 4302.2 | P34: DMR00910 | Q34: ENABLE. | R34: Research | S34: Pending Close | T34: Organic Chemistry | U34: Schofield, Prof Christopher | V34: g- 10/02/2026 email from Anders Karlen - We are writing to inform you that we have received €123 977,43 from the appointed liquidator of JUVABIS AG to be distributed to ENABLE beneficiaries that have suffered a financial loss deriving from the misuse of pre-financing by JUVABIS AG. It represents approximately 22% of the losses. In order to reduce the administrative burden of executing the payments, the distribution cut-off will be 500 EUR, representing nineteen of thirty-one partners with a financial loss. Please contact us if you have any questions related to this final payment. Thank you for your cooperation. We will contact you to check the financial details of your organization shortly. 10/02/2026 email from Tequila to the dept plus - Please see the email below and the attached final payment for UOXF following the liquidators’ distribution. Our share of the payment is €16,404.94. | W34: 115583
A35: European Commission | B35: 5367 | C35: 210118418 | D35: 44685 | E35: 44715 | F35: 46091 | G35: 1376 | H35: 360+ days overdue | I35: EUR | J35: 94210.68 | K35: 0 | L35: 52100.03 | M35: 0 | N35: =IF(I35="GBP",L35-K35,O35-K35) -> 44408.5 | O35: 44408.5 | P35: HMR01870 | Q35: IMPRiND | R35: Research | S35: Pending Close | T35: Clinical Neurosciences | U35: Tofaris, Prof George | V35: d- Payment expected end of January 2026 | W35: 116060-1
A36: European Commission | B36: 5367 | C36: 210119510 | D36: 44721 | E36: 44751 | F36: 46091 | G36: 1340 | H36: 360+ days overdue | I36: EUR | J36: 4927.44 | K36: 0 | L36: 4927.44 | M36: 0 | N36: =IF(I36="GBP",L36-K36,O36-K36) -> 4200 | O36: 4200 | P36: HMR01870 | Q36: IMPRiND | R36: Research | S36: Pending Close | T36: Clinical Neurosciences | U36: Tofaris, Prof George | V36: d- Payment expected end of January 2026 | W36: 116060-1
A37: European Commission | B37: 5367 | C37: 210119534 | D37: 44722 | E37: 44752 | F37: 46091 | G37: 1339 | H37: 360+ days overdue | I37: EUR | J37: 42459.15 | K37: 0 | L37: 6238.94 | M37: 0 | N37: =IF(I37="GBP",L37-K37,O37-K37) -> 5304.03 | O37: 5304.03 | P37: YDR00330 | Q37: MetCogCon | R37: Research | S37: Pending Close | T37: Philosophy Faculty | U37: Sanders, Dr Rachael | V37: d- Payment expected end of January 2026 | W37: 681422
A38: Wellcome Trust | B38: 7186 | C38: 210121303 | D38: 44761 | E38: 44791 | F38: 46091 | G38: 1300 | H38: 360+ days overdue | I38: GBP | J38: 304758.58 | K38: 0 | L38: 15068.12 | M38: 0 | N38: =IF(I38="GBP",L38-K38,O38-K38) -> 15068.12 | O38: 15068.12 | P38: ALR00850 | Q38: Micron renewal fr Jan 2016 | R38: Research | S38: Pending Close | T38: Biochemistry | U38: Davis, Prof Ilan | V38: b- 04/02/2026 comment from Ciaran - WT Comments: This grant ended on 25/12/2021, and the FER was submitted on 08/03/2022, according to our records. The final payment of £480,101.03 was issued to your organisation on 21/06/2022. 04/02/2026 email to Ciaran - Re project ALR00850 – 210121303 balance of £15,068.12, I had a look at the remit received Wellcome paid the amount of £480,101.03 but only the amount of £464,816.13 was applied to the invoices – difference of £15,284.90, the reason for this is re project CQR01880 they paid £7,786.15 but only £6,931.17 was applied re invoice 210119027 leaving a balance of £854.78, re project CFR00580 they were taking back the amount of £17,494.60 but only the amount of £1,355.12 was available re credit 210117993 difference of £16,138.48. | W38: 107457/Z/15/Z
A39: Oxford University Hospitals NHS Foundation Trust | B39: 3667 | C39: 210122470 | D39: 44783 | E39: 44813 | F39: 46091 | G39: 1278 | H39: 360+ days overdue | I39: GBP | J39: 11149.23 | K39: 0 | L39: 11149.23 | M39: 0 | N39: =IF(I39="GBP",L39-K39,O39-K39) -> 11149.23 | O39: 11149.23 | P39: HSR00820 | Q39: AMGEN | R39: Research | S39: Pending Close | T39: RDM Cardiovascular Medicine | U39: Rodgers, Dr. Christopher | V39: g- 22/07/25 email from Melissa (dept) to Nigel Byng - Please can I follow-up on the below? It appears this invoice is still outstanding. 22/07/25 email from Nigel - It probably is and I have to admit I have been out of the loop on the detail since Feb. I’m just back from leave so will loot at it this week 😊 17/09/25 list of outstanding invoices sent to various at OUP. 29/10/25 email to Nigel Byng - Can you help would you be able to let me know who can advise on the payment status of the attached invoice. 29/10/25 email from Nigel - I didn’t recognise it on first sight (I see so many) but it has come back to me now – see attached. Richard – can you have a discussion with Dylan from RDM for us please to try and bottom out the status of this invoice ? Its starting to suck up quite a lot of time for various individuals in the OU and the Trust, but there is little we can do about it. 17/12/2025 email from Dylan (dept) to James - I will follow up again with OUH about this one but I haven't received a response from my last two chasers. I also cannot see that Richard followed up with us about this one as per Nigel's reply in the notes below for 29/10/2025. 17/12/2025 email from James B to Dylan - Do you know who this Richard is? Can you contact them directly? 17/12/2025 email from Dylan to James - Yes, I have been emailing both Richard and Nigel about this. Hopefully I hear back this time. 21/01/2026 email from Dylan (dept) to Joel Atkin - I continue to chase this up with Richard but have not received a reply yet. Nigel from OUH is replying to my emails asking Richard to respond to me but still nothing. Is there any advice on how I should proceed going forward as I am not sure I'm making much progress here. | W39: PID12548
A40: Sichuan University | B40: 25069 | C40: 210122524 | D40: 44784 | E40: 44814 | F40: 46091 | G40: 1277 | H40: 360+ days overdue | I40: GBP | J40: 20000 | K40: 0 | L40: 20000 | M40: 0 | N40: =IF(I40="GBP",L40-K40,O40-K40) -> 20000 | O40: 20000 | P40: BBR00211 | Q40: WCH Student funds | R40: Research | S40: Approved | T40: Cancer Centre | U40: Middleton, Prof Mark | V40: g- 25/11/2025 email from Mae to Ruoting - Many thanks for the update — that is excellent news. We greatly appreciate you and your colleagues' efforts, and it is reassuring that future transactions should move more smoothly once this year’s process is completed. With the infrastructure invoice now progressing through your internal system, I would also like to kindly follow up on the two invoices under the separate Visiting Scholar Support Agreement. As these fall outside the infrastructure contract and are processed through different financial streams on our side, it would be very helpful if they could also be settled through your finance office. Clearing these will allow us to move ahead with preparing the next round of scholar visits and project proposals. 15/01/2026 email from Mae (dept) - FYI – I tried to get David to prompt Sichuan University before the holidays. I hadn’t heard back and in the new year, I nudged to make sure he had sent something. Please see next email for the response (08/01/2026 email from David Kerr - This was their immediate response to my wechat message. In san Francisco for a week at conference etc). | W40: N/A
A41: Economic & Social Research Council | B41: 8101 | C41: 210123182 | D41: 44812 | E41: 44842 | F41: 46091 | G41: 1249 | H41: 360+ days overdue | I41: GBP | J41: 22627.79 | K41: 0 | L41: 22627.79 | M41: 0 | N41: =IF(I41="GBP",L41-K41,O41-K41) -> 22627.79 | O41: 22627.79 | P41: EPR01230 | Q41: CGHE TRANSFER | R41: Research | S41: Pending Close | T41: Education | U41: Marginson, Prof. Simon | V41: b- 03/10/25 email from Maurice Guiry (post award) - Thank you for your email concerning Grant reference number ES/M010082/2 and dated 18/08/2025. I am sorry for the delay in acknowledging it. With regard to your question about why the grant only received funds in the amount of £2,002,290.38 rather than funds in the amount of £2,039,928.17 as you would have expected. While reviewing the grant’s reconciliation history I encountered an issue that meant I have had to escalate your query to my line manager. I will contact you again as soon as I receive any further information on the matter. 06/11/2026 email from Maurice Guiry - In summary, expenditure reported of £2,039,928.17 only received the payment amount of £2,002,290.38” due to the Exceptions Other Costs heading being overspent, whilst this fund heading should have only been paid up to £167,275.22. However, due to an exceptional arrangement with ESRC a further £84,372.69 was paid as a manual payment to the RO to allow some of the funds unspent from Exceptions equipment to pay against other costs incurred. So, in total the correct payment figure against this grant = SES reconciliation Q3 22/23 £1,917917.69. Plus, the £84,372.69 paid as manual payment Total paid = £2,002,290.38. 23/02/2026 email to Daniel - Please see the email below regarding project EPR01230 and invoices 210111282 & 210123182, can you look into this with the department and let me know the outcome. | W41: ES/M010082/2
A42: European Commission | B42: 5367 | C42: 210123348 | D42: 44824 | E42: 44854 | F42: 46091 | G42: 1237 | H42: 360+ days overdue | I42: EUR | J42: 131448.56 | K42: 0 | L42: 38933.81 | M42: 0 | N42: =IF(I42="GBP",L42-K42,O42-K42) -> 33101.91 | O42: 33101.91 | P42: HNR00610 | Q42: PERISCOPE | R42: Research | S42: Pending Close | T42: Paediatrics | U42: Kelly, Dr Dominic | V42: d- Payment expected end of January 2026 | W42: 115910-2
A43: Economic & Social Research Council | B43: 8101 | C43: 210123448 | D43: 44827 | E43: 44857 | F43: 46091 | G43: 1234 | H43: 360+ days overdue | I43: GBP | J43: -468.33 | K43: 0 | L43: -205.51 | M43: 0 | N43: =IF(I43="GBP",L43-K43,O43-K43) -> -205.51 | O43: -205.51 | P43: CQR01670 | Q43: Resilience to adolescent Psych | R43: Research | S43: Pending Close | T43: Experimental Psychology | U43: Fox, Prof Elaine | V43: e- 29/07/25 email from Laura - 29/07 SeS currently back with Jenny. Due 08/08. 07/10/25 email from Laura - With regards to the other two the SESs have been done. So would expect the Councils to offset these credits in future remits shortly. 16/12/2025 email from the post award team to Laura - This email is sent to advise you that the re-reconciliation of grant reference ES/R004285/1 has now been completed by using expenditure details taken from the Supplementary Expenditure Statement (SES) submitted on 30/10/2025. The final balance payment of [-£205.50] will be recovered from your organisation in the next pay run. | W43: ES/R004285/1
A44: European Commission | B44: 5367 | C44: 210123964 | D44: 44833 | E44: 44863 | F44: 46091 | G44: 1228 | H44: 360+ days overdue | I44: EUR | J44: 11052.33 | K44: 0 | L44: 11052.33 | M44: 0 | N44: =IF(I44="GBP",L44-K44,O44-K44) -> 9396.8 | O44: 9396.8 | P44: HNR00610 | Q44: PERISCOPE | R44: Research | S44: Pending Close | T44: Paediatrics | U44: Kelly, Dr Dominic | V44: d- Payment expected end of January 2026 | W44: 115910-2
A45: European Commission | B45: 5367 | C45: 210125534 | D45: 44866 | E45: 44896 | F45: 46091 | G45: 1195 | H45: 360+ days overdue | I45: EUR | J45: 16290.21 | K45: 0 | L45: 16290.21 | M45: 0 | N45: =IF(I45="GBP",L45-K45,O45-K45) -> 13778.75 | O45: 13778.75 | P45: HSR00310 | Q45: BETA3_LVH | R45: Research | S45: Pending Close | T45: RDM Cardiovascular Medicine | U45: Casadei, Prof Barbara | V45: d- Payment expected end of January 2026 | W45: 634559
A46: European Commission | B46: 5367 | C46: 210126886 | D46: 44909 | E46: 44939 | F46: 46091 | G46: 1152 | H46: 360+ days overdue | I46: EUR | J46: 3756.42 | K46: 0 | L46: 3756.42 | M46: 0 | N46: =IF(I46="GBP",L46-K46,O46-K46) -> 3193.75 | O46: 3193.75 | P46: HNR00610 | Q46: PERISCOPE | R46: Research | S46: Pending Close | T46: Paediatrics | U46: Kelly, Dr Dominic | V46: d- Payment expected end of January 2026 | W46: 115910-2
A47: European Commission | B47: 5367 | C47: 210127949 | D47: 44931 | E47: 44961 | F47: 46091 | G47: 1130 | H47: 360+ days overdue | I47: EUR | J47: 14547.66 | K47: 0 | L47: 14547.66 | M47: 0 | N47: =IF(I47="GBP",L47-K47,O47-K47) -> 12955.88 | O47: 12955.88 | P47: ATR00950 | Q47: COMBACTE-MAGNET | R47: Research | S47: Pending Close | T47: Zoology | U47: Maclean, Prof Roderick | V47: d- Payment expected end of January 2026
A48: European Commission | B48: 5367 | C48: 210130735 | D48: 45008 | E48: 45038 | F48: 46091 | G48: 1053 | H48: 360+ days overdue | I48: EUR | J48: 202272.69 | K48: 0 | L48: 32382.91 | M48: 0 | N48: =IF(I48="GBP",L48-K48,O48-K48) -> 27867.11 | O48: 27867.11 | P48: HCR00570 | Q48: EAVI2020 | R48: Research | S48: Pending Close | T48: Jenner Institute | U48: Hanke, Prof Tomas | V48: d- Payment expected end of January 2026 | W48: 681137
A49: National Institute for Health Research | B49: 44423 | C49: 210132127 | D49: 45027 | E49: 45057 | F49: 46091 | G49: 1034 | H49: 360+ days overdue | I49: GBP | J49: 6111.96 | K49: 0 | L49: 4764.65 | M49: 0 | N49: =IF(I49="GBP",L49-K49,O49-K49) -> 4764.65 | O49: 4764.65 | P49: HMR02080 | Q49: TIMBER | R49: Research | S49: Pending Close | T49: Clinical Neurosciences | U49: Kyle, Dr Simon | V49: b- 25/09/25 email from Tehseen to finance - Apologies for the delay in this. I can confirm that the dissemination costs are now fully spent as per the FSTOX and that there are no more costs for this one. 12/11/2025 email from Tehseen - This relates to the balance for invoices 210118336 and 210132127. Small balance remains which I will query with the dept as to fi they will put more costs on or if we need to return some of the funds. 16/12/2025 email to Tehseen - I believe this should be paid. 09/02/2026 chase to Nets finance. 09/02/2026 email from Sandra Light - We are looking into these, I have just looked at 16/84/01, and I can see this one is now fully paid, with the last payment being made on the 31/10/25. 09/02/2026 email to Ellie - Please see the email below regarding invoice 210132127 on the above project, the last payment of £21,600.00 see attached was applied to the following it seems no further payment will be made, can you look into this and let me know the outcome. 04/03/2026 email from Ellie to Sarah Light - I can see that the final payment was sent based on an estimated dissemination figure of £21,600. However, we were actually given approval to spend up to £27,000 in dissemination costs based on the attached email from Roderick on 17th December 2021 in response to Simon's email making the request. Therefore, there is not actually an underspend of £4,764.64 as detailed on the FSTOX and we believe a further payment of £4,371.02 would be due. Are we able to provide an FSTOX confirming final costs as I can't see that we were ever asked to complete a post-dissemination FSTOX? | W49: 536034 - 16/84/01, DoH 123010
A50: Royal Brompton & Harefield NHS Trust | B50: 4845 | C50: 210133121 | D50: 45056 | E50: 45086 | F50: 46091 | G50: 1005 | H50: 360+ days overdue | I50: GBP | J50: 21429.68 | K50: 0 | L50: 2363 | M50: 0 | N50: =IF(I50="GBP",L50-K50,O50-K50) -> 2363 | O50: 2363 | P50: BXR01140 | Q50: MARS-2 | R50: Research | S50: Pending Close | T50: Population Health | U50: Stokes, Dr Elizabeth | V50: e- 02/07/25 email from Bharkavi to ap - Please can we get these invoices paid as a matter of urgency? POs also attached. 04/08/25 email to various - Can you let me know the payment status of invoice 210134662 copy attached, also regarding invoice 210133121 - £21,429.68 we received the attached payment of £19,066.68 which our Cashers department could not identify, they applied the payment to invoice 210133121 as they did not know what the payment was for but we are left with a balance against the invoice of £2,363.00, also attached is invoice 210138299 can you let me know the payment status of this. 04/08/25 email from Bkarkavi Srikuma to Dawn & Susan - Please can you get back to Wayne regarding this? 22/10/25 email to various - Can I have an update on the payment status of the attached invoices. 22/10/25 email from Dawn Clarke - Please can I have the order number for the below invoice. 22/10/25 email from Bharkavi to Dawn - Please see attached. 22/10/25 email from Dawn - Thanks I still can’t see the purchase order numbers on any of this documentation? 16/12/2025 email to various - Can I have an update on when the attached invoices will be paid, , also regarding invoice 210133121 - £21,429.68 we received the attached payment of £19,066.68 which our Cashers department could not identify, they applied the payment to invoice 210133121 as they did not know what the payment was for but we are left with a balance against the invoice of £2,363.00. 23/01/2026 further chase to various. 04/02/2026 new PO received and invoice reissued. payment 10/03/2026 | W50: 6632/51012
A51: European Commission | B51: 5367 | C51: 210133743 | D51: 45078 | E51: 45108 | F51: 46091 | G51: 983 | H51: 360+ days overdue | I51: EUR | J51: 98791.6 | K51: 0 | L51: 75654.89 | M51: 0 | N51: =IF(I51="GBP",L51-K51,O51-K51) -> 64837 | O51: 64837 | P51: YDR00610 | Q51: RESPONSIBILITY. | R51: Research | S51: Pending Close | T51: Philosophy Faculty | U51: Hyman, Prof. John | V51: d- Payment expected end of January 2026 | W51: 789270
A52: European Commission | B52: 5367 | C52: 210133891 | D52: 45085 | E52: 45115 | F52: 46091 | G52: 976 | H52: 360+ days overdue | I52: EUR | J52: 368696.92 | K52: 0 | L52: 40579.99 | M52: 0 | N52: =IF(I52="GBP",L52-K52,O52-K52) -> 35079.78 | O52: 35079.78 | P52: HER00670 | Q52: IMI-PainCare | R52: Research | S52: Pending Close | T52: Women’s & Reproductive Healt | U52: Vincent, Dr Katy | V52: d- Payment expected end of January 2026 | W52: 777500
A53: European Commission | B53: 5367 | C53: 210134648 | D53: 45106 | E53: 45136 | F53: 46091 | G53: 955 | H53: 360+ days overdue | I53: EUR | J53: 760.14 | K53: 0 | L53: 760.14 | M53: 0 | N53: =IF(I53="GBP",L53-K53,O53-K53) -> 676.97 | O53: 676.97 | P53: ATR00950 | Q53: COMBACTE-MAGNET | R53: Research | S53: Pending Close | T53: Zoology | U53: Maclean, Prof Roderick | V53: d- Payment expected end of January 2026
A54: Royal Brompton & Harefield NHS Trust | B54: 4845 | C54: 210134662 | D54: 45106 | E54: 45136 | F54: 46091 | G54: 955 | H54: 360+ days overdue | I54: GBP | J54: 31340.75 | K54: 0 | L54: 31340.75 | M54: 0 | N54: =IF(I54="GBP",L54-K54,O54-K54) -> 31340.75 | O54: 31340.75 | P54: HBR02880 | Q54: J Stradling - RfPB (Brompton) | R54: Research | S54: Pending Close | T54: NDM Experimental Medicine | U54: Stradling, Prof John | V54: d- 02/07/25 email from Bharkavi to ap - Please can we get these invoices paid as a matter of urgency? POs also attached. 04/08/25 email to various - Can you let me know the payment status of invoice 210134662 copy attached, also regarding invoice 210133121 - £21,429.68 we received the attached payment of £19,066.68 which our Cashers department could not identify, they applied the payment to invoice 210133121 as they did not know what the payment was for but we are left with a balance against the invoice of £2,363.00, also attached is invoice 210138299 can you let me know the payment status of this. 04/08/25 email from Bkarkavi Srikuma to Dawn & Susan - Please can you get back to Wayne regarding this? 22/10/25 email to various - Can I have an update on the payment status of the attached invoices. 22/10/25 email from Dawn Clarke - Please can I have the order number for the below invoice. 22/10/25 email from Bharkavi to Dawn - Please see attached. 22/10/25 email from Dawn - Thanks I still can’t see the purchase order numbers on any of this documentation? 16/12/2025 email to various - Can I have an update on when the attached invoices will be paid, , also regarding invoice 210133121 - £21,429.68 we received the attached payment of £19,066.68 which our Cashers department could not identify, they applied the payment to invoice 210133121 as they did not know what the payment was for but we are left with a balance against the invoice of £2,363.00. 23/01/2026 further chase to various. 02/02/2026 New PO received invoice resubmitted. | W54: PB-PG-0817-20049
A55: Pixstory Global Holding Inc | B55: 88693 | C55: 210135764 | D55: 45125 | E55: 45155 | F55: 46091 | G55: 936 | H55: 360+ days overdue | I55: GBP | J55: 103530 | K55: 0 | L55: 103530 | M55: 0 | N55: =IF(I55="GBP",L55-K55,O55-K55) -> 103530 | O55: 103530 | P55: CZR01180 | Q55: Internet Social Good | R55: Research | S55: Pending Close | T55: Oxford Internet Institute | U55: Schroeder, Prof Ralph | V55: g- 02/09/24 copy emails forwarded to Duncan. 23/10/24 email from Kathleen Parsons to James - Just to confirm we are following up with a letter with regards to this debt and writing from the department to see what we can recover. Legal have advised a strongly worded letter and we will see what response we get. 21/01/25 email to Duncan Passey - Re the above project did a legal letter get sent to the funder re the outstanding debt? 22/01/25 email from Duncan - Let me check with both our Head of Admin and Research Facilitation team and I’ll get back once I have an answer. 03/03/25 email to Duncan - Thanks for your email, can you let me know if there is any update? 10/03/25 email from Duncan - Adding in our joint Head of Admin, Joanna Barlow, who was looking into this and can provide an update. (Jo – this was the Pixstory grant debt). 28/05/25 email to Jo Barlow - Re the Pixstory grant is there any update on the situation. 08/08/25 email to Jo Barlow - Can you let me know if there is any update with the above project. 21/08/25 email from James B to Duncan - We’ve been waiting for her to respond for a while, so I thought I’d give you a nudge to see what was going on! Thanks for getting back to me so quickly. When is Jo back? We would greatly appreciate it if you would ask her to get in touch with us, many thanks! 21/08/25 email from Duncan - Back on 1 September – added to my handover list for her return! 22/10/25 email to Duncan - Is there any update from Jo re the above project? 22/10/25 email from Duncan - Sorry no, she does have on her to do list but hasn’t got round to it yet.
A56: European Commission | B56: 5367 | C56: 210136178 | D56: 45133 | E56: 45163 | F56: 46091 | G56: 928 | H56: 360+ days overdue | I56: EUR | J56: 231280.98 | K56: 0 | L56: 13931.82 | M56: 0 | N56: =IF(I56="GBP",L56-K56,O56-K56) -> 12113.3 | O56: 12113.3 | P56: HMR02420 | Q56: AIMS-2-TRIALS | R56: Research | S56: Pending Close | T56: Clinical Neurosciences | U56: Cader, Prof Muhammed | V56: d- Payment expected end of January 2026 | W56: 777394
A57: European Commission | B57: 5367 | C57: 210136499 | D57: 45141 | E57: 45171 | F57: 46091 | G57: 920 | H57: 360+ days overdue | I57: EUR | J57: 3133.97 | K57: 0 | L57: 3133.97 | M57: 0 | N57: =IF(I57="GBP",L57-K57,O57-K57) -> 2720 | O57: 2720 | P57: YDR00330 | Q57: MetCogCon | R57: Research | S57: Pending Close | T57: Philosophy Faculty | U57: Sanders, Dr Rachael | V57: d- Payment expected end of January 2026 | W57: 681422
A58: Royal Society | B58: 3610 | C58: 210136524 | D58: 45141 | E58: 45171 | F58: 46091 | G58: 920 | H58: 360+ days overdue | I58: GBP | J58: 41023.64 | K58: 0 | L58: 7118.81 | M58: 0 | N58: =IF(I58="GBP",L58-K58,O58-K58) -> 7118.81 | O58: 7118.81 | P58: DJR01800 | Q58: QCheMG | R58: Research | S58: Pending Close | T58: Materials | U58: Bogani, Prof Lapo | V58: b- 10/10/25 email from Matthew to Lucy Hill - I just wanted to follow up on Laura’s email (copied below) regarding the outstanding payment of £7,118.81 on this award. Have you had a chance to review this? Email from Matthew - 14/11/2025 - Follow up email sent to Lucy regarding the £7k payment. Email from Matthew - 12/12/25 - Follow up email sent to Lucy regarding the £7k payment. 13/01/2026 email from Matthew - 07/01/26 - Follow up email sent. 13/02/26 - Follow up email sent. 19/02/2026 email from Lucy Hill to Laura - thank you for sending this over, apologies again for the delay, I’ve been looking at the award and I still can’t see any documentation that confirms the increase in 7k, from the £676035.9 that has been paid out on the award. 19/02/2026 email from Matthew to Lucy Hill - Please could you provide your detailed budget breakdown at your earliest convenience? Once received, we will reconcile this against our own breakdown (see below) and identify any variances. For our understanding, could you please clarify whether the “amount offered” refers to the total budget you have recorded as awarded to us for this project? We just want to ensure we are aligned, as the total awarded budget and the income actually received can represent two different sums. | W58: URF\R\191030
A59: European Commission | B59: 5367 | C59: 210137064 | D59: 45169 | E59: 45199 | F59: 46091 | G59: 892 | H59: 360+ days overdue | I59: EUR | J59: 347029.86 | K59: 0 | L59: 93213.35 | M59: 0 | N59: =IF(I59="GBP",L59-K59,O59-K59) -> 81056.05 | O59: 81056.05 | P59: ALR01910 | Q59: PEP-NET | R59: Research | S59: Pending Close | T59: Biochemistry | U59: Mellor, Prof Elizabeth | V59: d- Payment expected end of January 2026 | W59: 813282
A60: European Commission | B60: 5367 | C60: 210151363 | D60: 45169 | E60: 45199 | F60: 46091 | G60: 892 | H60: 360+ days overdue | I60: EUR | J60: 619938.74 | K60: 0 | L60: 65384 | M60: 0 | N60: =IF(I60="GBP",L60-K60,O60-K60) -> 56421.16 | O60: 56421.16 | P60: ALR01430 | Q60: OMPORG | R60: Research | S60: Pending Close | T60: Biochemistry | U60: Kleanthous, Prof Kleanthis | V60: d- Payment expected end of January 2026 | W60: 742555
A61: Wellcome Trust | B61: 7186 | C61: 210139310 | D61: 45199 | E61: 45229 | F61: 46091 | G61: 862 | H61: 360+ days overdue | I61: GBP | J61: 60367.27 | K61: 0 | L61: 21073.62 | M61: 0 | N61: =IF(I61="GBP",L61-K61,O61-K61) -> 21073.62 | O61: 21073.62 | P61: BVR00110 | Q61: Genetic control | R61: Research | S61: Approved | T61: Dunn School of Pathology | U61: Robertson, Prof Elizabeth | V61: f- Retention | W61: 102811/Z/13/Z
A62: Santersus AG | B62: 98913 | C62: 210138168 | D62: 45201 | E62: 45231 | F62: 46091 | G62: 860 | H62: 360+ days overdue | I62: GBP | J62: 30074.26 | K62: 0 | L62: 8906.08 | M62: 0 | N62: =IF(I62="GBP",L62-K62,O62-K62) -> 8906.08 | O62: 8906.08 | P62: HJR02470 | Q62: Santersus ACLs | R62: Research | S62: Approved | T62: Surgical Sciences | U62: Friend, Prof Peter | V62: g- 15/07/25 email to Aleksander & finance - I’m being chased by our head of finance for an update on when next payments will be made have you an update. 23/07/25 email from Aleksander - As part of our regular updates, we wish to inform you that, due to the seasonal vacation period, finalizing the paperwork for the fundraising round has encountered a brief delay. This is purely procedural in nature and does not reflect any change in the intentions of the involved parties or in the agreed terms. All substantive matters have been successfully concluded, and our legal teams are diligently working to complete the formal documentation. Given the international nature of the parties involved, slight scheduling constraints may arise over the coming summer weeks. We sincerely appreciate your continued patience and understanding and remain committed to keeping you informed as we progress toward closure. 16/10/25 email to Alexsander - Thanks for your email below, can you let me know if there is any update? 19/10/25 email from Aleksander - Thank you for checking in. I was hoping to surprise you with some good news, but you beat me to it :) We're just about to wrap up our fundraising round, and we expect the first tranche to land in early November. Immediately afterward, we’ll begin normalizing our payment discipline. We're fully committed to getting things back on track as soon as possible. Thanks again for your patience and continued support. 01/12/2025 email to Aleksander - Thanks for your email, can you let me know if there is any update regarding your fundraising. payment of £10,000.00 on 30/12/2025 & 20/01/2026 & 10/02/2026 | W62: R81872
A63: National Institute for Health Research | B63: 44423 | C63: 210138907 | D63: 45212 | E63: 45242 | F63: 46091 | G63: 849 | H63: 360+ days overdue | I63: GBP | J63: 246796.67 | K63: 0 | L63: 246796.67 | M63: 0 | N63: =IF(I63="GBP",L63-K63,O63-K63) -> 246796.67 | O63: 246796.67 | P63: BZR00030 | Q63: BARACK D | R63: Research | S63: Pending Close | T63: Primary Care Health Sciences | U63: Hobbs, Prof Frederick | V63: g- 22/09/25 email to Donna - Please see the email below regarding project BZR00030 (210138907), can you respond to Sarah regarding the FSTOX copying me into the response. Email from Donna - 7/10/25 Anna (dept) is oging to work ont he FSTOX. 05/11/25 email from Donna to Sarah Light - I have reached out to the department about the FSTOX for BZR00030. Have you had any response from the post-award@phc.ox.ac.uk mail box? If you can let me know what the comment/queries are, I shall try to assist in reaching a resolution.10-12-25 emaile department to chase answer to funder queries. email from Donna - 14 1 26 chsed department and gave thema deadline friday 16 1 26. 21/01/2026 email from Felicity (dept) to James B - Attaching an email that Anna Karlinska sent regarding this a couple of weeks ago. By copy of this email I will ask her to advise if any further update yet (06/01/2026 email from Anna (dept) to various - Just to send an update on BZR00030 (BARACK-D ) – I am liaising with the PI regarding final publication/ dissemination costs as those could have been incurred 24 months after the end date (and I believe there might have been discussions about longer period than 2 years). I will reply to NIHR either this or next week). | W63: 12/01/52 # 509248
A64: European Space Agency | B64: 4049 | C64: 210139475 | D64: 45226 | E64: 45256 | F64: 46091 | G64: 835 | H64: 360+ days overdue | I64: EUR | J64: 30000 | K64: 0 | L64: 30000 | M64: 0 | N64: =IF(I64="GBP",L64-K64,O64-K64) -> 24000 | O64: 24000 | P64: DFR05600 | Q64: Studentship - Francesco Pinto | R64: Research | S64: Pending Close | T64: Engineering Science | U64: Torr, Prof Philip | V64: d- 03/02/2026 email to Jonasus - Please see the email below regarding invoice 210139475 – DFR05600, can you look into this and submit the requested on the portal letting me know once done. 09/02/2026 email from Jonasus to the dept - Please may I ask if you can forward the attachment/thesis to us? This email address was not included in the earlier emails of this trail. 09/02/2026 email from Katie (dept) to Jonasus -I have shared the thesis with you, you should receive a OneDrive link. I will forward the other email to you (29/01/2026 email from Katie to Yelania & Gian Lorenzo - My emails were bouncing back yesterday due to the file size of the thesis. I shared the final progress report and the students thesis with your colleague Magda Krajcovicova in November. Please see the email attached. I will send the link to Francesco's thesis to you in a separate email. Please let me know if you have any issues accessing the thesis. 10/02/2026 email from Jonasus to Katie - I assume the submission is fine and no action is needed required from my end? Please note I have tried to amend the existing invoice on the ESA portal, but it says awaiting for approval (also doesn't let me edit or attach documents). 10/02/2026 email from Katie (dept) to Jonasus - ESA did not respond to my emails, I will follow up with them. | W64: n/a
A65: European Commission | B65: 5367 | C65: 210141966 | D65: 45230 | E65: 45260 | F65: 46091 | G65: 831 | H65: 360+ days overdue | I65: EUR | J65: 18230.5 | K65: 0 | L65: 17035.63 | M65: 0 | N65: =IF(I65="GBP",L65-K65,O65-K65) -> 14752.86 | O65: 14752.86 | P65: DCR00870 | Q65: SO-CHIC | R65: Research | S65: Pending Close | T65: Atmospheric Ocean and Planet P | U65: Marshall, Prof David | V65: d- Payment expected end of January 2026 | W65: 821001
A66: European Commission | B66: 5367 | C66: 210139772 | D66: 45236 | E66: 45266 | F66: 46091 | G66: 825 | H66: 360+ days overdue | I66: EUR | J66: 227293.1 | K66: 0 | L66: 387.78 | M66: 0 | N66: =IF(I66="GBP",L66-K66,O66-K66) -> 333.71 | O66: 333.71 | P66: DJR01830 | Q66: ESTEEM3 | R66: Research | S66: Approved | T66: Materials | U66: Kirkland, Prof Angus | V66: d- Payment expected end of January 2026 | W66: 823717
A67: Beijing Niujin Shisong Biotechnology Co., Ltd | B67: 49263 | C67: 210140157 | D67: 45252 | E67: 45282 | F67: 46091 | G67: 809 | H67: 360+ days overdue | I67: GBP | J67: 40000 | K67: 0 | L67: 40000 | M67: 0 | N67: =IF(I67="GBP",L67-K67,O67-K67) -> 40000 | O67: 40000 | P67: ANR00891 | Q67: ROP Technology Platform. | R67: Research | S67: Pending Close | T67: Oncology | U67: Jiang, Dr Shisong | V67: d- 16/12/2025 email to Mrs Zhuang - Can you let me know if there is any update on the processing of payment the outstanding invoice. 19/12/2025 email from Mrs Zhuang - We received a reminder from the Beijing Tax Service Bureau when following up on the filing progress, informing us that this filing does not meet the relevant conditions for designated withholding after review. I have consulted the tax bureau about the relevant matters and prepared some supplementary materials as required to resubmit to the tax bureau. 23/02/2026 email to Mrs Zhuang - Thanks for your email, can you let me know if there is any update? 26/02/2026 email from Mrs Zhuang - Please accept my apologies for the delayed response. I was on leave for the Chinese New Year holiday and am only replying to your email today. I wish to update you on the progress: the contract filing has been approved. I will now proceed with the Tax Filing for External Payments as the next step. | W67: NONE
... A69: European Commission | B69: 5367 | C69: 210140282 | D69: 45257 | E69: 45287 | F69: 46091 | G69: 804 | H69: 360+ days overdue | I69: EUR | J69: 33607.84 | K69: 0 | L69: 33607.84 | M69: 0 | N69: =IF(I69="GBP",L69-K69,O69-K69) -> 29050.28 | O69: 29050.28 | P69: YDR00610 | Q69: RESPONSIBILITY. | R69: Research | S69: Pending Close | T69: Philosophy Faculty | U69: Hyman, Prof. John | V69: d- Payment expected end of January 2026 | W69: 789270
A70: Arcturis Data (UK) Limited | B70: 75029 | C70: 210140736 | D70: 45272 | E70: 45302 | F70: 46091 | G70: 789 | H70: 360+ days overdue | I70: GBP | J70: 116952 | K70: 19492 | L70: 116952 | M70: 19492 | N70: =IF(I70="GBP",L70-K70,O70-K70) -> 97460 | O70: 116952 | P70: HBR04210 | Q70: T Hinks - Sensyne | R70: Research | S70: Pending Close | T70: NDM Experimental Medicine | U70: Hinks, Dr Timothy | V70: g- 16/10/25 email to Jo Hovard - Thanks for your email to James regarding project HBR04210, do you know if there has been any further progress. 17/10/25 email from Jo - Sorry I have chased the PI on this again. 16/10/25 email from Jo Hovard - Please see below from the PI (16/10/25 email from Tim Hinks - It’s still in legal wranglings. They are not going to release the data without charging us 233k. I guess that’s up for negotiation, but they probably won’t give us the last payment or two. It’s with Gavin Brown). 24/12/2025 email from Jo (dept) to James B - You emailed again about the debt on HBR04210, the PI is still in discussion with the Funder and has asked for data as per the email below (11/12/2025 email from Tim Hinks to Robert Durichen - Thank you for your time today and what was a productive meeting. As requested, this is the summary of what we need from Arcturis, please. Robert, if we have further technical details, you and I could correspond without the rest of the cc’d parties. I would likely bring in Kate Elliott for clarifications. We request receipt of the raw data (fastq files) for all sequencing performed on the MORSE cohort to date. Accompanying this data would need to be mappings of Novogene IDs to MORSE IDs). 02/02/2026 email from Jo (dept) to James B - For HBR04210 a meeting was held with Gavin Brown and Legal Services to discuss next steps and Gavin and Legal Services are going to go back to Arcturis to discuss some data. I explained the position of the department and how much costs have already been incurred and the current shortfall on the account if the invoices are not paid. We will need to wait for Gavin and Legal Services to go back to Arcturis.
A71: European Commission | B71: 5367 | C71: 210149965 | D71: 45291 | E71: 45321 | F71: 46091 | G71: 770 | H71: 360+ days overdue | I71: EUR | J71: 264805.4 | K71: 0 | L71: 136590.03 | M71: 0 | N71: =IF(I71="GBP",L71-K71,O71-K71) -> 118804.64 | O71: 118804.64 | P71: HMR02680 | Q71: IM2PACT | R71: Research | S71: Approved | T71: Clinical Neurosciences | U71: Cader, Prof Muhammed | V71: d- Payment expected end of January 2026 | W71: 807015#
A72: Wellcome Trust | B72: 7186 | C72: 210171791 | D72: 45291 | E72: 45321 | F72: 46091 | G72: 770 | H72: 360+ days overdue | I72: GBP | J72: 39086.77 | K72: 0 | L72: 39086.77 | M72: 0 | N72: =IF(I72="GBP",L72-K72,O72-K72) -> 39086.77 | O72: 39086.77 | P72: B9R05210 | Q72: KWTRP Open Access 22/23 | R72: Research | S72: Pending Close | T72: Tropical Medicine | U72: Bejon, Prof Philip | V72: d- 04/02/2026 comment from Ciaran - FER Now Due, RA advisor to be working on. | W72: 226916/Z/23/Z
A73: European Commission | B73: 5367 | C73: 210149978 | D73: 45291 | E73: 45321 | F73: 46091 | G73: 770 | H73: 360+ days overdue | I73: EUR | J73: 30190.48 | K73: 0 | L73: 30190.48 | M73: 0 | N73: =IF(I73="GBP",L73-K73,O73-K73) -> 25745.23 | O73: 25745.23 | P73: HMR02680 | Q73: IM2PACT | R73: Research | S73: Approved | T73: Clinical Neurosciences | U73: Cader, Prof Muhammed | V73: d- Payment expected end of January 2026 | W73: 807015#
A74: Santersus AG | B74: 98913 | C74: 210141470 | D74: 45293 | E74: 45323 | F74: 46091 | G74: 768 | H74: 360+ days overdue | I74: GBP | J74: 30074.26 | K74: 0 | L74: 30074.26 | M74: 0 | N74: =IF(I74="GBP",L74-K74,O74-K74) -> 30074.26 | O74: 30074.26 | P74: HJR02470 | Q74: Santersus ACLs | R74: Research | S74: Approved | T74: Surgical Sciences | U74: Friend, Prof Peter | V74: g- 15/07/25 email to Aleksander & finance - I’m being chased by our head of finance for an update on when next payments will be made have you an update. 23/07/25 email from Aleksander - As part of our regular updates, we wish to inform you that, due to the seasonal vacation period, finalizing the paperwork for the fundraising round has encountered a brief delay. This is purely procedural in nature and does not reflect any change in the intentions of the involved parties or in the agreed terms. All substantive matters have been successfully concluded, and our legal teams are diligently working to complete the formal documentation. Given the international nature of the parties involved, slight scheduling constraints may arise over the coming summer weeks. We sincerely appreciate your continued patience and understanding and remain committed to keeping you informed as we progress toward closure. 16/10/25 email to Alexsander - Thanks for your email below, can you let me know if there is any update? 19/10/25 email from Aleksander - Thank you for checking in. I was hoping to surprise you with some good news, but you beat me to it :) We're just about to wrap up our fundraising round, and we expect the first tranche to land in early November. Immediately afterward, we’ll begin normalizing our payment discipline. We're fully committed to getting things back on track as soon as possible. Thanks again for your patience and continued support. 01/12/2025 email to Aleksander - Thanks for your email, can you let me know if there is any update regarding your fundraising. payment of £10,000.00 on 30/12/2025 & 20/01/2026 & 10/02/2026 | W74: R81872
A75: Wellcome Trust | B75: 7186 | C75: 210141510 | D75: 45293 | E75: 45323 | F75: 46091 | G75: 768 | H75: 360+ days overdue | I75: GBP | J75: 33668.75 | K75: 0 | L75: 6999.8 | M75: 0 | N75: =IF(I75="GBP",L75-K75,O75-K75) -> 6999.8 | O75: 6999.8 | P75: AVR02490 | Q75: SS_WT Collab_Cell fate | R75: Research | S75: Pending Close | T75: Physiology Anatomy and Genetic | U75: Srinivas, Prof Shankar | V75: b- 04/02/2026 comment from Ciaran - Gabrielle to confirm if FER has been submitted. 13/02/2026 email from Gabrielle - 13.02.2026 - FER ready to be submitted, waiting for one final comment from dept to explain overspend on one category. | W75: 220379/C/20/Z
A76: European Commission | B76: 5367 | C76: 210141962 | D76: 45299 | E76: 45329 | F76: 46091 | G76: 762 | H76: 360+ days overdue | I76: EUR | J76: 224933.76 | K76: 0 | L76: 146206.94 | M76: 0 | N76: =IF(I76="GBP",L76-K76,O76-K76) -> 125622.46 | O76: 125622.46 | P76: YDR00880 | Q76: LEWE | R76: Research | S76: Pending Close | T76: Philosophy Faculty | U76: Mcmahan, Prof Jefferson | V76: d- Payment expected end of January 2026 | W76: 101024087
A77: Blue Water Vaccines Inc | B77: 81353 | C77: 210142342 | D77: 45309 | E77: 45339 | F77: 46091 | G77: 752 | H77: 360+ days overdue | I77: GBP | J77: 53500 | K77: 0 | L77: 53500 | M77: 0 | N77: =IF(I77="GBP",L77-K77,O77-K77) -> 53500 | O77: 53500 | P77: ATR03330 | Q77: Blue Water Vaccines | R77: Research | S77: Pending Close | T77: Zoology | U77: Gupta, Prof Sunetra | V77: g- 06/01/25 email from Emma (dept) - Hopefully, we can get a further update soon from Karina. 24/02/25 email to Karina Fedasz - Thanks for your email, can you let me know when you will be able to make payment for the outstanding invoice. 02/05/25 further chase to Karina. 06/05/25 email from Pippa Hitchcock to James B & Wayne - Has there been any further communication on this? I’m happy to contact Karina to check what’s happening if you’ve heard nothing more? Id really like to get this sorted out asap. 06/05/25 Pippa to chase the sponsor. 28/07/25 email to Pippa (dept) - Have you had any luck with Blue Water Vaccines Inc? 27/08/25 chase to Pippa. 23/09/25 email from Donna - Have we had any movement on this final unpaid invoice? Do you need me to do anything? 24/09/25 email to Donna - See the attached emails awaiting a response from Pippa who was contacting the funder. 24/09/25 email from Donna - Thank you. I will reach out to Pippa now. 29/09/25 email from Izzy (dept) - The blue water vaccines – Pippa Hitchcock will contact PI Sunetra Gupta and if she can’t get them to pay it soon, we will cancel the invoice. 29/10/25 email to Izzy (dept) - Thanks for your email, re Blue Water did Pippa or the PI have any luck? | W77: n/a
A78: Tulane University | B78: 63166 | C78: 210142566 | D78: 45315 | E78: 45345 | F78: 46091 | G78: 746 | H78: 360+ days overdue | I78: USD | J78: 14358.94 | K78: 0 | L78: 14358.94 | M78: 0 | N78: =IF(I78="GBP",L78-K78,O78-K78) -> 10636.25 | O78: 10636.25 | P78: HNR02531 | Q78: NIH Grant, Tulane University. | R78: Research | S78: Pending Close | T78: Paediatrics | U78: Song, Dr Rinn | V78: g- 02/05/25 email to the dept - Re the email below from Kyle regarding project HNR02531 is there any update on this. 06/05/25 email from Gabi (dept) to Rinn - Do you have any update on the sample shipping, please? 29/05/25 email from Gabi (dept) to Rinn - Can you possibly update on the sample shipping, please? Adding Euken and Duyen into the email chain who will be your grants contact going forward. 22/07/25 email to the various in the dept - Can you let me know if there is any update on the samples so we can get the two outstanding invoice paid. 22/08/25 email from Euken (dept) to James - Not that I’m aware of. The most recent update I have on why our invoice is in dispute is that it relates to the scope of work. Oxford was responsible for ensuring the shipment of samples, but since the samples have not been shipped, the US lead is withholding payment, stating that we have not delivered on the agreed scope. This issue dates back to May 2025, and Gem was leading the discussions with the PI and the Department. She may be able to provide a further update once she returns from leave next week. 26/08/25 email from Gem Brown to James B - I’m afraid I don’t have any more information that Euken. Attached is the last correspondence I have on this. Parv is currently on leave, so we won’t be able to get anything further until she is back, but I’ll make a note to follow up with her. 20/01/2026 email from Sam Branch to Lucia & Sophie - Euken has asked that I forward the email to you. Can you please update comments and reply to Research Accounts and the Divisional Finance team. | W78: TUL-HSC-559133-21/22
A79: European Commission | B79: 5367 | C79: 210143115 | D79: 45331 | E79: 45361 | F79: 46091 | G79: 730 | H79: 360+ days overdue | I79: EUR | J79: 623054.01 | K79: 0 | L79: 1777.89 | M79: 0 | N79: =IF(I79="GBP",L79-K79,O79-K79) -> 1536.88 | O79: 1536.88 | P79: DCR00620 | Q79: ITHACA | R79: Research | S79: Approved | T79: Atmospheric Ocean and Planet P | U79: Palmer, Prof Timothy | V79: b- 24/10/25 dept to remove costs by mid November due to staff shortage. | W79: 741112
A80: European Commission | B80: 5367 | C80: 210143516 | D80: 45345 | E80: 45375 | F80: 46091 | G80: 716 | H80: 360+ days overdue | I80: EUR | J80: 21900.28 | K80: 0 | L80: 1206.39 | M80: 0 | N80: =IF(I80="GBP",L80-K80,O80-K80) -> 1045.84 | O80: 1045.84 | P80: CMR00040 | Q80: Resolution | R80: Research | S80: Pending Close | T80: Centre for Medicines Discovery | U80: Burgess-Brown, Dr Nicola | V80: d- Payment expected end of January 2026 | W80: 101034439
A81: European Commission | B81: 5367 | C81: 210143669 | D81: 45350 | E81: 45380 | F81: 46091 | G81: 711 | H81: 360+ days overdue | I81: EUR | J81: 250789.4 | K81: 0 | L81: 39065.73 | M81: 0 | N81: =IF(I81="GBP",L81-K81,O81-K81) -> 33887.96 | O81: 33887.96 | P81: H9R00230 | Q81: ReSOLUTE | R81: Research | S81: Approved | T81: Structural Genomics Consortium | U81: Sauer, Dr David | V81: b- 15/12/2025 - Tequila to reconcile checking linked project. | W81: 777372
A82: European Commission | B82: 5367 | C82: 210143650 | D82: 45350 | E82: 45380 | F82: 46091 | G82: 711 | H82: 360+ days overdue | I82: EUR | J82: 114540 | K82: 0 | L82: 20440 | M82: 0 | N82: =IF(I82="GBP",L82-K82,O82-K82) -> 17623.57 | O82: 17623.57 | P82: LDR01030 | Q82: GEOCEP | R82: Research | S82: Approved | T82: Smith School | U82: Hepburn, Prof Cameron | V82: d- Payment expected end of January 2026 | W82: 870245
A83: Hanako Foundation | B83: 81901 | C83: 210143820 | D83: 45357 | E83: 45387 | F83: 46091 | G83: 704 | H83: 360+ days overdue | I83: GBP | J83: 222365 | K83: 0 | L83: 22236 | M83: 0 | N83: =IF(I83="GBP",L83-K83,O83-K83) -> 22236 | O83: 22236 | P83: B9R03660 | Q83: Thai-Seidlein-Hanako | R83: Research | S83: Approved | T83: Tropical Medicine | U83: Von Seidlein, Prof Lorenz | V83: d- 29/07/25 email to Danielle & Ciaran - Thanks for your email, checking the payments we received £264,891.93 of this £32,552.93 was applied to invoice 210137184 with the balance of £232,339.00 being applied to invoice 210142763, so I guess the outstanding balance against invoice 210142763 should be credited? Re invoice 210143820 we received the amount of £200,129.00 leaving a balance of £22,236.00 is this going to be paid? 11/08/25 email from Dori (dept) to Ciaran & Wayne - Regarding 210143820 (invoice 7), £22,236.00 should be paid after the Final report is sent to Hanako. They confirmed that thay already have the narrative report and I’m waiting for @David Kidd to confirm if the financial report was sent too. 12/08/25 email from Dori (dept) to Jennifer Goh - I believe you have received the final study narrative report and financial report. I was wondering if the payment of £22,236 has been approved. Please find the following attachments for your info: Finance report, Invoice, Hanako amendment. 27/10/25 email to Dori (dept) - Can I check did you get any response from Jennifer regarding your email below. 30/10/25 email from Dori (dept) to Jennifer Goh - This is a kind reminder that we are still waiting for your answer; please see my email below in August 2025. Please see the invoice 210143820 here attached which shows 2 descriptions: Final study Narrative Report: £22,236 – still pending - Four Year Study Narrative: £200,129 - paid - I know the project has been extended until 31 June 2026. | W83: NONE
A84: Arcturis Data (UK) Limited | B84: 75029 | C84: 210144935 | D84: 45377 | E84: 45407 | F84: 46091 | G84: 684 | H84: 360+ days overdue | I84: GBP | J84: 116952 | K84: 19492 | L84: 116952 | M84: 19492 | N84: =IF(I84="GBP",L84-K84,O84-K84) -> 97460 | O84: 116952 | P84: HBR04210 | Q84: T Hinks - Sensyne | R84: Research | S84: Pending Close | T84: NDM Experimental Medicine | U84: Hinks, Dr Timothy | V84: g- 16/10/25 email to Jo Hovard - Thanks for your email to James regarding project HBR04210, do you know if there has been any further progress. 17/10/25 email from Jo - Sorry I have chased the PI on this again. 16/10/25 email from Jo Hovard - Please see below from the PI (16/10/25 email from Tim Hinks - It’s still in legal wranglings. They are not going to release the data without charging us 233k. I guess that’s up for negotiation, but they probably won’t give us the last payment or two. It’s with Gavin Brown). 24/12/2025 email from Jo (dept) to James B - You emailed again about the debt on HBR04210, the PI is still in discussion with the Funder and has asked for data as per the email below (11/12/2025 email from Tim Hinks to Robert Durichen - Thank you for your time today and what was a productive meeting. As requested, this is the summary of what we need from Arcturis, please. Robert, if we have further technical details, you and I could correspond without the rest of the cc’d parties. I would likely bring in Kate Elliott for clarifications. We request receipt of the raw data (fastq files) for all sequencing performed on the MORSE cohort to date. Accompanying this data would need to be mappings of Novogene IDs to MORSE IDs). 02/02/2026 email from Jo (dept) to James B - For HBR04210 a meeting was held with Gavin Brown and Legal Services to discuss next steps and Gavin and Legal Services are going to go back to Arcturis to discuss some data. I explained the position of the department and how much costs have already been incurred and the current shortfall on the account if the invoices are not paid. We will need to wait for Gavin and Legal Services to go back to Arcturis.
A85: Oxford Hospitals Charity | B85: 7502 | C85: 210145021 | D85: 45378 | E85: 45408 | F85: 46091 | G85: 683 | H85: 360+ days overdue | I85: GBP | J85: 18470.4 | K85: 0 | L85: 18470.4 | M85: 0 | N85: =IF(I85="GBP",L85-K85,O85-K85) -> 18470.4 | O85: 18470.4 | P85: HER01530 | Q85: Exposure to red light | R85: Research | S85: Approved | T85: Women’s & Reproductive Healt | U85: Poulton, Prof Joanna | V85: g- 11/12/24 email from George Kearse to Oscar - I’m afraid the previous invoices are still in contention and I still don’t yet have an update, so I don’t recommend that any further invoices be raised for now at least. 08/01/25 email from Oscar to Page (dept) - HER01530 ended 02-Dec-2024, has there been any update on the disputed invoices? 08/01/25 email from Page to Oscar - Not yet, the last communication I had with the funder was just before Christmas so I’m guessing they’re catching up on things after the holidays. 13/02/25 email from Oscar - 07/02/25 Dept confirmed discussions still in progress with funder regarding disputed invoices. Email from Oscar - 06/03/25 Dept still chasing funder. 17/06/25 email from Oscar - Chased dept. 16/07/25 email from Oscar - Dept waiting for finance manager Tony Nobes to return from long term leave before this can be resolved. 17/06/25 email from Page (dept) to Oscar - Unfortunately not. I have passed this over to our finance manager Tony (cc’d) to determine how the department will proceed with the debt, but he is currently on long-term leave. @Sarah I’m looping you into this & can provide the background separately, but I appreciate you may not be able to advise until Tony and/or Lesa return. 20/08/25 email from Oscar - Chased dept now that Tony has returned from leave. 11/09/25 email from Oscar - Escalating within dept, sent chaser. Email from Oscar - Sent chaser to dept 08/10/25. Email from Oscar - 12/11/25 Sent chaser to dept. 07/01/2026 email from Oscar - Junaid chasing dept for resolution. | W85: GN- 10767#11233
A86: Santersus AG | B86: 98913 | C86: 210145053 | D86: 45383 | E86: 45413 | F86: 46091 | G86: 678 | H86: 360+ days overdue | I86: GBP | J86: 30074.26 | K86: 0 | L86: 30074.26 | M86: 0 | N86: =IF(I86="GBP",L86-K86,O86-K86) -> 30074.26 | O86: 30074.26 | P86: HJR02470 | Q86: Santersus ACLs | R86: Research | S86: Approved | T86: Surgical Sciences | U86: Friend, Prof Peter | V86: g- 15/07/25 email to Aleksander & finance - I’m being chased by our head of finance for an update on when next payments will be made have you an update. 23/07/25 email from Aleksander - As part of our regular updates, we wish to inform you that, due to the seasonal vacation period, finalizing the paperwork for the fundraising round has encountered a brief delay. This is purely procedural in nature and does not reflect any change in the intentions of the involved parties or in the agreed terms. All substantive matters have been successfully concluded, and our legal teams are diligently working to complete the formal documentation. Given the international nature of the parties involved, slight scheduling constraints may arise over the coming summer weeks. We sincerely appreciate your continued patience and understanding and remain committed to keeping you informed as we progress toward closure. 16/10/25 email to Alexsander - Thanks for your email below, can you let me know if there is any update? 19/10/25 email from Aleksander - Thank you for checking in. I was hoping to surprise you with some good news, but you beat me to it :) We're just about to wrap up our fundraising round, and we expect the first tranche to land in early November. Immediately afterward, we’ll begin normalizing our payment discipline. We're fully committed to getting things back on track as soon as possible. Thanks again for your patience and continued support. 01/12/2025 email to Aleksander - Thanks for your email, can you let me know if there is any update regarding your fundraising. payment of £10,000.00 on 30/12/2025 & 20/01/2026 & 10/02/2026 | W86: R81872
A87: British Heart Foundation | B87: 7239 | C87: 210145851 | D87: 45400 | E87: 45430 | F87: 46091 | G87: 661 | H87: 360+ days overdue | I87: GBP | J87: 134441.34 | K87: 0 | L87: 134441.34 | M87: 0 | N87: =IF(I87="GBP",L87-K87,O87-K87) -> 134441.34 | O87: 134441.34 | P87: HSR01720 | Q87: OxVALVE_BHF Special Project | R87: Research | S87: Approved | T87: RDM Cardiovascular Medicine | U87: Myerson, Dr Saul | V87: b- 15/02/2026 email from Ami to Dylan & Lucy - Thank you for you the below. I have replied in red for ease. 25/02/2026 email from Dylan (dept) to Ami - Apologies for the delay. I have removed the £50 travel cost as discussed. I have contacted the OUH team about your salary queries too and will update you as soon as I have heard back. Lucy - sorry but I think we need to re-run this invoice please and if possible make it clearer that the conferences and travel expenditure are grouped together, so not £500 on the invoice but £661.93 now that I have removed £50. I think we also need to try and make the Other Costs clearer because the OUH costs should all be Non-Oxford Other and I think they are being grouped into the normal Other Costs on the first page of the invoice. I am happy to try and split this out on a new draft if that is easier? | W87: SP/F/22/150035
A88: Polestar Performance AB | B88: 107433 | C88: 210146006 | D88: 45405 | E88: 45435 | F88: 46091 | G88: 656 | H88: 360+ days overdue | I88: GBP | J88: 30000 | K88: 5000 | L88: 5000 | M88: 833.33 | N88: =IF(I88="GBP",L88-K88,O88-K88) -> 0 | O88: 5000 | P88: DHR01990 | Q88: eliminating GHG emissions | R88: Research | S88: Closed | T88: Inorganic Chemistry | U88: Williams, Prof Charlotte | V88: d- 02/04/25 email from Sandra Pettersson - Thanks for your email and respond and yes, I confirm the final invoice and the final amount to be paid is £5,000.00. @POLFIN, POLFIN – please find attached credit , @Duguay, Carley – please procced with internal process after POLFIN has booked the credits. 08/04/25 email from Sandra - Is seams we need a root invoice ? do you have that ? 09/04/25 email to Sandra - invoice attached. 06/06/25 email to Sandra Pettersson - Can you let me know if there is any update regarding the attached invoice. 09/06/25 email from Sandra - Have you sent in the new and correct invoice to d Invoice to:invoice.PolestarPerformanceAB.SE63@ap.volvocars.biz ? @PPABap – could you please support and see if attached invoice has been paid ? and let us know when ? 08/08/25 email to various - Can you let me know if the attached invoice has been approved for payment. 24/10/25 statemment of account forwarded as requested. 24/10/25 email from Elisa Litjens (ap support) - Thank you for your email with the statement of account. We appreciate your input and will forward and validate your feedback with our client. If further clarification is needed, we will contact you. 09/02/2026 chase to Eliza. 09/02/2026 chase to the finance team. 09/02/2026 email from Mark Mihaila - I have made a request to the payment team to provide more details on why this invoice is not yet paid. | W88: N/A
A89: National Institute for Health Research | B89: 44423 | C89: 210146084 | D89: 45407 | E89: 45437 | F89: 46091 | G89: 654 | H89: 360+ days overdue | I89: GBP | J89: 15820.11 | K89: 0 | L89: 15820.11 | M89: 0 | N89: =IF(I89="GBP",L89-K89,O89-K89) -> 15820.11 | O89: 15820.11 | P89: HMR03220 | Q89: NIHR DRF JB Dec 18 | R89: Research | S89: Pending Close | T89: Clinical Neurosciences | U89: Bedford, Dr Jonathan | V89: d- 13/08/25 email from Tehseen - Will check status of FSTOX with Laura as there is a signed one already. 20/08/25 email from Tehseen - Apologies for the delay in this, I have a had a look and I can see that the FTSOX was sent. Kay did have confirm receipt but had some queries regarding so I am guessing there still some queries outstanding. Have emailed Kay and CC'd you in, will follow up with the department once I get confirmation of what the queries outstanding are. 20/08/25 email from Tehseen to academy awards - For project reference NIHR300224 I wanted to check if you have any outstanding queries regarding the FSTOX? I believe the FSTOX was submitted to yourselves in April 2024 so I wanted to check whether there were any queries regarding it due to the final invoice for this award still being outstanding. 10/09/25 email from Tehseen - Emailed NIHR on 20/08/2025 asking what outstanding queries there are for the FSTOX, no reply yet. 10/10/25 email to Tehseen to academy awards - I just wanted to check if there was any update on this and whether there were any outstanding queries? 12/11/2025 email from Tehseen - Doesn't seem like there is any action from RA required, FSTOX was submitted and no known queries from the funder. Emailed the funder 20/08/2025 and 10/10/2025, no response. I believ they should pay the invoice. 09/02/2026 chase to academy awards. | W89: NIHR300224#545704
A90: Oxford Hospitals Charity | B90: 7502 | C90: 210146946 | D90: 45434 | E90: 45464 | F90: 46091 | G90: 627 | H90: 360+ days overdue | I90: GBP | J90: 15519.54 | K90: 0 | L90: 15519.54 | M90: 0 | N90: =IF(I90="GBP",L90-K90,O90-K90) -> 15519.54 | O90: 15519.54 | P90: HER01530 | Q90: Exposure to red light | R90: Research | S90: Approved | T90: Women’s & Reproductive Healt | U90: Poulton, Prof Joanna | V90: g- 11/12/24 email from George Kearse to Oscar - I’m afraid the previous invoices are still in contention and I still don’t yet have an update, so I don’t recommend that any further invoices be raised for now at least. 08/01/25 email from Oscar to Page (dept) - HER01530 ended 02-Dec-2024, has there been any update on the disputed invoices? 08/01/25 email from Page to Oscar - Not yet, the last communication I had with the funder was just before Christmas so I’m guessing they’re catching up on things after the holidays. 13/02/25 email from Oscar - 07/02/25 Dept confirmed discussions still in progress with funder regarding disputed invoices. Email from Oscar - 06/03/25 Dept still chasing funder. 17/06/25 email from Oscar - Chased dept. 16/07/25 email from Oscar - Dept waiting for finance manager Tony Nobes to return from long term leave before this can be resolved. 17/06/25 email from Page (dept) to Oscar - Unfortunately not. I have passed this over to our finance manager Tony (cc’d) to determine how the department will proceed with the debt, but he is currently on long-term leave. @Sarah I’m looping you into this & can provide the background separately, but I appreciate you may not be able to advise until Tony and/or Lesa return. 20/08/25 email from Oscar - Chased dept now that Tony has returned from leave. 11/09/25 email from Oscar - Escalating within dept, sent chaser. Email from Oscar - Sent chaser to dept 08/10/25. Email from Oscar - 12/11/25 Sent chaser to dept. 07/01/2026 email from Oscar - Junaid chasing dept for resolution. | W90: GN- 10767#11233
A91: European Commission | B91: 5367 | C91: 210147096 | D91: 45442 | E91: 45472 | F91: 46091 | G91: 619 | H91: 360+ days overdue | I91: EUR | J91: 91013.88 | K91: 0 | L91: 5654.8 | M91: 0 | N91: =IF(I91="GBP",L91-K91,O91-K91) -> 4905.71 | O91: 4905.71 | P91: DLR00930 | Q91: AIDAinnova | R91: Research | S91: Pending Close | T91: Particle Physics | U91: Bortoletto, Prof Daniela | V91: d- Payment expected end of January 2026 | W91: 101004761
A92: European Commission | B92: 5367 | C92: 210151345 | D92: 45447 | E92: 45477 | F92: 46091 | G92: 614 | H92: 360+ days overdue | I92: EUR | J92: 391839.17 | K92: 0 | L92: 5403.01 | M92: 0 | N92: =IF(I92="GBP",L92-K92,O92-K92) -> 4646.21 | O92: 4646.21 | P92: BKR01120 | Q92: ACB | R92: Research | S92: Approved | T92: Mathematical Institute | U92: Alday, Prof Luis | V92: d- Payment expected end of January 2026 | W92: 787185#
A93: Kaleibe Therapeutics Inc. | B93: 100353 | C93: 210147379 | D93: 45453 | E93: 45483 | F93: 46091 | G93: 608 | H93: 360+ days overdue | I93: GBP | J93: 400316.05 | K93: 0 | L93: 400316.05 | M93: 0 | N93: =IF(I93="GBP",L93-K93,O93-K93) -> 400316.05 | O93: 400316.05 | P93: AVR03170 | Q93: RichardWM_therapeutic gene | R93: Research | S93: Approved | T93: Physiology Anatomy and Genetic | U93: Wade-Martins, Prof Richard | V93: g- 21/05/25 email from Sally Vine to James B - By way of update, we have recently exchanged legal letters with the funder. Our current offer is to terminate the agreement on payment of a sum that covers the direct costs and provides some overheads but does leave the department with a significant shortfall against the budgeted overheads. 21/05/25 email from James to Sally - do you think this will be resolved ahead of year-end? 21/05/25 email from Sally to James - We have asked for a response by 2 June but I should think this has some way to go. I will keep you posted. 16/07/25 still under investigation.
A94: European Commission | B94: 5367 | C94: 210147478 | D94: 45455 | E94: 45485 | F94: 46091 | G94: 606 | H94: 360+ days overdue | I94: EUR | J94: 361970.06 | K94: 0 | L94: 128421.32 | M94: 0 | N94: =IF(I94="GBP",L94-K94,O94-K94) -> 111310.46 | O94: 111310.46 | P94: BLR03450 | Q94: WhiteMech - 834228 | R94: Research | S94: Approved | T94: Computer Science | U94: De Giacomo, Prof Giuseppe | V94: d- Payment expected end of January 2026 | W94: 834228
A95: British Heart Foundation | B95: 7239 | C95: 210147510 | D95: 45456 | E95: 45486 | F95: 46091 | G95: 605 | H95: 360+ days overdue | I95: GBP | J95: 27347.67 | K95: 0 | L95: 27347.67 | M95: 0 | N95: =IF(I95="GBP",L95-K95,O95-K95) -> 27347.67 | O95: 27347.67 | P95: BWR01310 | Q95: Microvascular NPY | R95: Research | S95: Pending Close | T95: Pharmacology | U95: Dora, Prof Kim | V95: b- 24/10/24 email from Sara to Anna - yes – if you could raise credits notes associated with the invoices where the incorrect claims were made and new invoices that would be fine. 04/11/24 email from Anna to Sara - Thank you! I'm just looking over all the corrections and will send you the credit notes alongside the revised invoices by the end of today! 11/11/24 email from Anna - Need to correct multiple invoices as incorrectly categorised and send back to Funder for review. 18/12/24 email from Anna - with Funder in the process of being resolved. 08/01/25 email from Anna - query with funder waiting to be resolved. 13/02/25 email from Anna - waiting for Funder to respond to a query. 03/03/25 email to Anna - Can you let me know if there is any update regarding invoice 210147510 – BWR01310 on the attached. 06/03/25 email from Anna - There has been a lot of back and forth regarding this project as the invoices had been incorrectly coded. We are now in the process of trying to find the best way to rectify this with the Funder. 13/03/25 email from Anna - Working on with Funder. 09/06/25 Anna is still working on this. 08/07/25 email from Anna - AC working on. 21/08/25 email from Anna - working with Lewis on, will update soon, complex. 27/10/25 email to Anna - Re invoice 210147510 on the attached, is there any update on the status of the invoice. 27/10/25 email from Anna - I'm afraid not yet, I have asked a few people and they are unsure how to tackle this so me and James will be prioritising this ticket in the next 2 weeks. 13/11/2025 email from Anna - working with James to resolve by next week. | W95: PG/20/10260
A96: Wellcome Trust | B96: 7186 | C96: 210148112 | D96: 45474 | E96: 45504 | F96: 46091 | G96: 587 | H96: 360+ days overdue | I96: GBP | J96: 52595.66 | K96: 0 | L96: 18931.77 | M96: 0 | N96: =IF(I96="GBP",L96-K96,O96-K96) -> 18931.77 | O96: 18931.77 | P96: B9R04360 | Q96: Shigella Human Infection Study | R96: Research | S96: Approved | T96: Tropical Medicine | U96: Kapulu, Dr Melissa | V96: d- 04/02/2026 comment from Ciaran - On OSR Queries for this QTR, currently looking into | W96: 218528/Z/19/Z
A97: Wellcome Trust | B97: 7186 | C97: 210148216 | D97: 45474 | E97: 45504 | F97: 46091 | G97: 587 | H97: 360+ days overdue | I97: GBP | J97: 98757.97 | K97: 0 | L97: 3371.21 | M97: 0 | N97: =IF(I97="GBP",L97-K97,O97-K97) -> 3371.21 | O97: 3371.21 | P97: HBR03540 | Q97: A Simmons - WT Investigator | R97: Research | S97: Pending Close | T97: NDM Experimental Medicine | U97: Simmons, Prof Alison | V97: d- 27/02/2026 email from Oscar - FER was submitted 15/01/2026 | W97: 219523/Z/19/Z
A98: Santersus AG | B98: 98913 | C98: 210147977 | D98: 45474 | E98: 45504 | F98: 46091 | G98: 587 | H98: 360+ days overdue | I98: GBP | J98: 30074.26 | K98: 0 | L98: 30074.26 | M98: 0 | N98: =IF(I98="GBP",L98-K98,O98-K98) -> 30074.26 | O98: 30074.26 | P98: HJR02470 | Q98: Santersus ACLs | R98: Research | S98: Approved | T98: Surgical Sciences | U98: Friend, Prof Peter | V98: g- 15/07/25 email to Aleksander & finance - I’m being chased by our head of finance for an update on when next payments will be made have you an update. 23/07/25 email from Aleksander - As part of our regular updates, we wish to inform you that, due to the seasonal vacation period, finalizing the paperwork for the fundraising round has encountered a brief delay. This is purely procedural in nature and does not reflect any change in the intentions of the involved parties or in the agreed terms. All substantive matters have been successfully concluded, and our legal teams are diligently working to complete the formal documentation. Given the international nature of the parties involved, slight scheduling constraints may arise over the coming summer weeks. We sincerely appreciate your continued patience and understanding and remain committed to keeping you informed as we progress toward closure. 16/10/25 email to Alexsander - Thanks for your email below, can you let me know if there is any update? 19/10/25 email from Aleksander - Thank you for checking in. I was hoping to surprise you with some good news, but you beat me to it :) We're just about to wrap up our fundraising round, and we expect the first tranche to land in early November. Immediately afterward, we’ll begin normalizing our payment discipline. We're fully committed to getting things back on track as soon as possible. Thanks again for your patience and continued support. 01/12/2025 email to Aleksander - Thanks for your email, can you let me know if there is any update regarding your fundraising. payment of £10,000.00 on 30/12/2025 & 20/01/2026 & 10/02/2026 | W98: R81872
A99: Wellcome Trust | B99: 7186 | C99: 210148227 | D99: 45474 | E99: 45504 | F99: 46091 | G99: 587 | H99: 360+ days overdue | I99: GBP | J99: 79146.63 | K99: 0 | L99: 6727.59 | M99: 0 | N99: =IF(I99="GBP",L99-K99,O99-K99) -> 6727.59 | O99: 6727.59 | P99: HMR03020 | Q99: Xue WT CRCDF (Stage2) | R99: Research | S99: Approved | T99: Clinical Neurosciences | U99: Xue, Dr Kanmin | V99: b- 04/02/2026 comment from Ciaran - Ellie to confirm if FER has been submitted. 11/02/2026 email from Ellie - Asked dept Please can you provide an update on this as soon as possible? We do really need to draft the figures and leave ourselves time to work on the report. Final invoice still to be raised. | W99: 216593/Z/19/Z
A100: National Institute for Health Research | B100: 44423 | C100: 210149016 | D100: 45489 | E100: 45519 | F100: 46091 | G100: 572 | H100: 360+ days overdue | I100: GBP | J100: 49929.7 | K100: 0 | L100: 39934.61 | M100: 0 | N100: =IF(I100="GBP",L100-K100,O100-K100) -> 39934.61 | O100: 39934.61 | P100: HQR01630 | Q100: 16/159 | R100: Research | S100: Pending Close | T100: Psychiatry | U100: Fazel, Prof Seena | V100: d- 24/09/25 email from Justin (dept) to James B - I spoke with Lewis (now left the University) and thought this case had been closed, could you follow up with the Research Accounts grants team ? The final expenditure statement should have been submitted. 25/09/25 email from James B to Ops - @UAS Research Accounts Operations do we have any update on when the outstanding debt on HQR01630 will be paid by the funder? Apparently there should be no further queries on this and we are just waiting for payment, is this as we understand it? 30/09/25 email from James to Justin (dept) - Just picking this up as Lewis has left but FYI the Research Accounts contact for HQ will be Gareth Hemmings from tomorrow. As per a previous email (excerpt below), it appears that the final statement has been approved and the penultimate and final payments will be released once the project results are published. Could you confirm if there is a timescale for when this is expected to happen? 01/10/25 email from Justin to James - The NIHR asked for some final formatting changes to the report. I will let you know as soon as it is submitted. 01/10/25 email from Justin (dept) to James - Further to below, the PI just checked with NIHR – all our tasks are complete. The main report was uploaded in July and accepted. Will be published in a week or so. 09/02/2026 chase to academy awards. | W100: 16/159/09 - 537694 - PROFESSOR SEENA FAZEL
A101: Baylor College of Medicine | B101: 63167 | C101: 210149380 | D101: 45490 | E101: 45520 | F101: 46091 | G101: 571 | H101: 360+ days overdue | I101: USD | J101: 107612.89 | K101: 0 | L101: 107612.89 | M101: 0 | N101: =IF(I101="GBP",L101-K101,O101-K101) -> 76866.35 | O101: 76866.35 | P101: HMR04760 | Q101: NIH - Behrens | R101: Research | S101: Pending Close | T101: Clinical Neurosciences | U101: Behrens, Prof Timothy | V101: d- 21/01/2026 email to Rebecca (dept) - I think we should push back on this, the outstanding invoice has been outstanding for quiet a while and we were informed this had not been paid because of a PO number issue, two subsequent on the project were paid so there is no reason why this should not be paid, I’m guessing the agreement does not impose a timing deadline. 21/01/2026 email from Deirdre (dept) - I absolutely agree with you. I think that this is down to their mix up with PO numbers. We may have been slightly late with invoicing at the time but this was not raised as an issue when the invoice was submitted. I have attached the subaward agreement relating to this period. Please can the matter be pursued. If you need any further information, do let me know. Also, Gavin Brown is our contracts lead in RS and is familiar with these awards. 21/01/2026 email to Sameer Steth - Thanks for your email, with regards to invoice 210149380 the outstanding invoice has been outstanding for quite a while and we were informed this had not been paid because of a PO number issue, attached is the subaward agreement relating to this period, this was not raised as an issue when the invoice was submitted, two subsequent invoices on the project were paid copies of these are attached, can this be looked into again? 21/01/2026 email from Sameer - Looping in our research administration team. | W101: #P7000001166
...
